Workbook

Sheet Sales
A1: Store | B1: Date | C1: Net Sales | D1: Sales Tax | E1: Refunds | F1: Promo | G1: Discounts | H1: Paid Out | I1: Gift Card Redeemed | J1: Gift Cards Sold | K1: Mobile CC | L1: Mastercard | M1: Visa | N1: Discover | O1: Amex | P1: Debit | Q1: Cash +/- | R1: Deletion $ | S1: Transaction Count | T1: Deposit 1 | U1: Deposit 2 | V1: Deposit 3 | W1: Register Sales | X1: Gross Sales | Y1: Paid Out | Z1: Acct Cash | AA1: Prior Year Net Sales | AB1: Hourly Labor Hours | AC1: Hourly Labor Dollars | AD1: Salaried Labor Hours | AE1: Salaried Labor Dollars | AF1: McLane Orders | AG1: GH Delivery Total | AH1: GH Mobile Total | AI1: Register Sales with donations | AJ1: Grub Hub Payments | AK1: Uber Sales | AL1: Uber Payments | AM1: DoorDash Net Sales | AN1: DoorDash Markup | AO1: DoorDash Payment | AP1: Donation | AQ1: Credit Card Other | AR1: TB Mobile App
A2: 37014 | B2: 05/26/2026 | C2: 4072.64 | D2: 335.96 | E2: 0 | F2: 0 | G2: 71.64 | H2: 0 | I2: -15.89 | J2: 0 | K2: -745.42 | L2: 422.04 | M2: 2679.96 | N2: 81.73 | O2: 45.3 | Q2: -1.5 | R2: 168.32 | S2: 288 | T2: 1168 | U2: 0 | V2: 0 | W2: 4486.06 | X2: 4129.98 | Y2: 0 | Z2: 1169.5 | AA2: 3500.78 | AB2: 56.49 | AC2: 1168.71 | AD2: 0 | AE2: 0 | AF2: 0 | AG2: 0 | AH2: 0 | AI2: 0 | AJ2: 0 | AK2: 0 | AL2: 0 | AM2: 0 | AN2: 0 | AO2: 0 | AP2: 5.82 | AQ2: 0 | AR2: 703.28
A3: 37171 | B3: 05/26/2026 | C3: 3325.13 | D3: 290.26 | E3: 11.98 | F3: 0 | G3: 95.02 | H3: 0 | I3: -15 | J3: 0 | K3: -546.09 | L3: 409.77 | M3: 1857.32 | N3: 27.95 | O3: 5.97 | Q3: -0.79 | R3: 165.29 | S3: 254 | T3: 1055 | U3: 0 | V3: 0 | W3: 3724.15 | X3: 3420.83 | Y3: 0 | Z3: 1055.79 | AA3: 3685.61 | AB3: 59.01 | AC3: 1266.58 | AD3: 0 | AE3: 0 | AF3: 0 | AG3: 0 | AH3: 0 | AI3: 0 | AJ3: 0 | AK3: 91.49 | AL3: 91.49 | AM3: 126.81 | AN3: 25.36 | AO3: 165.84 | AP3: 13.74 | AQ3: 0 | AR3: 501.19
A4: 36224 | B4: 05/26/2026 | C4: 5130.87 | D4: 410.72 | E4: 0 | F4: 0 | G4: 142.86 | H4: 0 | I4: -16.12 | J4: 10 | K4: -1310.06 | L4: 590.68 | M4: 3467.34 | N4: 56.43 | O4: 70.05 | Q4: -38.85 | R4: 374.23 | S4: 350 | T4: 648.61 | U4: 0 | V4: 0 | W4: 5703.31 | X4: 5282.59 | Y4: 0 | Z4: 687.46 | AA4: 5340.52 | AB4: 74.03 | AC4: 1529.2 | AD4: 0 | AE4: 0 | AF4: 3385.71 | AG4: 46.58 | AH4: 0 | AI4: 0 | AJ4: 50.37 | AK4: 56.33 | AL4: 56.33 | AM4: 435.98 | AN4: 87.2 | AO4: 565.67 | AP4: 8.86 | AQ4: 0 | AR4: 1211.69
A5: 30256 | B5: 05/26/2026 | C5: 5789.49 | D5: 463.5 | E5: 0 | F5: 0 | G5: 124.31 | H5: 0 | I5: 0 | J5: 0 | K5: -1104.26 | L5: 554.59 | M5: 3764.02 | N5: 78.72 | O5: 199.38 | Q5: -2 | R5: 193.31 | S5: 411 | T5: 1076 | U5: 0 | V5: 0 | W5: 6393.73 | X5: 5930.23 | Y5: 0 | Z5: 1078 | AA5: 4756.32 | AB5: 71.79 | AC5: 1482.66 | AD5: 0 | AE5: 0 | AF5: 0 | AG5: 0 | AH5: 0 | AI5: 0 | AJ5: 0 | AK5: 52.28 | AL5: 52.28 | AM5: 418.05 | AN5: 83.61 | AO5: 542.43 | AP5: 16.43 | AQ5: 0 | AR5: 1021.27
A6: 40404 | B6: 05/26/2026 | C6: 6086.02 | D6: 0 | E6: 0 | F6: 5.58 | G6: 272.95 | H6: 0 | I6: -18.56 | J6: 0 | K6: -832.76 | L6: 653.31 | M6: 3578.68 | N6: 73.08 | O6: 78.98 | Q6: -7.36 | R6: 625.77 | S6: 434 | T6: 966 | U6: 0 | V6: 0 | W6: 6376.99 | X6: 6367.22 | Y6: 0 | Z6: 973.36 | AA6: 0 | AB6: 94.52 | AC6: 1706.57 | AD6: 0 | AE6: 0 | AF6: 0 | AG6: 37.25 | AH6: 0 | AI6: 0 | AJ6: 37.25 | AK6: 272.1 | AL6: 272.1 | AM6: 344.28 | AN6: 68.86 | AO6: 413.14 | AP6: 12.44 | AQ6: 0 | AR6: 829.77
A7: 29423 | B7: 05/26/2026 | C7: 4437.27 | D7: 364.8 | E7: 0 | F7: 0 | G7: 70.6 | H7: 0 | I7: 0 | J7: 0 | K7: -912.83 | L7: 972.45 | M7: 2380.77 | N7: 88.26 | O7: 62.52 | Q7: -637.5 | R7: 119.9 | S7: 308 | T7: 535 | U7: 0 | V7: 0 | W7: 4886.47 | X7: 4521.67 | Y7: 0 | Z7: 1172.5 | AA7: 4261.18 | AB7: 54.56 | AC7: 1178.7 | AD7: 0 | AE7: 0 | AF7: 0 | AG7: 0 | AH7: 0 | AI7: 0 | AJ7: 0 | AK7: 16.75 | AL7: 16.75 | AM7: 94.39 | AN7: 18.88 | AO7: 122.62 | AP7: 13.8 | AQ7: 0 | AR7: 829.54
A8: 33444 | B8: 05/26/2026 | C8: 2589.59 | D8: 187.74 | E8: 0 | F8: 0 | G8: 65.95 | H8: 0 | I8: 0 | J8: 0 | K8: -300.61 | L8: 313.73 | M8: 1845.18 | N8: 43.36 | O8: 0 | Q8: -0.51 | R8: 107.2 | S8: 188 | T8: 582 | U8: 0 | V8: 0 | W8: 2850.73 | X8: 2662.99 | Y8: 0 | Z8: 582.51 | AA8: 2631.94 | AB8: 46.07 | AC8: 962.12 | AD8: 0 | AE8: 0 | AF8: 0 | AG8: 0 | AH8: 0 | AI8: 0 | AJ8: 0 | AK8: 0 | AL8: 0 | AM8: 0 | AN8: 0 | AO8: 0 | AP8: 7.45 | AQ8: 0 | AR8: 269.01
A9: 30491 | B9: 05/26/2026 | C9: 4455.23 | D9: 389.13 | E9: 0 | F9: 0 | G9: 201.65 | H9: 0 | I9: -36.6 | J9: 0 | K9: -821.47 | L9: 764.83 | M9: 2864.73 | N9: 38.95 | O9: 186.03 | Q9: -1.15 | R9: 145.04 | S9: 333 | T9: 893 | U9: 0 | V9: 0 | W9: 5074.21 | X9: 4685.08 | Y9: 0 | Z9: 894.15 | AA9: 4015.69 | AB9: 57.44 | AC9: 1281.61 | AD9: 0 | AE9: 0 | AF9: 0 | AG9: 0 | AH9: 0 | AI9: 0 | AJ9: 0 | AK9: 0 | AL9: 0 | AM9: 66.88 | AN9: 13.38 | AO9: 87.27 | AP9: 28.2 | AQ9: 0 | AR9: 764.47
A10: 32680 | B10: 05/26/2026 | C10: 5087.01 | D10: 418.82 | E10: 10.88 | F10: 3.69 | G10: 199.74 | H10: 0 | I10: 0 | J10: 0 | K10: -608.27 | L10: 434.24 | M10: 3142.82 | N10: 81.92 | O10: 9.3 | Q10: -1.88 | R10: 293.47 | S10: 378 | T10: 1432 | U10: 0 | V10: 0 | W10: 5734.78 | X10: 5304.18 | Y10: 0 | Z10: 1433.88 | AA10: 5860.16 | AB10: 87.04 | AC10: 1833.76 | AD10: 0 | AE10: 0 | AF10: 0 | AG10: 0 | AH10: 0 | AI10: 0 | AJ10: 0 | AK10: 10.98 | AL10: 10.98 | AM10: 321.93 | AN10: 64.39 | AO10: 418.21 | AP10: 25.52 | AQ10: 0 | AR10: 561.97
A11: 37718 | B11: 05/26/2026 | C11: 3799.11 | D11: 0 | E11: 1.79 | F11: 0 | G11: 99.02 | H11: 0 | I11: -5.38 | J11: 0 | K11: -520.66 | L11: 717.12 | M11: 2220.89 | N11: 0 | O11: 58.3 | Q11: 4.97 | R11: 68.78 | S11: 271 | T11: 602 | U11: 0 | V11: 0 | W11: 3899.44 | X11: 3872.42 | Y11: 0 | Z11: 597.03 | AA11: 3223.9 | AB11: 69.17 | AC11: 1248.42 | AD11: 0 | AE11: 0 | AF11: 5090.79 | AG11: 0 | AH11: 0 | AI11: 0 | AJ11: 0 | AK11: 12.43 | AL11: 12.43 | AM11: 157.73 | AN11: 31.55 | AO11: 189.27 | AP11: 1.31 | AQ11: 0 | AR11: 496.19
A12: 37732 | B12: 05/26/2026 | C12: 5233.61 | D12: 433.88 | E12: 0 | F12: 0 | G12: 176.73 | H12: 0 | I12: -20.29 | J12: 0 | K12: -1088.86 | L12: 668.14 | M12: 3059.33 | N12: 166.27 | O12: 217.7 | Q12: -0.01 | R12: 197.24 | S12: 374 | T12: 715 | U12: 0 | V12: 0 | W12: 5856.19 | X12: 5422.31 | Y12: 0 | Z12: 715.01 | AA12: 0 | AB12: 84.5 | AC12: 1772.82 | AD12: 0 | AE12: 0 | AF12: 0 | AG12: 17.66 | AH12: 0 | AI12: 0 | AJ12: 19.14 | AK12: 51.33 | AL12: 51.33 | AM12: 586.39 | AN12: 117.28 | AO12: 762.25 | AP12: 11.97 | AQ12: 0 | AR12: 1011.68
A13: 34793 | B13: 05/26/2026 | C13: 4329.39 | D13: 382.34 | E13: 5.99 | F13: 3.19 | G13: 133.87 | H13: 0 | I13: -14.66 | J13: 15 | K13: -985.78 | L13: 466.51 | M13: 3096.72 | N13: 85.72 | O13: 76.05 | Q13: -1.71 | R13: 216.79 | S13: 337 | T13: 896 | U13: 0 | V13: 0 | W13: 4893.13 | X13: 4489.26 | Y13: 0 | Z13: 897.71 | AA13: 4775.38 | AB13: 63.23 | AC13: 1447.43 | AD13: 0 | AE13: 0 | AF13: 0 | AG13: 0 | AH13: 0 | AI13: 0 | AJ13: 0 | AK13: 69.75 | AL13: 69.75 | AM13: 37.44 | AN13: 7.49 | AO13: 48.95 | AP13: 29.34 | AQ13: 0 | AR13: 918.04
... A40: 32952 | B40: 05/26/2026 | C40: 5845.93 | D40: 440.07 | E40: 32.49 | F40: 25.62 | G40: 127.55 | H40: 0 | I40: -13.02 | J40: 0 | K40: -1070.62 | L40: 489.47 | M40: 4366.8 | N40: 148.38 | O40: 96.16 | Q40: 0.23 | R40: 208.98 | S40: 441 | T40: 920 | U40: 0 | V40: 0 | W40: 6461.36 | X40: 5970.84 | Y40: 0 | Z40: 919.77 | AA40: 6749.88 | AB40: 97.49 | AC40: 1959.82 | AD40: 0 | AE40: 0 | AF40: 0 | AG40: 0 | AH40: 0 | AI40: 0 | AJ40: 0 | AK40: 58.86 | AL40: 58.86 | AM40: 179.78 | AN40: 35.96 | AO40: 215.73 | AP40: 22.19 | AQ40: 0 | AR40: 998.3

Sheet EBT AMOUNTS
A1: Product Code | B1: Site ID (BE) | C1: Funded Date | D1: Site Alternate ID | E1: Site Name | F1: Major Category | G1: Processed Currency | H1: Transaction Count | I1: Processed Transaction Amount | L1: LOCATION
A2: ElectronicBenefitsTransfer | B2: 498467401887 | C2: 46169 | E2: TACO BELL #28843 | F2: Deposits | G2: USD | H2: 2 | I2: 20.44 | L2: =RIGHT(E2,5) -> 28843
A3: ElectronicBenefitsTransfer | B3: 498474176886 | C3: 46169 | E3: TACO BELL #28844 | F3: Deposits | G3: USD | H3: 2 | I3: 15.28 | L3: =RIGHT(E3,5) -> 28844
A4: ElectronicBenefitsTransfer | B4: 498467386880 | C4: 46169 | E4: TACO BELL #30256 | F4: Deposits | G4: USD | H4: 2 | I4: 34.04 | L4: =RIGHT(E4,5) -> 30256
A5: ElectronicBenefitsTransfer | B5: 498467397887 | C5: 46169 | E5: TACO BELL #30491 | F5: Deposits | G5: USD | H5: 1 | I5: 7.58 | L5: =RIGHT(E5,5) -> 30491
A6: ElectronicBenefitsTransfer | B6: 498474172885 | C6: 46169 | E6: TACO BELL #28841 | F6: Deposits | G6: USD | H6: 1 | I6: 49.28 | L6: =RIGHT(E6,5) -> 28841
A7: ElectronicBenefitsTransfer | B7: 498467400889 | C7: 46169 | E7: TACO BELL #28845 | F7: Deposits | G7: USD | H7: 3 | I7: 30.24 | L7: =RIGHT(E7,5) -> 28845
A8: ElectronicBenefitsTransfer | B8: 498467398885 | C8: 46169 | E8: TACO BELL #36224 | F8: Deposits | G8: USD | H8: 2 | I8: 20.15 | L8: =RIGHT(E8,5) -> 36224
A9: ElectronicBenefitsTransfer | B9: 498474173883 | C9: 46169 | E9: TACO BELL #28846 | F9: Deposits | G9: USD | H9: 8 | I9: 108.77 | L9: =RIGHT(E9,5) -> 28846
A13: Sales Day
A14: ='Daily Sales Taco Bell 03-14 202'!B2 -> 05/26/2026
A17: {=_xlfn.LET( _xlpm.data,_xlfn._xlws.FILTER( 'Daily Sales Taco Bell RED'!D:K, ((('Daily Sales Taco Bell RED'!I:I<>0)+('Daily Sales Taco Bell RED'!J:J<>0))* ISNUMBER(MATCH('Daily Sales Taco Bell RED'!H:H,{28841,28843,28844,28845,28846,30256,30491,36224},0))* (('Daily Sales Taco Bell RED'!E:E="Cash Expected Deposit")+('Daily Sales Taco Bell RED'!E:E="EBT Expected Deposit"))) ), _xlpm.memoCol,INDEX(_xlpm.data,,2), _xlpm.locCol,INDEX(_xlpm.data,,5), _xlpm.sortGroup, IF(_xlpm.memoCol="Cash Expected Deposit",1, IF(_xlpm.memoCol="EBT Expected Deposit",2,0)), _xlpm.sorted,_xlfn.SORTBY(_xlpm.data,_xlpm.sortGroup,1,_xlpm.locCol,1), _xlfn.HSTACK( INDEX(_xlpm.sorted,,1), INDEX(_xlpm.sorted,,2), IF(INDEX(_xlpm.sorted,,3)=0,"",INDEX(_xlpm.sorted,,3)), INDEX(_xlpm.sorted,,4), INDEX(_xlpm.sorted,,5), IF(INDEX(_xlpm.sorted,,6)=0,"",INDEX(_xlpm.sorted,,6)), IF(INDEX(_xlpm.sorted,,7)=0,"",INDEX(_xlpm.sorted,,7)), IF(INDEX(_xlpm.sorted,,8)=0,"",INDEX(_xlpm.sorted,,8)) ) )} -> POS Data Upload Sabretooth | B17: Cash Expected Deposit | D17: 101900 | E17: 28841 | F17: 972.28
A18: POS Data Upload Sabretooth | B18: Cash Expected Deposit | D18: 101900 | E18: 28843 | F18: 1153.01
A19: POS Data Upload Sabretooth | B19: Cash Expected Deposit | D19: 101900 | E19: 28844 | F19: 2627.77
A20: POS Data Upload Sabretooth | B20: Cash Expected Deposit | D20: 101900 | E20: 28845 | F20: 1159.12
A21: POS Data Upload Sabretooth | B21: Cash Expected Deposit | D21: 101900 | E21: 28846 | F21: 1491.03
A22: POS Data Upload Sabretooth | B22: Cash Expected Deposit | D22: 101900 | E22: 30256 | F22: 1043.96
A23: POS Data Upload Sabretooth | B23: Cash Expected Deposit | D23: 101900 | E23: 30491 | F23: 886.57
A24: POS Data Upload Sabretooth | B24: Cash Expected Deposit | D24: 101900 | E24: 36224 | F24: 667.31
A25: POS Data Upload Sabretooth | B25: EBT Expected Deposit | D25: 111200 | E25: 28841 | F25: 49.28
A26: POS Data Upload Sabretooth | B26: EBT Expected Deposit | D26: 111200 | E26: 28843 | F26: 20.44
A27: POS Data Upload Sabretooth | B27: EBT Expected Deposit | D27: 111200 | E27: 28844 | F27: 15.28
A28: POS Data Upload Sabretooth | B28: EBT Expected Deposit | D28: 111200 | E28: 28845 | F28: 30.24
A29: POS Data Upload Sabretooth | B29: EBT Expected Deposit | D29: 111200 | E29: 28846 | F29: 108.77
... A32: POS Data Upload Sabretooth | B32: EBT Expected Deposit | D32: 111200 | E32: 36224 | F32: 20.15

Sheet Conciliation
A1: Store | C1: Sales TAX | D1: Gross Sales POS | E1: Discounts | F1: Promo | G1: Donations | H1: Net Sales | I1: Sales TAX | J1: GC Sold | K1: Paid Out | L1: Paid In | M1: Donation | N1: Total Revenue | O1: Mastercard | P1: Visa | Q1: Discover | R1: Amex | S1: Debit | U1: EBT | V1: GC Redeem | W1: Acct Cash | X1: Deposits | Y1: GH | Z1: Uber | AA1: DD | AB1: CC Totals | AC1: Payments Total | AD1: O/S | AE1: OS | AH1: Deposit 1 | AI1: Deposit 2 | AJ1: Deposit 3 | AK1: Cash +/- | AL1: Cash Expected | AM1: Difference
A2: 28841 | C2: =_xlfn.XLOOKUP($A2,Sales!$A:$A,Sales!$D:$D,"0") -> 392.96 | D2: =SUM(H2+F2+E2-Z2,"0") -> 5040.05 | E2: =_xlfn.XLOOKUP($A2,Sales!$A:$A,Sales!$G:$G,"0") -> 151.86 | F2: =_xlfn.XLOOKUP($A2,Sales!$A:$A,Sales!$F:$F,"0") -> 3.19 | G2: =_xlfn.XLOOKUP($A2,Sales!$A:$A,Sales!$AP:$AP,"0") -> 21.59 | H2: =_xlfn.XLOOKUP($A2,Sales!$A:$A,Sales!$C:$C,"0") -> 4931.78 | I2: =C2 -> 392.96 | J2: =_xlfn.XLOOKUP($A2,Sales!$A:$A,Sales!$J:$J,"0") -> 15 | K2: =_xlfn.XLOOKUP($A2,Sales!$A:$A,Sales!$H:$H,"0") -> 28.9 | L2: 0 | M2: =_xlfn.XLOOKUP($A2,Sales!$A:$A,Sales!$AP:$AP,"0") -> 21.59 | N2: =H2+I2+J2+M2+L2-K2 -> 5332.43 | O2: =_xlfn.XLOOKUP($A2,Sales!$A:$A,Sales!$L:$L,"0") -> 509.08 | P2: =_xlfn.XLOOKUP($A2,Sales!$A:$A,Sales!$M:$M,"0") -> 2813.72 | Q2: =_xlfn.XLOOKUP($A2,Sales!$A:$A,Sales!$N:$N,"0") -> 109.1 | R2: =_xlfn.XLOOKUP($A2,Sales!$A:$A,Sales!$O:$O,"0") -> 120.76 | S2: =_xlfn.XLOOKUP($A2,Sales!$A:$A,Sales!$P:$P,"0") -> 0 | U2: =SUMIFS('EBT AMOUNTS'!I:I,'EBT AMOUNTS'!L:L,Conciliation!A2) -> 49.28 | V2: =_xlfn.XLOOKUP($A2,Sales!$A:$A,Sales!$I:$I,"0")*-1 -> 5.1 | W2: =_xlfn.XLOOKUP($A2,Sales!$A:$A,Sales!$Z:$Z,"0")-K2-U2 -> 972.28 | X2: {=_xlfn.XLOOKUP($A2,Sales!$A:$A,Sales!$T:$T+Sales!$U:$U+Sales!$V:$V,"0")} -> 1021 | Y2: =_xlfn.XLOOKUP($A2,Sales!$A:$A,Sales!$AJ:$AJ,"0") -> 0 | Z2: =_xlfn.XLOOKUP($A2,Sales!$A:$A,Sales!$AL:$AL,"0") -> 46.78 | AA2: =_xlfn.XLOOKUP($A2,Sales!$A:$A,Sales!$AO:$AO,"0") -> 706.33 | AB2: =O2+P2+Q2+S2 -> 3431.9 | AC2: =O2+P2+Q2+R2+S2+V2+W2+Y2+Z2+AA2+U2 -> 5332.43 | AD2: =N2-AC2 -> 0 | AE2: =_xlfn.XLOOKUP($A2,Sales!$A:$A,Sales!$Q:$Q,"0") -> -0.56 | AG2: 28841 | AH2: =VLOOKUP(AG2,Sales!A:V,20,FALSE) -> 1021 | AI2: =VLOOKUP(AG2,Sales!A:U,21,FALSE) -> 0 | AJ2: =VLOOKUP(AG2,Sales!A:V,22,FALSE) -> 0 | AK2: =VLOOKUP(AG2,Sales!A:Q,17,FALSE) -> -0.56 | AL2: =SUMIF(A:A,AG2,W:W) -> 972.28 | AM2: =AL2-(AH2+AI2+AJ2)+AK2+U2 -> 8.5265128e-14
A3: 28842 | C3: =_xlfn.XLOOKUP($A3,Sales!$A:$A,Sales!$D:$D,"0") -> 567.13 | D3: =SUM(H3+F3+E3-Z3,"0") -> 6973.73 | E3: =_xlfn.XLOOKUP($A3,Sales!$A:$A,Sales!$G:$G,"0") -> 202.13 | F3: =_xlfn.XLOOKUP($A3,Sales!$A:$A,Sales!$F:$F,"0") -> 0 | G3: =_xlfn.XLOOKUP($A3,Sales!$A:$A,Sales!$AP:$AP,"0") -> 37.8 | H3: =_xlfn.XLOOKUP($A3,Sales!$A:$A,Sales!$C:$C,"0") -> 6909.03 | I3: =C3 -> 567.13 | J3: =_xlfn.XLOOKUP($A3,Sales!$A:$A,Sales!$J:$J,"0") -> 0 | K3: =_xlfn.XLOOKUP($A3,Sales!$A:$A,Sales!$H:$H,"0") -> 0 | L3: 0 | M3: =_xlfn.XLOOKUP($A3,Sales!$A:$A,Sales!$AP:$AP,"0") -> 37.8 | N3: =H3+I3+J3+M3+L3-K3 -> 7513.96 | O3: =_xlfn.XLOOKUP($A3,Sales!$A:$A,Sales!$L:$L,"0") -> 938.73 | P3: =_xlfn.XLOOKUP($A3,Sales!$A:$A,Sales!$M:$M,"0") -> 4277.42 | Q3: =_xlfn.XLOOKUP($A3,Sales!$A:$A,Sales!$N:$N,"0") -> 108.37 | R3: =_xlfn.XLOOKUP($A3,Sales!$A:$A,Sales!$O:$O,"0") -> 113.84 | S3: =_xlfn.XLOOKUP($A3,Sales!$A:$A,Sales!$P:$P,"0") -> 0 | V3: =_xlfn.XLOOKUP($A3,Sales!$A:$A,Sales!$I:$I,"0")*-1 -> 9.4 | W3: =_xlfn.XLOOKUP($A3,Sales!$A:$A,Sales!$Z:$Z,"0")-K3-U3 -> 1108.08 | X3: {=_xlfn.XLOOKUP($A3,Sales!$A:$A,Sales!$T:$T+Sales!$U:$U+Sales!$V:$V,"0")-K3} -> 1107 | Y3: =_xlfn.XLOOKUP($A3,Sales!$A:$A,Sales!$AJ:$AJ,"0") -> 0 | Z3: =_xlfn.XLOOKUP($A3,Sales!$A:$A,Sales!$AL:$AL,"0") -> 137.43 | AA3: =_xlfn.XLOOKUP($A3,Sales!$A:$A,Sales!$AO:$AO,"0") -> 820.69 | AB3: =O3+P3+Q3+S3 -> 5324.52 | AC3: =O3+P3+Q3+R3+S3+V3+W3+Y3+Z3+AA3+U3 -> 7513.96 | AD3: =N3-AC3 -> 0 | AE3: =_xlfn.XLOOKUP($A3,Sales!$A:$A,Sales!$Q:$Q,"0") -> -1.08 | AG3: 28842 | AH3: =VLOOKUP(AG3,Sales!A:V,20,FALSE) -> 1107 | AI3: =VLOOKUP(AG3,Sales!A:U,21,FALSE) -> 0 | AJ3: =VLOOKUP(AG3,Sales!A:V,22,FALSE) -> 0 | AK3: =VLOOKUP(AG3,Sales!A:Q,17,FALSE) -> -1.08 | AL3: =SUMIF(A:A,AG3,W:W) -> 1108.08 | AM3: =AL3-(AH3+AI3+AJ3)+AK3 -> -7.283063e-14
A4: 28843 | C4: =_xlfn.XLOOKUP($A4,Sales!$A:$A,Sales!$D:$D,"0") -> 482.66 | D4: =SUM(H4+F4+E4-Z4,"0") -> 5473.4 | E4: =_xlfn.XLOOKUP($A4,Sales!$A:$A,Sales!$G:$G,"0") -> 164.27 | F4: =_xlfn.XLOOKUP($A4,Sales!$A:$A,Sales!$F:$F,"0") -> 0 | G4: =_xlfn.XLOOKUP($A4,Sales!$A:$A,Sales!$AP:$AP,"0") -> 22.89 | H4: =_xlfn.XLOOKUP($A4,Sales!$A:$A,Sales!$C:$C,"0") -> 5394.89 | I4: =C4 -> 482.66 | J4: =_xlfn.XLOOKUP($A4,Sales!$A:$A,Sales!$J:$J,"0") -> 0 | K4: =_xlfn.XLOOKUP($A4,Sales!$A:$A,Sales!$H:$H,"0") -> 0 | L4: 0 | M4: =_xlfn.XLOOKUP($A4,Sales!$A:$A,Sales!$AP:$AP,"0") -> 22.89 | N4: =H4+I4+J4+M4+L4-K4 -> 5900.44 | O4: =_xlfn.XLOOKUP($A4,Sales!$A:$A,Sales!$L:$L,"0") -> 467.17 | P4: =_xlfn.XLOOKUP($A4,Sales!$A:$A,Sales!$M:$M,"0") -> 3305.78 | Q4: =_xlfn.XLOOKUP($A4,Sales!$A:$A,Sales!$N:$N,"0") -> 36.84 | R4: =_xlfn.XLOOKUP($A4,Sales!$A:$A,Sales!$O:$O,"0") -> 131.52 | S4: =_xlfn.XLOOKUP($A4,Sales!$A:$A,Sales!$P:$P,"0") -> 0 | U4: =SUMIFS('EBT AMOUNTS'!I:I,'EBT AMOUNTS'!L:L,Conciliation!A4) -> 20.44 | V4: =_xlfn.XLOOKUP($A4,Sales!$A:$A,Sales!$I:$I,"0")*-1 -> 0 | W4: =_xlfn.XLOOKUP($A4,Sales!$A:$A,Sales!$Z:$Z,"0")-K4-U4 -> 1153.01 | X4: {=_xlfn.XLOOKUP($A4,Sales!$A:$A,Sales!$T:$T+Sales!$U:$U+Sales!$V:$V,"0")-K4} -> 1170 | Y4: =_xlfn.XLOOKUP($A4,Sales!$A:$A,Sales!$AJ:$AJ,"0") -> 27.42 | Z4: =_xlfn.XLOOKUP($A4,Sales!$A:$A,Sales!$AL:$AL,"0") -> 85.76 | AA4: =_xlfn.XLOOKUP($A4,Sales!$A:$A,Sales!$AO:$AO,"0") -> 672.5 | AB4: =O4+P4+Q4+S4 -> 3809.79 | AC4: =O4+P4+Q4+R4+S4+V4+W4+Y4+Z4+AA4+U4 -> 5900.44 | AD4: =N4-AC4 -> 0 | AE4: =_xlfn.XLOOKUP($A4,Sales!$A:$A,Sales!$Q:$Q,"0") -> -3.45 | AG4: 28843 | AH4: =VLOOKUP(AG4,Sales!A:V,20,FALSE) -> 1170 | AI4: =VLOOKUP(AG4,Sales!A:U,21,FALSE) -> 0 | AJ4: =VLOOKUP(AG4,Sales!A:V,22,FALSE) -> 0 | AK4: =VLOOKUP(AG4,Sales!A:Q,17,FALSE) -> -3.45 | AL4: =SUMIF(A:A,AG4,W:W) -> 1153.01 | AM4: =AL4-(AH4+AI4+AJ4)+AK4+U4 -> 0
A5: 28844 | C5: =_xlfn.XLOOKUP($A5,Sales!$A:$A,Sales!$D:$D,"0") -> 794.81 | D5: =SUM(H5+F5+E5-Z5,"0") -> 10252.94 | E5: =_xlfn.XLOOKUP($A5,Sales!$A:$A,Sales!$G:$G,"0") -> 315.18 | F5: =_xlfn.XLOOKUP($A5,Sales!$A:$A,Sales!$F:$F,"0") -> 0 | G5: =_xlfn.XLOOKUP($A5,Sales!$A:$A,Sales!$AP:$AP,"0") -> 34.64 | H5: =_xlfn.XLOOKUP($A5,Sales!$A:$A,Sales!$C:$C,"0") -> 10050.16 | I5: =C5 -> 794.81 | J5: =_xlfn.XLOOKUP($A5,Sales!$A:$A,Sales!$J:$J,"0") -> 0 | K5: =_xlfn.XLOOKUP($A5,Sales!$A:$A,Sales!$H:$H,"0") -> 0 | L5: 0 | M5: =_xlfn.XLOOKUP($A5,Sales!$A:$A,Sales!$AP:$AP,"0") -> 34.64 | N5: =H5+I5+J5+M5+L5-K5 -> 10879.61 | O5: =_xlfn.XLOOKUP($A5,Sales!$A:$A,Sales!$L:$L,"0") -> 1094.69 | P5: =_xlfn.XLOOKUP($A5,Sales!$A:$A,Sales!$M:$M,"0") -> 5676.43 | Q5: =_xlfn.XLOOKUP($A5,Sales!$A:$A,Sales!$N:$N,"0") -> 218.19 | R5: =_xlfn.XLOOKUP($A5,Sales!$A:$A,Sales!$O:$O,"0") -> 38.59 | S5: =_xlfn.XLOOKUP($A5,Sales!$A:$A,Sales!$P:$P,"0") -> 0 | U5: =SUMIFS('EBT AMOUNTS'!I:I,'EBT AMOUNTS'!L:L,Conciliation!A5) -> 15.28 | V5: =_xlfn.XLOOKUP($A5,Sales!$A:$A,Sales!$I:$I,"0")*-1 -> 39.25 | W5: =_xlfn.XLOOKUP($A5,Sales!$A:$A,Sales!$Z:$Z,"0")-K5-U5 -> 2627.77 | X5: {=_xlfn.XLOOKUP($A5,Sales!$A:$A,Sales!$T:$T+Sales!$U:$U+Sales!$V:$V,"0")-K5} -> 2642.57 | Y5: =_xlfn.XLOOKUP($A5,Sales!$A:$A,Sales!$AJ:$AJ,"0") -> 0 | Z5: =_xlfn.XLOOKUP($A5,Sales!$A:$A,Sales!$AL:$AL,"0") -> 112.4 | AA5: =_xlfn.XLOOKUP($A5,Sales!$A:$A,Sales!$AO:$AO,"0") -> 1057.01 | AB5: =O5+P5+Q5+S5 -> 6989.31 | AC5: =O5+P5+Q5+R5+S5+V5+W5+Y5+Z5+AA5+U5 -> 10879.61 | AD5: =N5-AC5 -> 0 | AE5: =_xlfn.XLOOKUP($A5,Sales!$A:$A,Sales!$Q:$Q,"0") -> -0.48 | AG5: 28844 | AH5: =VLOOKUP(AG5,Sales!A:V,20,FALSE) -> 2642.57 | AI5: =VLOOKUP(AG5,Sales!A:U,21,FALSE) -> 0 | AJ5: =VLOOKUP(AG5,Sales!A:V,22,FALSE) -> 0 | AK5: =VLOOKUP(AG5,Sales!A:Q,17,FALSE) -> -0.48 | AL5: =SUMIF(A:A,AG5,W:W) -> 2627.77 | AM5: =AL5-(AH5+AI5+AJ5)+AK5+U5 -> -1.8296475e-13
A6: 28845 | C6: =_xlfn.XLOOKUP($A6,Sales!$A:$A,Sales!$D:$D,"0") -> 776.16 | D6: =SUM(H6+F6+E6-Z6,"0") -> 9879.26 | E6: =_xlfn.XLOOKUP($A6,Sales!$A:$A,Sales!$G:$G,"0") -> 298.4 | F6: =_xlfn.XLOOKUP($A6,Sales!$A:$A,Sales!$F:$F,"0") -> 0 | G6: =_xlfn.XLOOKUP($A6,Sales!$A:$A,Sales!$AP:$AP,"0") -> 24.73 | H6: =_xlfn.XLOOKUP($A6,Sales!$A:$A,Sales!$C:$C,"0") -> 9685.93 | I6: =C6 -> 776.16 | J6: =_xlfn.XLOOKUP($A6,Sales!$A:$A,Sales!$J:$J,"0") -> 10 | K6: =_xlfn.XLOOKUP($A6,Sales!$A:$A,Sales!$H:$H,"0") -> 0 | L6: 0 | M6: =_xlfn.XLOOKUP($A6,Sales!$A:$A,Sales!$AP:$AP,"0") -> 24.73 | N6: =H6+I6+J6+M6+L6-K6 -> 10496.82 | O6: =_xlfn.XLOOKUP($A6,Sales!$A:$A,Sales!$L:$L,"0") -> 1040.72 | P6: =_xlfn.XLOOKUP($A6,Sales!$A:$A,Sales!$M:$M,"0") -> 5844.26 | Q6: =_xlfn.XLOOKUP($A6,Sales!$A:$A,Sales!$N:$N,"0") -> 147.04 | R6: =_xlfn.XLOOKUP($A6,Sales!$A:$A,Sales!$O:$O,"0") -> 349.48 | S6: =_xlfn.XLOOKUP($A6,Sales!$A:$A,Sales!$P:$P,"0") -> 0 | U6: =SUMIFS('EBT AMOUNTS'!I:I,'EBT AMOUNTS'!L:L,Conciliation!A6) -> 30.24 | V6: =_xlfn.XLOOKUP($A6,Sales!$A:$A,Sales!$I:$I,"0")*-1 -> 26.25 | W6: =_xlfn.XLOOKUP($A6,Sales!$A:$A,Sales!$Z:$Z,"0")-K6-U6 -> 1159.12 | X6: {=_xlfn.XLOOKUP($A6,Sales!$A:$A,Sales!$T:$T+Sales!$U:$U+Sales!$V:$V,"0")-K6} -> 1178.24 | Y6: =_xlfn.XLOOKUP($A6,Sales!$A:$A,Sales!$AJ:$AJ,"0") -> 90.74 | Z6: =_xlfn.XLOOKUP($A6,Sales!$A:$A,Sales!$AL:$AL,"0") -> 105.07 | AA6: =_xlfn.XLOOKUP($A6,Sales!$A:$A,Sales!$AO:$AO,"0") -> 1703.9 | AB6: =O6+P6+Q6+S6 -> 7032.02 | AC6: =O6+P6+Q6+R6+S6+V6+W6+Y6+Z6+AA6+U6 -> 10496.82 | AD6: =N6-AC6 -> 0 | AE6: =_xlfn.XLOOKUP($A6,Sales!$A:$A,Sales!$Q:$Q,"0") -> -11.12 | AG6: 28845 | AH6: =VLOOKUP(AG6,Sales!A:V,20,FALSE) -> 1178.24 | AI6: =VLOOKUP(AG6,Sales!A:U,21,FALSE) -> 0 | AJ6: =VLOOKUP(AG6,Sales!A:V,22,FALSE) -> 0 | AK6: =VLOOKUP(AG6,Sales!A:Q,17,FALSE) -> -11.12 | AL6: =SUMIF(A:A,AG6,W:W) -> 1159.12 | AM6: =AL6-(AH6+AI6+AJ6)+AK6+U6 -> -1.1723955e-13
A7: 28846 | C7: =_xlfn.XLOOKUP($A7,Sales!$A:$A,Sales!$D:$D,"0") -> 628.61 | D7: =SUM(H7+F7+E7-Z7,"0") -> 7855.45 | E7: =_xlfn.XLOOKUP($A7,Sales!$A:$A,Sales!$G:$G,"0") -> 238 | F7: =_xlfn.XLOOKUP($A7,Sales!$A:$A,Sales!$F:$F,"0") -> 0 | G7: =_xlfn.XLOOKUP($A7,Sales!$A:$A,Sales!$AP:$AP,"0") -> 27.83 | H7: =_xlfn.XLOOKUP($A7,Sales!$A:$A,Sales!$C:$C,"0") -> 7920.15 | I7: =C7 -> 628.61 | J7: =_xlfn.XLOOKUP($A7,Sales!$A:$A,Sales!$J:$J,"0") -> 0 | K7: =_xlfn.XLOOKUP($A7,Sales!$A:$A,Sales!$H:$H,"0") -> 0 | L7: 0 | M7: =_xlfn.XLOOKUP($A7,Sales!$A:$A,Sales!$AP:$AP,"0") -> 27.83 | N7: =H7+I7+J7+M7+L7-K7 -> 8576.59 | O7: =_xlfn.XLOOKUP($A7,Sales!$A:$A,Sales!$L:$L,"0") -> 924.44 | P7: =_xlfn.XLOOKUP($A7,Sales!$A:$A,Sales!$M:$M,"0") -> 3917.32 | Q7: =_xlfn.XLOOKUP($A7,Sales!$A:$A,Sales!$N:$N,"0") -> 83.67 | R7: =_xlfn.XLOOKUP($A7,Sales!$A:$A,Sales!$O:$O,"0") -> 75.28 | S7: =_xlfn.XLOOKUP($A7,Sales!$A:$A,Sales!$P:$P,"0") -> 0 | U7: =SUMIFS('EBT AMOUNTS'!I:I,'EBT AMOUNTS'!L:L,Conciliation!A7) -> 108.77 | V7: =_xlfn.XLOOKUP($A7,Sales!$A:$A,Sales!$I:$I,"0")*-1 -> 9.72 | W7: =_xlfn.XLOOKUP($A7,Sales!$A:$A,Sales!$Z:$Z,"0")-K7-U7 -> 1491.03 | X7: {=_xlfn.XLOOKUP($A7,Sales!$A:$A,Sales!$T:$T+Sales!$U:$U+Sales!$V:$V,"0")-K7} -> 1604.77 | Y7: =_xlfn.XLOOKUP($A7,Sales!$A:$A,Sales!$AJ:$AJ,"0") -> 37.79 | Z7: =_xlfn.XLOOKUP($A7,Sales!$A:$A,Sales!$AL:$AL,"0") -> 302.7 | AA7: =_xlfn.XLOOKUP($A7,Sales!$A:$A,Sales!$AO:$AO,"0") -> 1625.87 | AB7: =O7+P7+Q7+S7 -> 4925.43 | AC7: =O7+P7+Q7+R7+S7+V7+W7+Y7+Z7+AA7+U7 -> 8576.59 | AD7: =N7-AC7 -> 0 | AE7: =_xlfn.XLOOKUP($A7,Sales!$A:$A,Sales!$Q:$Q,"0") -> 4.97 | AG7: 28846 | AH7: =VLOOKUP(AG7,Sales!A:V,20,FALSE) -> 1604.77 | AI7: =VLOOKUP(AG7,Sales!A:U,21,FALSE) -> 0 | AJ7: =VLOOKUP(AG7,Sales!A:V,22,FALSE) -> 0 | AK7: =VLOOKUP(AG7,Sales!A:Q,17,FALSE) -> 4.97 | AL7: =SUMIF(A:A,AG7,W:W) -> 1491.03 | AM7: =AL7-(AH7+AI7+AJ7)+AK7+U7 -> 0
A8: 29423 | C8: =_xlfn.XLOOKUP($A8,Sales!$A:$A,Sales!$D:$D,"0") -> 364.8 | D8: =SUM(H8+F8+E8-Z8,"0") -> 4491.12 | E8: =_xlfn.XLOOKUP($A8,Sales!$A:$A,Sales!$G:$G,"0") -> 70.6 | F8: =_xlfn.XLOOKUP($A8,Sales!$A:$A,Sales!$F:$F,"0") -> 0 | G8: =_xlfn.XLOOKUP($A8,Sales!$A:$A,Sales!$AP:$AP,"0") -> 13.8 | H8: =_xlfn.XLOOKUP($A8,Sales!$A:$A,Sales!$C:$C,"0") -> 4437.27 | I8: =C8 -> 364.8 | J8: =_xlfn.XLOOKUP($A8,Sales!$A:$A,Sales!$J:$J,"0") -> 0 | K8: =_xlfn.XLOOKUP($A8,Sales!$A:$A,Sales!$H:$H,"0") -> 0 | L8: 0 | M8: =_xlfn.XLOOKUP($A8,Sales!$A:$A,Sales!$AP:$AP,"0") -> 13.8 | N8: =H8+I8+J8+M8+L8-K8 -> 4815.87 | O8: =_xlfn.XLOOKUP($A8,Sales!$A:$A,Sales!$L:$L,"0") -> 972.45 | P8: =_xlfn.XLOOKUP($A8,Sales!$A:$A,Sales!$M:$M,"0") -> 2380.77 | Q8: =_xlfn.XLOOKUP($A8,Sales!$A:$A,Sales!$N:$N,"0") -> 88.26 | R8: =_xlfn.XLOOKUP($A8,Sales!$A:$A,Sales!$O:$O,"0") -> 62.52 | S8: =_xlfn.XLOOKUP($A8,Sales!$A:$A,Sales!$P:$P,"0") -> 0 | V8: =_xlfn.XLOOKUP($A8,Sales!$A:$A,Sales!$I:$I,"0")*-1 -> 0 | W8: =_xlfn.XLOOKUP($A8,Sales!$A:$A,Sales!$Z:$Z,"0")-K8-U8 -> 1172.5 | X8: {=_xlfn.XLOOKUP($A8,Sales!$A:$A,Sales!$T:$T+Sales!$U:$U+Sales!$V:$V,"0")-K8} -> 535 | Y8: =_xlfn.XLOOKUP($A8,Sales!$A:$A,Sales!$AJ:$AJ,"0") -> 0 | Z8: =_xlfn.XLOOKUP($A8,Sales!$A:$A,Sales!$AL:$AL,"0") -> 16.75 | AA8: =_xlfn.XLOOKUP($A8,Sales!$A:$A,Sales!$AO:$AO,"0") -> 122.62 | AB8: =O8+P8+Q8+S8 -> 3441.48 | AC8: =O8+P8+Q8+R8+S8+V8+W8+Y8+Z8+AA8+U8 -> 4815.87 | AD8: =N8-AC8 -> 0 | AE8: =_xlfn.XLOOKUP($A8,Sales!$A:$A,Sales!$Q:$Q,"0") -> -637.5 | AG8: 29423 | AH8: =VLOOKUP(AG8,Sales!A:V,20,FALSE) -> 535 | AI8: =VLOOKUP(AG8,Sales!A:U,21,FALSE) -> 0 | AJ8: =VLOOKUP(AG8,Sales!A:V,22,FALSE) -> 0 | AK8: =VLOOKUP(AG8,Sales!A:Q,17,FALSE) -> -637.5 | AL8: =SUMIF(A:A,AG8,W:W) -> 1172.5 | AM8: =AL8-(AH8+AI8+AJ8)+AK8 -> 0
A9: 30256 | C9: =_xlfn.XLOOKUP($A9,Sales!$A:$A,Sales!$D:$D,"0") -> 463.5 | D9: =SUM(H9+F9+E9-Z9,"0") -> 5861.52 | E9: =_xlfn.XLOOKUP($A9,Sales!$A:$A,Sales!$G:$G,"0") -> 124.31 | F9: =_xlfn.XLOOKUP($A9,Sales!$A:$A,Sales!$F:$F,"0") -> 0 | G9: =_xlfn.XLOOKUP($A9,Sales!$A:$A,Sales!$AP:$AP,"0") -> 16.43 | H9: =_xlfn.XLOOKUP($A9,Sales!$A:$A,Sales!$C:$C,"0") -> 5789.49 | I9: =C9 -> 463.5 | J9: =_xlfn.XLOOKUP($A9,Sales!$A:$A,Sales!$J:$J,"0") -> 0 | K9: =_xlfn.XLOOKUP($A9,Sales!$A:$A,Sales!$H:$H,"0") -> 0 | L9: 0 | M9: =_xlfn.XLOOKUP($A9,Sales!$A:$A,Sales!$AP:$AP,"0") -> 16.43 | N9: =H9+I9+J9+M9+L9-K9 -> 6269.42 | O9: =_xlfn.XLOOKUP($A9,Sales!$A:$A,Sales!$L:$L,"0") -> 554.59 | P9: =_xlfn.XLOOKUP($A9,Sales!$A:$A,Sales!$M:$M,"0") -> 3764.02 | Q9: =_xlfn.XLOOKUP($A9,Sales!$A:$A,Sales!$N:$N,"0") -> 78.72 | R9: =_xlfn.XLOOKUP($A9,Sales!$A:$A,Sales!$O:$O,"0") -> 199.38 | S9: =_xlfn.XLOOKUP($A9,Sales!$A:$A,Sales!$P:$P,"0") -> 0 | U9: =SUMIFS('EBT AMOUNTS'!I:I,'EBT AMOUNTS'!L:L,Conciliation!A9) -> 34.04 | V9: =_xlfn.XLOOKUP($A9,Sales!$A:$A,Sales!$I:$I,"0")*-1 -> 0 | W9: =_xlfn.XLOOKUP($A9,Sales!$A:$A,Sales!$Z:$Z,"0")-K9-U9 -> 1043.96 | X9: {=_xlfn.XLOOKUP($A9,Sales!$A:$A,Sales!$T:$T+Sales!$U:$U+Sales!$V:$V,"0")-K9} -> 1076 | Y9: =_xlfn.XLOOKUP($A9,Sales!$A:$A,Sales!$AJ:$AJ,"0") -> 0 | Z9: =_xlfn.XLOOKUP($A9,Sales!$A:$A,Sales!$AL:$AL,"0") -> 52.28 | AA9: =_xlfn.XLOOKUP($A9,Sales!$A:$A,Sales!$AO:$AO,"0") -> 542.43 | AB9: =O9+P9+Q9+S9 -> 4397.33 | AC9: =O9+P9+Q9+R9+S9+V9+W9+Y9+Z9+AA9+U9 -> 6269.42 | AD9: =N9-AC9 -> 0 | AE9: =_xlfn.XLOOKUP($A9,Sales!$A:$A,Sales!$Q:$Q,"0") -> -2 | AG9: 30256 | AH9: =VLOOKUP(AG9,Sales!A:V,20,FALSE) -> 1076 | AI9: =VLOOKUP(AG9,Sales!A:U,21,FALSE) -> 0 | AJ9: =VLOOKUP(AG9,Sales!A:V,22,FALSE) -> 0 | AK9: =VLOOKUP(AG9,Sales!A:Q,17,FALSE) -> -2 | AL9: =SUMIF(A:A,AG9,W:W) -> 1043.96 | AM9: =AL9-(AH9+AI9+AJ9)+AK9+U9 -> 0
A10: 30491 | C10: =_xlfn.XLOOKUP($A10,Sales!$A:$A,Sales!$D:$D,"0") -> 389.13 | D10: =SUM(H10+F10+E10-Z10,"0") -> 4656.88 | E10: =_xlfn.XLOOKUP($A10,Sales!$A:$A,Sales!$G:$G,"0") -> 201.65 | F10: =_xlfn.XLOOKUP($A10,Sales!$A:$A,Sales!$F:$F,"0") -> 0 | G10: =_xlfn.XLOOKUP($A10,Sales!$A:$A,Sales!$AP:$AP,"0") -> 28.2 | H10: =_xlfn.XLOOKUP($A10,Sales!$A:$A,Sales!$C:$C,"0") -> 4455.23 | I10: =C10 -> 389.13 | J10: =_xlfn.XLOOKUP($A10,Sales!$A:$A,Sales!$J:$J,"0") -> 0 | K10: =_xlfn.XLOOKUP($A10,Sales!$A:$A,Sales!$H:$H,"0") -> 0 | L10: 0 | M10: =_xlfn.XLOOKUP($A10,Sales!$A:$A,Sales!$AP:$AP,"0") -> 28.2 | N10: =H10+I10+J10+M10+L10-K10 -> 4872.56 | O10: =_xlfn.XLOOKUP($A10,Sales!$A:$A,Sales!$L:$L,"0") -> 764.83 | P10: =_xlfn.XLOOKUP($A10,Sales!$A:$A,Sales!$M:$M,"0") -> 2864.73 | Q10: =_xlfn.XLOOKUP($A10,Sales!$A:$A,Sales!$N:$N,"0") -> 38.95 | R10: =_xlfn.XLOOKUP($A10,Sales!$A:$A,Sales!$O:$O,"0") -> 186.03 | S10: =_xlfn.XLOOKUP($A10,Sales!$A:$A,Sales!$P:$P,"0") -> 0 | U10: =SUMIFS('EBT AMOUNTS'!I:I,'EBT AMOUNTS'!L:L,Conciliation!A10) -> 7.58 | V10: =_xlfn.XLOOKUP($A10,Sales!$A:$A,Sales!$I:$I,"0")*-1 -> 36.6 | W10: =_xlfn.XLOOKUP($A10,Sales!$A:$A,Sales!$Z:$Z,"0")-K10-U10 -> 886.57 | X10: {=_xlfn.XLOOKUP($A10,Sales!$A:$A,Sales!$T:$T+Sales!$U:$U+Sales!$V:$V,"0")-K10} -> 893 | Y10: =_xlfn.XLOOKUP($A10,Sales!$A:$A,Sales!$AJ:$AJ,"0") -> 0 | Z10: =_xlfn.XLOOKUP($A10,Sales!$A:$A,Sales!$AL:$AL,"0") -> 0 | AA10: =_xlfn.XLOOKUP($A10,Sales!$A:$A,Sales!$AO:$AO,"0") -> 87.27 | AB10: =O10+P10+Q10+S10 -> 3668.51 | AC10: =O10+P10+Q10+R10+S10+V10+W10+Y10+Z10+AA10+U10 -> 4872.56 | AD10: =N10-AC10 -> 0 | AE10: =_xlfn.XLOOKUP($A10,Sales!$A:$A,Sales!$Q:$Q,"0") -> -1.15 | AG10: 30491 | AH10: =VLOOKUP(AG10,Sales!A:V,20,FALSE) -> 893 | AI10: =VLOOKUP(AG10,Sales!A:U,21,FALSE) -> 0 | AJ10: =VLOOKUP(AG10,Sales!A:V,22,FALSE) -> 0 | AK10: =VLOOKUP(AG10,Sales!A:Q,17,FALSE) -> -1.15 | AL10: =SUMIF(A:A,AG10,W:W) -> 886.57 | AM10: =AL10-(AH10+AI10+AJ10)+AK10+U10 -> -6.3948846e-14
A11: 32680 | C11: =_xlfn.XLOOKUP($A11,Sales!$A:$A,Sales!$D:$D,"0") -> 418.82 | D11: =SUM(H11+F11+E11-Z11,"0") -> 5279.46 | E11: =_xlfn.XLOOKUP($A11,Sales!$A:$A,Sales!$G:$G,"0") -> 199.74 | F11: =_xlfn.XLOOKUP($A11,Sales!$A:$A,Sales!$F:$F,"0") -> 3.69 | G11: =_xlfn.XLOOKUP($A11,Sales!$A:$A,Sales!$AP:$AP,"0") -> 25.52 | H11: =_xlfn.XLOOKUP($A11,Sales!$A:$A,Sales!$C:$C,"0") -> 5087.01 | I11: =C11 -> 418.82 | J11: =_xlfn.XLOOKUP($A11,Sales!$A:$A,Sales!$J:$J,"0") -> 0 | K11: =_xlfn.XLOOKUP($A11,Sales!$A:$A,Sales!$H:$H,"0") -> 0 | L11: 0 | M11: =_xlfn.XLOOKUP($A11,Sales!$A:$A,Sales!$AP:$AP,"0") -> 25.52 | N11: =H11+I11+J11+M11+L11-K11 -> 5531.35 | O11: =_xlfn.XLOOKUP($A11,Sales!$A:$A,Sales!$L:$L,"0") -> 434.24 | P11: =_xlfn.XLOOKUP($A11,Sales!$A:$A,Sales!$M:$M,"0") -> 3142.82 | Q11: =_xlfn.XLOOKUP($A11,Sales!$A:$A,Sales!$N:$N,"0") -> 81.92 | R11: =_xlfn.XLOOKUP($A11,Sales!$A:$A,Sales!$O:$O,"0") -> 9.3 | S11: =_xlfn.XLOOKUP($A11,Sales!$A:$A,Sales!$P:$P,"0") -> 0 | V11: =_xlfn.XLOOKUP($A11,Sales!$A:$A,Sales!$I:$I,"0")*-1 -> 0 | W11: =_xlfn.XLOOKUP($A11,Sales!$A:$A,Sales!$Z:$Z,"0")-K11-U11 -> 1433.88 | X11: {=_xlfn.XLOOKUP($A11,Sales!$A:$A,Sales!$T:$T+Sales!$U:$U+Sales!$V:$V,"0")-K11} -> 1432 | Y11: =_xlfn.XLOOKUP($A11,Sales!$A:$A,Sales!$AJ:$AJ,"0") -> 0 | Z11: =_xlfn.XLOOKUP($A11,Sales!$A:$A,Sales!$AL:$AL,"0") -> 10.98 | AA11: =_xlfn.XLOOKUP($A11,Sales!$A:$A,Sales!$AO:$AO,"0") -> 418.21 | AB11: =O11+P11+Q11+S11 -> 3658.98 | AC11: =O11+P11+Q11+R11+S11+V11+W11+Y11+Z11+AA11+U11 -> 5531.35 | AD11: =N11-AC11 -> 0 | AE11: =_xlfn.XLOOKUP($A11,Sales!$A:$A,Sales!$Q:$Q,"0") -> -1.88 | AG11: 32680 | AH11: =VLOOKUP(AG11,Sales!A:V,20,FALSE) -> 1432 | AI11: =VLOOKUP(AG11,Sales!A:U,21,FALSE) -> 0 | AJ11: =VLOOKUP(AG11,Sales!A:V,22,FALSE) -> 0 | AK11: =VLOOKUP(AG11,Sales!A:Q,17,FALSE) -> -1.88 | AL11: =SUMIF(A:A,AG11,W:W) -> 1433.88 | AM11: =AL11-(AH11+AI11+AJ11)+AK11 -> 1.0924595e-13
A12: 32932 | C12: =_xlfn.XLOOKUP($A12,Sales!$A:$A,Sales!$D:$D,"0") -> 0 | D12: =SUM(H12+F12+E12-Z12,"0") -> 6625.5 | E12: =_xlfn.XLOOKUP($A12,Sales!$A:$A,Sales!$G:$G,"0") -> 280.58 | F12: =_xlfn.XLOOKUP($A12,Sales!$A:$A,Sales!$F:$F,"0") -> 9.75 | G12: =_xlfn.XLOOKUP($A12,Sales!$A:$A,Sales!$AP:$AP,"0") -> 16.58 | H12: =_xlfn.XLOOKUP($A12,Sales!$A:$A,Sales!$C:$C,"0") -> 6924.33 | I12: =C12 -> 0 | J12: =_xlfn.XLOOKUP($A12,Sales!$A:$A,Sales!$J:$J,"0") -> 0 | K12: =_xlfn.XLOOKUP($A12,Sales!$A:$A,Sales!$H:$H,"0") -> 0 | L12: 0 | M12: =_xlfn.XLOOKUP($A12,Sales!$A:$A,Sales!$AP:$AP,"0") -> 16.58 | N12: =H12+I12+J12+M12+L12-K12 -> 6940.91 | O12: =_xlfn.XLOOKUP($A12,Sales!$A:$A,Sales!$L:$L,"0") -> 409.76 | P12: =_xlfn.XLOOKUP($A12,Sales!$A:$A,Sales!$M:$M,"0") -> 3736.92 | Q12: =_xlfn.XLOOKUP($A12,Sales!$A:$A,Sales!$N:$N,"0") -> 81.99 | R12: =_xlfn.XLOOKUP($A12,Sales!$A:$A,Sales!$O:$O,"0") -> 27.46 | S12: =_xlfn.XLOOKUP($A12,Sales!$A:$A,Sales!$P:$P,"0") -> 0 | V12: =_xlfn.XLOOKUP($A12,Sales!$A:$A,Sales!$I:$I,"0")*-1 -> 31.19 | W12: =_xlfn.XLOOKUP($A12,Sales!$A:$A,Sales!$Z:$Z,"0")-K12-U12 -> 1254.2 | X12: {=_xlfn.XLOOKUP($A12,Sales!$A:$A,Sales!$T:$T+Sales!$U:$U+Sales!$V:$V,"0")-K12} -> 1260 | Y12: =_xlfn.XLOOKUP($A12,Sales!$A:$A,Sales!$AJ:$AJ,"0") -> 83.22 | Z12: =_xlfn.XLOOKUP($A12,Sales!$A:$A,Sales!$AL:$AL,"0") -> 589.16 | AA12: =_xlfn.XLOOKUP($A12,Sales!$A:$A,Sales!$AO:$AO,"0") -> 727.01 | AB12: =O12+P12+Q12+S12 -> 4228.67 | AC12: =O12+P12+Q12+R12+S12+V12+W12+Y12+Z12+AA12+U12 -> 6940.91 | AD12: =N12-AC12 -> 0 | AE12: =_xlfn.XLOOKUP($A12,Sales!$A:$A,Sales!$Q:$Q,"0") -> 5.8 | AG12: 32932 | AH12: =VLOOKUP(AG12,Sales!A:V,20,FALSE) -> 1260 | AI12: =VLOOKUP(AG12,Sales!A:U,21,FALSE) -> 0 | AJ12: =VLOOKUP(AG12,Sales!A:V,22,FALSE) -> 0 | AK12: =VLOOKUP(AG12,Sales!A:Q,17,FALSE) -> 5.8 | AL12: =SUMIF(A:A,AG12,W:W) -> 1254.2 | AM12: =AL12-(AH12+AI12+AJ12)+AK12 -> 4.5297099e-14
A13: 32933 | C13: =_xlfn.XLOOKUP($A13,Sales!$A:$A,Sales!$D:$D,"0") -> 0 | D13: =SUM(H13+F13+E13-Z13,"0") -> 11276.94 | E13: =_xlfn.XLOOKUP($A13,Sales!$A:$A,Sales!$G:$G,"0") -> 451.4 | F13: =_xlfn.XLOOKUP($A13,Sales!$A:$A,Sales!$F:$F,"0") -> 129.18 | G13: =_xlfn.XLOOKUP($A13,Sales!$A:$A,Sales!$AP:$AP,"0") -> 29.87 | H13: =_xlfn.XLOOKUP($A13,Sales!$A:$A,Sales!$C:$C,"0") -> 12023.19 | I13: =C13 -> 0 | J13: =_xlfn.XLOOKUP($A13,Sales!$A:$A,Sales!$J:$J,"0") -> 20 | K13: =_xlfn.XLOOKUP($A13,Sales!$A:$A,Sales!$H:$H,"0") -> 0 | L13: 0 | M13: =_xlfn.XLOOKUP($A13,Sales!$A:$A,Sales!$AP:$AP,"0") -> 29.87 | N13: =H13+I13+J13+M13+L13-K13 -> 12073.06 | O13: =_xlfn.XLOOKUP($A13,Sales!$A:$A,Sales!$L:$L,"0") -> 865.27 | P13: =_xlfn.XLOOKUP($A13,Sales!$A:$A,Sales!$M:$M,"0") -> 6312.3 | Q13: =_xlfn.XLOOKUP($A13,Sales!$A:$A,Sales!$N:$N,"0") -> 185.85 | R13: =_xlfn.XLOOKUP($A13,Sales!$A:$A,Sales!$O:$O,"0") -> 89.84 | S13: =_xlfn.XLOOKUP($A13,Sales!$A:$A,Sales!$P:$P,"0") -> 0 | V13: =_xlfn.XLOOKUP($A13,Sales!$A:$A,Sales!$I:$I,"0")*-1 -> 59.44 | W13: =_xlfn.XLOOKUP($A13,Sales!$A:$A,Sales!$Z:$Z,"0")-K13-U13 -> 1917.89 | X13: {=_xlfn.XLOOKUP($A13,Sales!$A:$A,Sales!$T:$T+Sales!$U:$U+Sales!$V:$V,"0")-K13} -> 0 | Y13: =_xlfn.XLOOKUP($A13,Sales!$A:$A,Sales!$AJ:$AJ,"0") -> 138.33 | Z13: =_xlfn.XLOOKUP($A13,Sales!$A:$A,Sales!$AL:$AL,"0") -> 1326.83 | AA13: =_xlfn.XLOOKUP($A13,Sales!$A:$A,Sales!$AO:$AO,"0") -> 1177.31 | AB13: =O13+P13+Q13+S13 -> 7363.42 | AC13: =O13+P13+Q13+R13+S13+V13+W13+Y13+Z13+AA13+U13 -> 12073.06 | AD13: =N13-AC13 -> 0 | AE13: =_xlfn.XLOOKUP($A13,Sales!$A:$A,Sales!$Q:$Q,"0") -> -1917.89 | AG13: 32933 | AH13: =VLOOKUP(AG13,Sales!A:V,20,FALSE) -> 0 | AI13: =VLOOKUP(AG13,Sales!A:U,21,FALSE) -> 0 | AJ13: =VLOOKUP(AG13,Sales!A:V,22,FALSE) -> 0 | AK13: =VLOOKUP(AG13,Sales!A:Q,17,FALSE) -> -1917.89 | AL13: =SUMIF(A:A,AG13,W:W) -> 1917.89 | AM13: =AL13-(AH13+AI13+AJ13)+AK13 -> 0
A14: 32934 | C14: =_xlfn.XLOOKUP($A14,Sales!$A:$A,Sales!$D:$D,"0") -> 0 | D14: =SUM(H14+F14+E14-Z14,"0") -> 8336.89 | E14: =_xlfn.XLOOKUP($A14,Sales!$A:$A,Sales!$G:$G,"0") -> 221.92 | F14: =_xlfn.XLOOKUP($A14,Sales!$A:$A,Sales!$F:$F,"0") -> 7.38 | G14: =_xlfn.XLOOKUP($A14,Sales!$A:$A,Sales!$AP:$AP,"0") -> 19.22 | H14: =_xlfn.XLOOKUP($A14,Sales!$A:$A,Sales!$C:$C,"0") -> 8711.2 | I14: =C14 -> 0 | J14: =_xlfn.XLOOKUP($A14,Sales!$A:$A,Sales!$J:$J,"0") -> 0 | K14: =_xlfn.XLOOKUP($A14,Sales!$A:$A,Sales!$H:$H,"0") -> 0 | L14: 0 | M14: =_xlfn.XLOOKUP($A14,Sales!$A:$A,Sales!$AP:$AP,"0") -> 19.22 | N14: =H14+I14+J14+M14+L14-K14 -> 8730.42 | O14: =_xlfn.XLOOKUP($A14,Sales!$A:$A,Sales!$L:$L,"0") -> 973.91 | P14: =_xlfn.XLOOKUP($A14,Sales!$A:$A,Sales!$M:$M,"0") -> 4526.47 | Q14: =_xlfn.XLOOKUP($A14,Sales!$A:$A,Sales!$N:$N,"0") -> 85.01 | R14: =_xlfn.XLOOKUP($A14,Sales!$A:$A,Sales!$O:$O,"0") -> 151.79 | S14: =_xlfn.XLOOKUP($A14,Sales!$A:$A,Sales!$P:$P,"0") -> 0 | V14: =_xlfn.XLOOKUP($A14,Sales!$A:$A,Sales!$I:$I,"0")*-1 -> 15.79 | W14: =_xlfn.XLOOKUP($A14,Sales!$A:$A,Sales!$Z:$Z,"0")-K14-U14 -> 1336.98 | X14: {=_xlfn.XLOOKUP($A14,Sales!$A:$A,Sales!$T:$T+Sales!$U:$U+Sales!$V:$V,"0")-K14} -> 1336 | Y14: =_xlfn.XLOOKUP($A14,Sales!$A:$A,Sales!$AJ:$AJ,"0") -> 182.75 | Z14: =_xlfn.XLOOKUP($A14,Sales!$A:$A,Sales!$AL:$AL,"0") -> 603.61 | AA14: =_xlfn.XLOOKUP($A14,Sales!$A:$A,Sales!$AO:$AO,"0") -> 854.11 | AB14: =O14+P14+Q14+S14 -> 5585.39 | AC14: =O14+P14+Q14+R14+S14+V14+W14+Y14+Z14+AA14+U14 -> 8730.42 | AD14: =N14-AC14 -> 0 | AE14: =_xlfn.XLOOKUP($A14,Sales!$A:$A,Sales!$Q:$Q,"0") -> -0.98 | AG14: 32934 | AH14: =VLOOKUP(AG14,Sales!A:V,20,FALSE) -> 1336 | AI14: =VLOOKUP(AG14,Sales!A:U,21,FALSE) -> 0 | AJ14: =VLOOKUP(AG14,Sales!A:V,22,FALSE) -> 0 | AK14: =VLOOKUP(AG14,Sales!A:Q,17,FALSE) -> -0.98 | AL14: =SUMIF(A:A,AG14,W:W) -> 1336.98 | AM14: =AL14-(AH14+AI14+AJ14)+AK14 -> 1.8207658e-14
A15: 32935 | C15: =_xlfn.XLOOKUP($A15,Sales!$A:$A,Sales!$D:$D,"0") -> 0 | D15: =SUM(H15+F15+E15-Z15,"0") -> 7555.98 | E15: =_xlfn.XLOOKUP($A15,Sales!$A:$A,Sales!$G:$G,"0") -> 503.26 | F15: =_xlfn.XLOOKUP($A15,Sales!$A:$A,Sales!$F:$F,"0") -> 0 | G15: =_xlfn.XLOOKUP($A15,Sales!$A:$A,Sales!$AP:$AP,"0") -> 17.9 | H15: =_xlfn.XLOOKUP($A15,Sales!$A:$A,Sales!$C:$C,"0") -> 7612.57 | I15: =C15 -> 0 | J15: =_xlfn.XLOOKUP($A15,Sales!$A:$A,Sales!$J:$J,"0") -> 0 | K15: =_xlfn.XLOOKUP($A15,Sales!$A:$A,Sales!$H:$H,"0") -> 0 | L15: 0 | M15: =_xlfn.XLOOKUP($A15,Sales!$A:$A,Sales!$AP:$AP,"0") -> 17.9 | N15: =H15+I15+J15+M15+L15-K15 -> 7630.47 | O15: =_xlfn.XLOOKUP($A15,Sales!$A:$A,Sales!$L:$L,"0") -> 482.92 | P15: =_xlfn.XLOOKUP($A15,Sales!$A:$A,Sales!$M:$M,"0") -> 3941.49 | Q15: =_xlfn.XLOOKUP($A15,Sales!$A:$A,Sales!$N:$N,"0") -> 23.08 | R15: =_xlfn.XLOOKUP($A15,Sales!$A:$A,Sales!$O:$O,"0") -> 40.24 | S15: =_xlfn.XLOOKUP($A15,Sales!$A:$A,Sales!$P:$P,"0") -> 0 | V15: =_xlfn.XLOOKUP($A15,Sales!$A:$A,Sales!$I:$I,"0")*-1 -> 0 | W15: =_xlfn.XLOOKUP($A15,Sales!$A:$A,Sales!$Z:$Z,"0")-K15-U15 -> 1358.71 | X15: {=_xlfn.XLOOKUP($A15,Sales!$A:$A,Sales!$T:$T+Sales!$U:$U+Sales!$V:$V,"0")-K15} -> 1353 | Y15: =_xlfn.XLOOKUP($A15,Sales!$A:$A,Sales!$AJ:$AJ,"0") -> 102.16 | Z15: =_xlfn.XLOOKUP($A15,Sales!$A:$A,Sales!$AL:$AL,"0") -> 559.85 | AA15: =_xlfn.XLOOKUP($A15,Sales!$A:$A,Sales!$AO:$AO,"0") -> 1122.02 | AB15: =O15+P15+Q15+S15 -> 4447.49 | AC15: =O15+P15+Q15+R15+S15+V15+W15+Y15+Z15+AA15+U15 -> 7630.47 | AD15: =N15-AC15 -> 0 | AE15: =_xlfn.XLOOKUP($A15,Sales!$A:$A,Sales!$Q:$Q,"0") -> -5.71 | AG15: 32935 | AH15: =VLOOKUP(AG15,Sales!A:V,20,FALSE) -> 1353 | AI15: =VLOOKUP(AG15,Sales!A:U,21,FALSE) -> 0 | AJ15: =VLOOKUP(AG15,Sales!A:V,22,FALSE) -> 0 | AK15: =VLOOKUP(AG15,Sales!A:Q,17,FALSE) -> -5.71 | AL15: =SUMIF(A:A,AG15,W:W) -> 1358.71 | AM15: =AL15-(AH15+AI15+AJ15)+AK15 -> 3.6415315e-14
A16: 32936 | C16: =_xlfn.XLOOKUP($A16,Sales!$A:$A,Sales!$D:$D,"0") -> 0 | D16: =SUM(H16+F16+E16-Z16,"0") -> 7484.98 | E16: =_xlfn.XLOOKUP($A16,Sales!$A:$A,Sales!$G:$G,"0") -> 244.93 | F16: =_xlfn.XLOOKUP($A16,Sales!$A:$A,Sales!$F:$F,"0") -> 50.2 | G16: =_xlfn.XLOOKUP($A16,Sales!$A:$A,Sales!$AP:$AP,"0") -> 4.98 | H16: =_xlfn.XLOOKUP($A16,Sales!$A:$A,Sales!$C:$C,"0") -> 7498.21 | I16: =C16 -> 0 | J16: =_xlfn.XLOOKUP($A16,Sales!$A:$A,Sales!$J:$J,"0") -> 0 | K16: =_xlfn.XLOOKUP($A16,Sales!$A:$A,Sales!$H:$H,"0") -> 0 | L16: 0 | M16: =_xlfn.XLOOKUP($A16,Sales!$A:$A,Sales!$AP:$AP,"0") -> 4.98 | N16: =H16+I16+J16+M16+L16-K16 -> 7503.19 | O16: =_xlfn.XLOOKUP($A16,Sales!$A:$A,Sales!$L:$L,"0") -> 742.5 | P16: =_xlfn.XLOOKUP($A16,Sales!$A:$A,Sales!$M:$M,"0") -> 4390.59 | Q16: =_xlfn.XLOOKUP($A16,Sales!$A:$A,Sales!$N:$N,"0") -> 132.59 | R16: =_xlfn.XLOOKUP($A16,Sales!$A:$A,Sales!$O:$O,"0") -> 136.49 | S16: =_xlfn.XLOOKUP($A16,Sales!$A:$A,Sales!$P:$P,"0") -> 0 | V16: =_xlfn.XLOOKUP($A16,Sales!$A:$A,Sales!$I:$I,"0")*-1 -> 32.51 | W16: =_xlfn.XLOOKUP($A16,Sales!$A:$A,Sales!$Z:$Z,"0")-K16-U16 -> 1209.01 | X16: {=_xlfn.XLOOKUP($A16,Sales!$A:$A,Sales!$T:$T+Sales!$U:$U+Sales!$V:$V,"0")-K16} -> 1208 | Y16: =_xlfn.XLOOKUP($A16,Sales!$A:$A,Sales!$AJ:$AJ,"0") -> 80.1 | Z16: =_xlfn.XLOOKUP($A16,Sales!$A:$A,Sales!$AL:$AL,"0") -> 308.36 | AA16: =_xlfn.XLOOKUP($A16,Sales!$A:$A,Sales!$AO:$AO,"0") -> 471.04 | AB16: =O16+P16+Q16+S16 -> 5265.68 | AC16: =O16+P16+Q16+R16+S16+V16+W16+Y16+Z16+AA16+U16 -> 7503.19 | AD16: =N16-AC16 -> 0 | AE16: =_xlfn.XLOOKUP($A16,Sales!$A:$A,Sales!$Q:$Q,"0") -> -1.01 | AG16: 32936 | AH16: =VLOOKUP(AG16,Sales!A:V,20,FALSE) -> 1208 | AI16: =VLOOKUP(AG16,Sales!A:U,21,FALSE) -> 0 | AJ16: =VLOOKUP(AG16,Sales!A:V,22,FALSE) -> 0 | AK16: =VLOOKUP(AG16,Sales!A:Q,17,FALSE) -> -1.01 | AL16: =SUMIF(A:A,AG16,W:W) -> 1209.01 | AM16: =AL16-(AH16+AI16+AJ16)+AK16 -> -9.1038288e-15
A17: 32937 | C17: =_xlfn.XLOOKUP($A17,Sales!$A:$A,Sales!$D:$D,"0") -> 0 | D17: =SUM(H17+F17+E17-Z17,"0") -> 11481.67 | E17: =_xlfn.XLOOKUP($A17,Sales!$A:$A,Sales!$G:$G,"0") -> 461.68 | F17: =_xlfn.XLOOKUP($A17,Sales!$A:$A,Sales!$F:$F,"0") -> 8.95 | G17: =_xlfn.XLOOKUP($A17,Sales!$A:$A,Sales!$AP:$AP,"0") -> 25.72 | H17: =_xlfn.XLOOKUP($A17,Sales!$A:$A,Sales!$C:$C,"0") -> 12233.19 | I17: =C17 -> 0 | J17: =_xlfn.XLOOKUP($A17,Sales!$A:$A,Sales!$J:$J,"0") -> 0 | K17: =_xlfn.XLOOKUP($A17,Sales!$A:$A,Sales!$H:$H,"0") -> 0 | L17: 0 | M17: =_xlfn.XLOOKUP($A17,Sales!$A:$A,Sales!$AP:$AP,"0") -> 25.72 | N17: =H17+I17+J17+M17+L17-K17 -> 12258.91 | O17: =_xlfn.XLOOKUP($A17,Sales!$A:$A,Sales!$L:$L,"0") -> 867.75 | P17: =_xlfn.XLOOKUP($A17,Sales!$A:$A,Sales!$M:$M,"0") -> 6032.12 | Q17: =_xlfn.XLOOKUP($A17,Sales!$A:$A,Sales!$N:$N,"0") -> 183.35 | R17: =_xlfn.XLOOKUP($A17,Sales!$A:$A,Sales!$O:$O,"0") -> 157.09 | S17: =_xlfn.XLOOKUP($A17,Sales!$A:$A,Sales!$P:$P,"0") -> 0 | V17: =_xlfn.XLOOKUP($A17,Sales!$A:$A,Sales!$I:$I,"0")*-1 -> 28.5 | W17: =_xlfn.XLOOKUP($A17,Sales!$A:$A,Sales!$Z:$Z,"0")-K17-U17 -> 1446.9 | X17: {=_xlfn.XLOOKUP($A17,Sales!$A:$A,Sales!$T:$T+Sales!$U:$U+Sales!$V:$V,"0")-K17} -> 1445 | Y17: =_xlfn.XLOOKUP($A17,Sales!$A:$A,Sales!$AJ:$AJ,"0") -> 304.25 | Z17: =_xlfn.XLOOKUP($A17,Sales!$A:$A,Sales!$AL:$AL,"0") -> 1222.15 | AA17: =_xlfn.XLOOKUP($A17,Sales!$A:$A,Sales!$AO:$AO,"0") -> 2016.8 | AB17: =O17+P17+Q17+S17 -> 7083.22 | AC17: =O17+P17+Q17+R17+S17+V17+W17+Y17+Z17+AA17+U17 -> 12258.91 | AD17: =N17-AC17 -> 0 | AE17: =_xlfn.XLOOKUP($A17,Sales!$A:$A,Sales!$Q:$Q,"0") -> -1.9 | AG17: 32937 | AH17: =VLOOKUP(AG17,Sales!A:V,20,FALSE) -> 1445 | AI17: =VLOOKUP(AG17,Sales!A:U,21,FALSE) -> 0 | AJ17: =VLOOKUP(AG17,Sales!A:V,22,FALSE) -> 0 | AK17: =VLOOKUP(AG17,Sales!A:Q,17,FALSE) -> -1.9 | AL17: =SUMIF(A:A,AG17,W:W) -> 1446.9 | AM17: =AL17-(AH17+AI17+AJ17)+AK17 -> 9.1038288e-14
A18: 32938 | C18: =_xlfn.XLOOKUP($A18,Sales!$A:$A,Sales!$D:$D,"0") -> 0 | D18: =SUM(H18+F18+E18-Z18,"0") -> 7617.67 | E18: =_xlfn.XLOOKUP($A18,Sales!$A:$A,Sales!$G:$G,"0") -> 343.84 | F18: =_xlfn.XLOOKUP($A18,Sales!$A:$A,Sales!$F:$F,"0") -> 91.73 | G18: =_xlfn.XLOOKUP($A18,Sales!$A:$A,Sales!$AP:$AP,"0") -> 16.58 | H18: =_xlfn.XLOOKUP($A18,Sales!$A:$A,Sales!$C:$C,"0") -> 7570.92 | I18: =C18 -> 0 | J18: =_xlfn.XLOOKUP($A18,Sales!$A:$A,Sales!$J:$J,"0") -> 25 | K18: =_xlfn.XLOOKUP($A18,Sales!$A:$A,Sales!$H:$H,"0") -> 0 | L18: 0 | M18: =_xlfn.XLOOKUP($A18,Sales!$A:$A,Sales!$AP:$AP,"0") -> 16.58 | N18: =H18+I18+J18+M18+L18-K18 -> 7612.5 | O18: =_xlfn.XLOOKUP($A18,Sales!$A:$A,Sales!$L:$L,"0") -> 876.63 | P18: =_xlfn.XLOOKUP($A18,Sales!$A:$A,Sales!$M:$M,"0") -> 4367.9 | Q18: =_xlfn.XLOOKUP($A18,Sales!$A:$A,Sales!$N:$N,"0") -> 62.82 | R18: =_xlfn.XLOOKUP($A18,Sales!$A:$A,Sales!$O:$O,"0") -> 71.22 | S18: =_xlfn.XLOOKUP($A18,Sales!$A:$A,Sales!$P:$P,"0") -> 0 | V18: =_xlfn.XLOOKUP($A18,Sales!$A:$A,Sales!$I:$I,"0")*-1 -> 46.62 | W18: =_xlfn.XLOOKUP($A18,Sales!$A:$A,Sales!$Z:$Z,"0")-K18-U18 -> 971.08 | X18: {=_xlfn.XLOOKUP($A18,Sales!$A:$A,Sales!$T:$T+Sales!$U:$U+Sales!$V:$V,"0")-K18} -> 969 | Y18: =_xlfn.XLOOKUP($A18,Sales!$A:$A,Sales!$AJ:$AJ,"0") -> 149.55 | Z18: =_xlfn.XLOOKUP($A18,Sales!$A:$A,Sales!$AL:$AL,"0") -> 388.82 | AA18: =_xlfn.XLOOKUP($A18,Sales!$A:$A,Sales!$AO:$AO,"0") -> 677.86 | AB18: =O18+P18+Q18+S18 -> 5307.35 | AC18: =O18+P18+Q18+R18+S18+V18+W18+Y18+Z18+AA18+U18 -> 7612.5 | AD18: =N18-AC18 -> 0 | AE18: =_xlfn.XLOOKUP($A18,Sales!$A:$A,Sales!$Q:$Q,"0") -> -2.08 | AG18: 32938 | AH18: =VLOOKUP(AG18,Sales!A:V,20,FALSE) -> 969 | AI18: =VLOOKUP(AG18,Sales!A:U,21,FALSE) -> 0 | AJ18: =VLOOKUP(AG18,Sales!A:V,22,FALSE) -> 0 | AK18: =VLOOKUP(AG18,Sales!A:Q,17,FALSE) -> -2.08 | AL18: =SUMIF(A:A,AG18,W:W) -> 971.08 | AM18: =AL18-(AH18+AI18+AJ18)+AK18 -> 4.0856207e-14
A19: 32939 | C19: =_xlfn.XLOOKUP($A19,Sales!$A:$A,Sales!$D:$D,"0") -> 0 | D19: =SUM(H19+F19+E19-Z19,"0") -> 11172.05 | E19: =_xlfn.XLOOKUP($A19,Sales!$A:$A,Sales!$G:$G,"0") -> 336.77 | F19: =_xlfn.XLOOKUP($A19,Sales!$A:$A,Sales!$F:$F,"0") -> 0 | G19: =_xlfn.XLOOKUP($A19,Sales!$A:$A,Sales!$AP:$AP,"0") -> 13.97 | H19: =_xlfn.XLOOKUP($A19,Sales!$A:$A,Sales!$C:$C,"0") -> 11533.5 | I19: =C19 -> 0 | J19: =_xlfn.XLOOKUP($A19,Sales!$A:$A,Sales!$J:$J,"0") -> 0 | K19: =_xlfn.XLOOKUP($A19,Sales!$A:$A,Sales!$H:$H,"0") -> 0 | L19: 0 | M19: =_xlfn.XLOOKUP($A19,Sales!$A:$A,Sales!$AP:$AP,"0") -> 13.97 | N19: =H19+I19+J19+M19+L19-K19 -> 11547.47 | O19: =_xlfn.XLOOKUP($A19,Sales!$A:$A,Sales!$L:$L,"0") -> 1027.46 | P19: =_xlfn.XLOOKUP($A19,Sales!$A:$A,Sales!$M:$M,"0") -> 6966.36 | Q19: =_xlfn.XLOOKUP($A19,Sales!$A:$A,Sales!$N:$N,"0") -> 129.49 | R19: =_xlfn.XLOOKUP($A19,Sales!$A:$A,Sales!$O:$O,"0") -> 87.63 | S19: =_xlfn.XLOOKUP($A19,Sales!$A:$A,Sales!$P:$P,"0") -> 0 | V19: =_xlfn.XLOOKUP($A19,Sales!$A:$A,Sales!$I:$I,"0")*-1 -> 40.25 | W19: =_xlfn.XLOOKUP($A19,Sales!$A:$A,Sales!$Z:$Z,"0")-K19-U19 -> 1365.25 | X19: {=_xlfn.XLOOKUP($A19,Sales!$A:$A,Sales!$T:$T+Sales!$U:$U+Sales!$V:$V,"0")-K19} -> 1368 | Y19: =_xlfn.XLOOKUP($A19,Sales!$A:$A,Sales!$AJ:$AJ,"0") -> 153.34 | Z19: =_xlfn.XLOOKUP($A19,Sales!$A:$A,Sales!$AL:$AL,"0") -> 698.22 | AA19: =_xlfn.XLOOKUP($A19,Sales!$A:$A,Sales!$AO:$AO,"0") -> 1079.47 | AB19: =O19+P19+Q19+S19 -> 8123.31 | AC19: =O19+P19+Q19+R19+S19+V19+W19+Y19+Z19+AA19+U19 -> 11547.47 | AD19: =N19-AC19 -> 0 | AE19: =_xlfn.XLOOKUP($A19,Sales!$A:$A,Sales!$Q:$Q,"0") -> 2.75 | AG19: 32939 | AH19: =VLOOKUP(AG19,Sales!A:V,20,FALSE) -> 1368 | AI19: =VLOOKUP(AG19,Sales!A:U,21,FALSE) -> 0 | AJ19: =VLOOKUP(AG19,Sales!A:V,22,FALSE) -> 0 | AK19: =VLOOKUP(AG19,Sales!A:Q,17,FALSE) -> 2.75 | AL19: =SUMIF(A:A,AG19,W:W) -> 1365.25 | AM19: =AL19-(AH19+AI19+AJ19)+AK19 -> 0
A20: 32940 | C20: =_xlfn.XLOOKUP($A20,Sales!$A:$A,Sales!$D:$D,"0") -> 0 | D20: =SUM(H20+F20+E20-Z20,"0") -> 7206.16 | E20: =_xlfn.XLOOKUP($A20,Sales!$A:$A,Sales!$G:$G,"0") -> 173.57 | F20: =_xlfn.XLOOKUP($A20,Sales!$A:$A,Sales!$F:$F,"0") -> 0 | G20: =_xlfn.XLOOKUP($A20,Sales!$A:$A,Sales!$AP:$AP,"0") -> 10.1 | H20: =_xlfn.XLOOKUP($A20,Sales!$A:$A,Sales!$C:$C,"0") -> 7781.39 | I20: =C20 -> 0 | J20: =_xlfn.XLOOKUP($A20,Sales!$A:$A,Sales!$J:$J,"0") -> 0 | K20: =_xlfn.XLOOKUP($A20,Sales!$A:$A,Sales!$H:$H,"0") -> 0 | L20: 0 | M20: =_xlfn.XLOOKUP($A20,Sales!$A:$A,Sales!$AP:$AP,"0") -> 10.1 | N20: =H20+I20+J20+M20+L20-K20 -> 7791.49 | O20: =_xlfn.XLOOKUP($A20,Sales!$A:$A,Sales!$L:$L,"0") -> 890.14 | P20: =_xlfn.XLOOKUP($A20,Sales!$A:$A,Sales!$M:$M,"0") -> 3547.34 | Q20: =_xlfn.XLOOKUP($A20,Sales!$A:$A,Sales!$N:$N,"0") -> 113.36 | R20: =_xlfn.XLOOKUP($A20,Sales!$A:$A,Sales!$O:$O,"0") -> 120.32 | S20: =_xlfn.XLOOKUP($A20,Sales!$A:$A,Sales!$P:$P,"0") -> 0 | V20: =_xlfn.XLOOKUP($A20,Sales!$A:$A,Sales!$I:$I,"0")*-1 -> 18.55 | W20: =_xlfn.XLOOKUP($A20,Sales!$A:$A,Sales!$Z:$Z,"0")-K20-U20 -> 913.37 | X20: {=_xlfn.XLOOKUP($A20,Sales!$A:$A,Sales!$T:$T+Sales!$U:$U+Sales!$V:$V,"0")-K20} -> 916 | Y20: =_xlfn.XLOOKUP($A20,Sales!$A:$A,Sales!$AJ:$AJ,"0") -> 317 | Z20: =_xlfn.XLOOKUP($A20,Sales!$A:$A,Sales!$AL:$AL,"0") -> 748.8 | AA20: =_xlfn.XLOOKUP($A20,Sales!$A:$A,Sales!$AO:$AO,"0") -> 1122.61 | AB20: =O20+P20+Q20+S20 -> 4550.84 | AC20: =O20+P20+Q20+R20+S20+V20+W20+Y20+Z20+AA20+U20 -> 7791.49 | AD20: =N20-AC20 -> 0 | AE20: =_xlfn.XLOOKUP($A20,Sales!$A:$A,Sales!$Q:$Q,"0") -> 2.63 | AG20: 32940 | AH20: =VLOOKUP(AG20,Sales!A:V,20,FALSE) -> 916 | AI20: =VLOOKUP(AG20,Sales!A:U,21,FALSE) -> 0 | AJ20: =VLOOKUP(AG20,Sales!A:V,22,FALSE) -> 0 | AK20: =VLOOKUP(AG20,Sales!A:Q,17,FALSE) -> 2.63 | AL20: =SUMIF(A:A,AG20,W:W) -> 913.37 | AM20: =AL20-(AH20+AI20+AJ20)+AK20 -> 4.4408921e-15
A21: 32941 | C21: =_xlfn.XLOOKUP($A21,Sales!$A:$A,Sales!$D:$D,"0") -> 0 | D21: =SUM(H21+F21+E21-Z21,"0") -> 6688.42 | E21: =_xlfn.XLOOKUP($A21,Sales!$A:$A,Sales!$G:$G,"0") -> 197.08 | F21: =_xlfn.XLOOKUP($A21,Sales!$A:$A,Sales!$F:$F,"0") -> 23.33 | G21: =_xlfn.XLOOKUP($A21,Sales!$A:$A,Sales!$AP:$AP,"0") -> 1.81 | H21: =_xlfn.XLOOKUP($A21,Sales!$A:$A,Sales!$C:$C,"0") -> 7246.22 | I21: =C21 -> 0 | J21: =_xlfn.XLOOKUP($A21,Sales!$A:$A,Sales!$J:$J,"0") -> 0 | K21: =_xlfn.XLOOKUP($A21,Sales!$A:$A,Sales!$H:$H,"0") -> 0 | L21: 0 | M21: =_xlfn.XLOOKUP($A21,Sales!$A:$A,Sales!$AP:$AP,"0") -> 1.81 | N21: =H21+I21+J21+M21+L21-K21 -> 7248.03 | O21: =_xlfn.XLOOKUP($A21,Sales!$A:$A,Sales!$L:$L,"0") -> 598.19 | P21: =_xlfn.XLOOKUP($A21,Sales!$A:$A,Sales!$M:$M,"0") -> 3722.19 | Q21: =_xlfn.XLOOKUP($A21,Sales!$A:$A,Sales!$N:$N,"0") -> 70.77 | R21: =_xlfn.XLOOKUP($A21,Sales!$A:$A,Sales!$O:$O,"0") -> 77.66 | S21: =_xlfn.XLOOKUP($A21,Sales!$A:$A,Sales!$P:$P,"0") -> 0 | V21: =_xlfn.XLOOKUP($A21,Sales!$A:$A,Sales!$I:$I,"0")*-1 -> 0 | W21: =_xlfn.XLOOKUP($A21,Sales!$A:$A,Sales!$Z:$Z,"0")-K21-U21 -> 920 | X21: {=_xlfn.XLOOKUP($A21,Sales!$A:$A,Sales!$T:$T+Sales!$U:$U+Sales!$V:$V,"0")-K21} -> 885 | Y21: =_xlfn.XLOOKUP($A21,Sales!$A:$A,Sales!$AJ:$AJ,"0") -> 176.61 | Z21: =_xlfn.XLOOKUP($A21,Sales!$A:$A,Sales!$AL:$AL,"0") -> 778.21 | AA21: =_xlfn.XLOOKUP($A21,Sales!$A:$A,Sales!$AO:$AO,"0") -> 904.4 | AB21: =O21+P21+Q21+S21 -> 4391.15 | AC21: =O21+P21+Q21+R21+S21+V21+W21+Y21+Z21+AA21+U21 -> 7248.03 | AD21: =N21-AC21 -> 0 | AE21: =_xlfn.XLOOKUP($A21,Sales!$A:$A,Sales!$Q:$Q,"0") -> -35 | AG21: 32941 | AH21: =VLOOKUP(AG21,Sales!A:V,20,FALSE) -> 885 | AI21: =VLOOKUP(AG21,Sales!A:U,21,FALSE) -> 0 | AJ21: =VLOOKUP(AG21,Sales!A:V,22,FALSE) -> 0 | AK21: =VLOOKUP(AG21,Sales!A:Q,17,FALSE) -> -35 | AL21: =SUMIF(A:A,AG21,W:W) -> 920 | AM21: =AL21-(AH21+AI21+AJ21)+AK21 -> 0
A22: 32942 | C22: =_xlfn.XLOOKUP($A22,Sales!$A:$A,Sales!$D:$D,"0") -> 0 | D22: =SUM(H22+F22+E22-Z22,"0") -> 7918.03 | E22: =_xlfn.XLOOKUP($A22,Sales!$A:$A,Sales!$G:$G,"0") -> 353.55 | F22: =_xlfn.XLOOKUP($A22,Sales!$A:$A,Sales!$F:$F,"0") -> 3.19 | G22: =_xlfn.XLOOKUP($A22,Sales!$A:$A,Sales!$AP:$AP,"0") -> 28.63 | H22: =_xlfn.XLOOKUP($A22,Sales!$A:$A,Sales!$C:$C,"0") -> 7745.13 | I22: =C22 -> 0 | J22: =_xlfn.XLOOKUP($A22,Sales!$A:$A,Sales!$J:$J,"0") -> 0 | K22: =_xlfn.XLOOKUP($A22,Sales!$A:$A,Sales!$H:$H,"0") -> 0 | L22: 0 | M22: =_xlfn.XLOOKUP($A22,Sales!$A:$A,Sales!$AP:$AP,"0") -> 28.63 | N22: =H22+I22+J22+M22+L22-K22 -> 7773.76 | O22: =_xlfn.XLOOKUP($A22,Sales!$A:$A,Sales!$L:$L,"0") -> 812.54 | P22: =_xlfn.XLOOKUP($A22,Sales!$A:$A,Sales!$M:$M,"0") -> 4526.93 | Q22: =_xlfn.XLOOKUP($A22,Sales!$A:$A,Sales!$N:$N,"0") -> 143.34 | R22: =_xlfn.XLOOKUP($A22,Sales!$A:$A,Sales!$O:$O,"0") -> 112.46 | S22: =_xlfn.XLOOKUP($A22,Sales!$A:$A,Sales!$P:$P,"0") -> 0 | V22: =_xlfn.XLOOKUP($A22,Sales!$A:$A,Sales!$I:$I,"0")*-1 -> 52.19 | W22: =_xlfn.XLOOKUP($A22,Sales!$A:$A,Sales!$Z:$Z,"0")-K22-U22 -> 1250.11 | X22: {=_xlfn.XLOOKUP($A22,Sales!$A:$A,Sales!$T:$T+Sales!$U:$U+Sales!$V:$V,"0")-K22} -> 1248 | Y22: =_xlfn.XLOOKUP($A22,Sales!$A:$A,Sales!$AJ:$AJ,"0") -> 114.83 | Z22: =_xlfn.XLOOKUP($A22,Sales!$A:$A,Sales!$AL:$AL,"0") -> 183.84 | AA22: =_xlfn.XLOOKUP($A22,Sales!$A:$A,Sales!$AO:$AO,"0") -> 577.52 | AB22: =O22+P22+Q22+S22 -> 5482.81 | AC22: =O22+P22+Q22+R22+S22+V22+W22+Y22+Z22+AA22+U22 -> 7773.76 | AD22: =N22-AC22 -> 0 | AE22: =_xlfn.XLOOKUP($A22,Sales!$A:$A,Sales!$Q:$Q,"0") -> -2.11 | AG22: 32942 | AH22: =VLOOKUP(AG22,Sales!A:V,20,FALSE) -> 1248 | AI22: =VLOOKUP(AG22,Sales!A:U,21,FALSE) -> 0 | AJ22: =VLOOKUP(AG22,Sales!A:V,22,FALSE) -> 0 | AK22: =VLOOKUP(AG22,Sales!A:Q,17,FALSE) -> -2.11 | AL22: =SUMIF(A:A,AG22,W:W) -> 1250.11 | AM22: =AL22-(AH22+AI22+AJ22)+AK22 -> -9.9920072e-14
... A33: 34793 | C33: =_xlfn.XLOOKUP($A33,Sales!$A:$A,Sales!$D:$D,"0") -> 382.34 | D33: =SUM(H33+F33+E33-Z33,"0") -> 4396.7 | E33: =_xlfn.XLOOKUP($A33,Sales!$A:$A,Sales!$G:$G,"0") -> 133.87 | F33: =_xlfn.XLOOKUP($A33,Sales!$A:$A,Sales!$F:$F,"0") -> 3.19 | G33: =_xlfn.XLOOKUP($A33,Sales!$A:$A,Sales!$AP:$AP,"0") -> 29.34 | H33: =_xlfn.XLOOKUP($A33,Sales!$A:$A,Sales!$C:$C,"0") -> 4329.39 | I33: =C33 -> 382.34 | J33: =_xlfn.XLOOKUP($A33,Sales!$A:$A,Sales!$J:$J,"0") -> 15 | K33: =_xlfn.XLOOKUP($A33,Sales!$A:$A,Sales!$H:$H,"0") -> 0 | L33: 0 | M33: =_xlfn.XLOOKUP($A33,Sales!$A:$A,Sales!$AP:$AP,"0") -> 29.34 | N33: =H33+I33+J33+M33+L33-K33 -> 4756.07 | O33: =_xlfn.XLOOKUP($A33,Sales!$A:$A,Sales!$L:$L,"0") -> 466.51 | P33: =_xlfn.XLOOKUP($A33,Sales!$A:$A,Sales!$M:$M,"0") -> 3096.72 | Q33: =_xlfn.XLOOKUP($A33,Sales!$A:$A,Sales!$N:$N,"0") -> 85.72 | R33: =_xlfn.XLOOKUP($A33,Sales!$A:$A,Sales!$O:$O,"0") -> 76.05 | S33: =_xlfn.XLOOKUP($A33,Sales!$A:$A,Sales!$P:$P,"0") -> 0 | V33: =_xlfn.XLOOKUP($A33,Sales!$A:$A,Sales!$I:$I,"0")*-1 -> 14.66 | W33: =_xlfn.XLOOKUP($A33,Sales!$A:$A,Sales!$Z:$Z,"0")-K33-U33 -> 897.71 | X33: {=_xlfn.XLOOKUP($A33,Sales!$A:$A,Sales!$T:$T+Sales!$U:$U+Sales!$V:$V,"0")-K33} -> 896 | Y33: =_xlfn.XLOOKUP($A33,Sales!$A:$A,Sales!$AJ:$AJ,"0") -> 0 | Z33: =_xlfn.XLOOKUP($A33,Sales!$A:$A,Sales!$AL:$AL,"0") -> 69.75 | AA33: =_xlfn.XLOOKUP($A33,Sales!$A:$A,Sales!$AO:$AO,"0") -> 48.95 | AB33: =O33+P33+Q33+S33 -> 3648.95 | AC33: =O33+P33+Q33+R33+S33+V33+W33+Y33+Z33+AA33+U33 -> 4756.07 | AD33: =N33-AC33 -> 0 | AE33: =_xlfn.XLOOKUP($A33,Sales!$A:$A,Sales!$Q:$Q,"0") -> -1.71 | AG33: 34793 | AH33: =VLOOKUP(AG33,Sales!A:V,20,FALSE) -> 896 | AI33: =VLOOKUP(AG33,Sales!A:U,21,FALSE) -> 0 | AJ33: =VLOOKUP(AG33,Sales!A:V,22,FALSE) -> 0 | AK33: =VLOOKUP(AG33,Sales!A:Q,17,FALSE) -> -1.71 | AL33: =SUMIF(A:A,AG33,W:W) -> 897.71 | AM33: =AL33-(AH33+AI33+AJ33)+AK33 -> 3.6415315e-14
A34: 36224 | C34: =_xlfn.XLOOKUP($A34,Sales!$A:$A,Sales!$D:$D,"0") -> 410.72 | D34: =SUM(H34+F34+E34-Z34,"0") -> 5217.4 | E34: =_xlfn.XLOOKUP($A34,Sales!$A:$A,Sales!$G:$G,"0") -> 142.86 | F34: =_xlfn.XLOOKUP($A34,Sales!$A:$A,Sales!$F:$F,"0") -> 0 | G34: =_xlfn.XLOOKUP($A34,Sales!$A:$A,Sales!$AP:$AP,"0") -> 8.86 | H34: =_xlfn.XLOOKUP($A34,Sales!$A:$A,Sales!$C:$C,"0") -> 5130.87 | I34: =C34 -> 410.72 | J34: =_xlfn.XLOOKUP($A34,Sales!$A:$A,Sales!$J:$J,"0") -> 10 | K34: =_xlfn.XLOOKUP($A34,Sales!$A:$A,Sales!$H:$H,"0") -> 0 | L34: 0 | M34: =_xlfn.XLOOKUP($A34,Sales!$A:$A,Sales!$AP:$AP,"0") -> 8.86 | N34: =H34+I34+J34+M34+L34-K34 -> 5560.45 | O34: =_xlfn.XLOOKUP($A34,Sales!$A:$A,Sales!$L:$L,"0") -> 590.68 | P34: =_xlfn.XLOOKUP($A34,Sales!$A:$A,Sales!$M:$M,"0") -> 3467.34 | Q34: =_xlfn.XLOOKUP($A34,Sales!$A:$A,Sales!$N:$N,"0") -> 56.43 | R34: =_xlfn.XLOOKUP($A34,Sales!$A:$A,Sales!$O:$O,"0") -> 70.05 | S34: =_xlfn.XLOOKUP($A34,Sales!$A:$A,Sales!$P:$P,"0") -> 0 | U34: =SUMIFS('EBT AMOUNTS'!I:I,'EBT AMOUNTS'!L:L,Conciliation!A34) -> 20.15 | V34: =_xlfn.XLOOKUP($A34,Sales!$A:$A,Sales!$I:$I,"0")*-1 -> 16.12 | W34: =_xlfn.XLOOKUP($A34,Sales!$A:$A,Sales!$Z:$Z,"0")-K34-U34 -> 667.31 | X34: {=_xlfn.XLOOKUP($A34,Sales!$A:$A,Sales!$T:$T+Sales!$U:$U+Sales!$V:$V,"0")-K34} -> 648.61 | Y34: =_xlfn.XLOOKUP($A34,Sales!$A:$A,Sales!$AJ:$AJ,"0") -> 50.37 | Z34: =_xlfn.XLOOKUP($A34,Sales!$A:$A,Sales!$AL:$AL,"0") -> 56.33 | AA34: =_xlfn.XLOOKUP($A34,Sales!$A:$A,Sales!$AO:$AO,"0") -> 565.67 | AB34: =O34+P34+Q34+S34 -> 4114.45 | AC34: =O34+P34+Q34+R34+S34+V34+W34+Y34+Z34+AA34+U34 -> 5560.45 | AD34: =N34-AC34 -> 0 | AE34: =_xlfn.XLOOKUP($A34,Sales!$A:$A,Sales!$Q:$Q,"0") -> -38.85 | AG34: 36224 | AH34: =VLOOKUP(AG34,Sales!A:V,20,FALSE) -> 648.61 | AI34: =VLOOKUP(AG34,Sales!A:U,21,FALSE) -> 0 | AJ34: =VLOOKUP(AG34,Sales!A:V,22,FALSE) -> 0 | AK34: =VLOOKUP(AG34,Sales!A:Q,17,FALSE) -> -38.85 | AL34: =SUMIF(A:A,AG34,W:W) -> 667.31 | AM34: =AL34-(AH34+AI34+AJ34)+AK34+U34 -> 4.2632564e-14
A35: 36225 | C35: =_xlfn.XLOOKUP($A35,Sales!$A:$A,Sales!$D:$D,"0") -> 0 | D35: =SUM(H35+F35+E35-Z35,"0") -> 0 | E35: =_xlfn.XLOOKUP($A35,Sales!$A:$A,Sales!$G:$G,"0") -> 0 | F35: =_xlfn.XLOOKUP($A35,Sales!$A:$A,Sales!$F:$F,"0") -> 0 | G35: =_xlfn.XLOOKUP($A35,Sales!$A:$A,Sales!$AP:$AP,"0") -> 0 | H35: =_xlfn.XLOOKUP($A35,Sales!$A:$A,Sales!$C:$C,"0") -> 0 | I35: =C35 -> 0 | J35: =_xlfn.XLOOKUP($A35,Sales!$A:$A,Sales!$J:$J,"0") -> 0 | K35: =_xlfn.XLOOKUP($A35,Sales!$A:$A,Sales!$H:$H,"0") -> 0 | L35: 0 | M35: =_xlfn.XLOOKUP($A35,Sales!$A:$A,Sales!$AP:$AP,"0") -> 0 | N35: =H35+I35+J35+M35+L35-K35 -> 0 | O35: =_xlfn.XLOOKUP($A35,Sales!$A:$A,Sales!$L:$L,"0") -> 0 | P35: =_xlfn.XLOOKUP($A35,Sales!$A:$A,Sales!$M:$M,"0") -> 0 | Q35: =_xlfn.XLOOKUP($A35,Sales!$A:$A,Sales!$N:$N,"0") -> 0 | R35: =_xlfn.XLOOKUP($A35,Sales!$A:$A,Sales!$O:$O,"0") -> 0 | S35: =_xlfn.XLOOKUP($A35,Sales!$A:$A,Sales!$P:$P,"0") -> 0 | V35: =_xlfn.XLOOKUP($A35,Sales!$A:$A,Sales!$I:$I,"0")*-1 -> 0 | W35: =_xlfn.XLOOKUP($A35,Sales!$A:$A,Sales!$Z:$Z,"0")-K35-U35 -> 0 | X35: {=_xlfn.XLOOKUP($A35,Sales!$A:$A,Sales!$T:$T+Sales!$U:$U+Sales!$V:$V,"0")-K35} -> 0 | Y35: =_xlfn.XLOOKUP($A35,Sales!$A:$A,Sales!$AJ:$AJ,"0") -> 0 | Z35: =_xlfn.XLOOKUP($A35,Sales!$A:$A,Sales!$AL:$AL,"0") -> 0 | AA35: =_xlfn.XLOOKUP($A35,Sales!$A:$A,Sales!$AO:$AO,"0") -> 0 | AB35: =O35+P35+Q35+S35 -> 0 | AC35: =O35+P35+Q35+R35+S35+V35+W35+Y35+Z35+AA35+U35 -> 0 | AD35: =N35-AC35 -> 0 | AE35: =_xlfn.XLOOKUP($A35,Sales!$A:$A,Sales!$Q:$Q,"0") -> 0 | AG35: 36225 | AH35: =VLOOKUP(AG35,Sales!A:V,20,FALSE) -> #N/A | AI35: =VLOOKUP(AG35,Sales!A:U,21,FALSE) -> #N/A | AJ35: =VLOOKUP(AG35,Sales!A:V,22,FALSE) -> #N/A | AK35: =VLOOKUP(AG35,Sales!A:Q,17,FALSE) -> #N/A | AL35: =SUMIF(A:A,AG35,W:W) -> 0
A36: 36433 | C36: =_xlfn.XLOOKUP($A36,Sales!$A:$A,Sales!$D:$D,"0") -> 0 | D36: =SUM(H36+F36+E36-Z36,"0") -> 0 | E36: =_xlfn.XLOOKUP($A36,Sales!$A:$A,Sales!$G:$G,"0") -> 0 | F36: =_xlfn.XLOOKUP($A36,Sales!$A:$A,Sales!$F:$F,"0") -> 0 | G36: =_xlfn.XLOOKUP($A36,Sales!$A:$A,Sales!$AP:$AP,"0") -> 0 | H36: =_xlfn.XLOOKUP($A36,Sales!$A:$A,Sales!$C:$C,"0") -> 0 | I36: =C36 -> 0 | J36: =_xlfn.XLOOKUP($A36,Sales!$A:$A,Sales!$J:$J,"0") -> 0 | K36: =_xlfn.XLOOKUP($A36,Sales!$A:$A,Sales!$H:$H,"0") -> 0 | L36: 0 | M36: =_xlfn.XLOOKUP($A36,Sales!$A:$A,Sales!$AP:$AP,"0") -> 0 | N36: =H36+I36+J36+M36+L36-K36 -> 0 | O36: =_xlfn.XLOOKUP($A36,Sales!$A:$A,Sales!$L:$L,"0") -> 0 | P36: =_xlfn.XLOOKUP($A36,Sales!$A:$A,Sales!$M:$M,"0") -> 0 | Q36: =_xlfn.XLOOKUP($A36,Sales!$A:$A,Sales!$N:$N,"0") -> 0 | R36: =_xlfn.XLOOKUP($A36,Sales!$A:$A,Sales!$O:$O,"0") -> 0 | S36: =_xlfn.XLOOKUP($A36,Sales!$A:$A,Sales!$P:$P,"0") -> 0 | V36: =_xlfn.XLOOKUP($A36,Sales!$A:$A,Sales!$I:$I,"0")*-1 -> 0 | W36: =_xlfn.XLOOKUP($A36,Sales!$A:$A,Sales!$Z:$Z,"0")-K36-U36 -> 0 | X36: {=_xlfn.XLOOKUP($A36,Sales!$A:$A,Sales!$T:$T+Sales!$U:$U+Sales!$V:$V,"0")-K36} -> 0 | Y36: =_xlfn.XLOOKUP($A36,Sales!$A:$A,Sales!$AJ:$AJ,"0") -> 0 | Z36: =_xlfn.XLOOKUP($A36,Sales!$A:$A,Sales!$AL:$AL,"0") -> 0 | AA36: =_xlfn.XLOOKUP($A36,Sales!$A:$A,Sales!$AO:$AO,"0") -> 0 | AB36: =O36+P36+Q36+S36 -> 0 | AC36: =O36+P36+Q36+R36+S36+V36+W36+Y36+Z36+AA36+U36 -> 0 | AD36: =N36-AC36 -> 0 | AE36: =_xlfn.XLOOKUP($A36,Sales!$A:$A,Sales!$Q:$Q,"0") -> 0 | AG36: 36433 | AM36: =AL36-(AH36+AI36+AJ36)+AK36 -> 0
A37: 36930 | C37: =_xlfn.XLOOKUP($A37,Sales!$A:$A,Sales!$D:$D,"0") -> 0 | D37: =SUM(H37+F37+E37-Z37,"0") -> 0 | E37: =_xlfn.XLOOKUP($A37,Sales!$A:$A,Sales!$G:$G,"0") -> 0 | F37: =_xlfn.XLOOKUP($A37,Sales!$A:$A,Sales!$F:$F,"0") -> 0 | G37: =_xlfn.XLOOKUP($A37,Sales!$A:$A,Sales!$AP:$AP,"0") -> 0 | H37: =_xlfn.XLOOKUP($A37,Sales!$A:$A,Sales!$C:$C,"0") -> 0 | I37: =C37 -> 0 | J37: =_xlfn.XLOOKUP($A37,Sales!$A:$A,Sales!$J:$J,"0") -> 0 | K37: =_xlfn.XLOOKUP($A37,Sales!$A:$A,Sales!$H:$H,"0") -> 0 | L37: 0 | M37: =_xlfn.XLOOKUP($A37,Sales!$A:$A,Sales!$AP:$AP,"0") -> 0 | N37: =H37+I37+J37+M37+L37-K37 -> 0 | O37: =_xlfn.XLOOKUP($A37,Sales!$A:$A,Sales!$L:$L,"0") -> 0 | P37: =_xlfn.XLOOKUP($A37,Sales!$A:$A,Sales!$M:$M,"0") -> 0 | Q37: =_xlfn.XLOOKUP($A37,Sales!$A:$A,Sales!$N:$N,"0") -> 0 | R37: =_xlfn.XLOOKUP($A37,Sales!$A:$A,Sales!$O:$O,"0") -> 0 | S37: =_xlfn.XLOOKUP($A37,Sales!$A:$A,Sales!$P:$P,"0") -> 0 | V37: =_xlfn.XLOOKUP($A37,Sales!$A:$A,Sales!$I:$I,"0")*-1 -> 0 | W37: =_xlfn.XLOOKUP($A37,Sales!$A:$A,Sales!$Z:$Z,"0")-K37-U37 -> 0 | X37: {=_xlfn.XLOOKUP($A37,Sales!$A:$A,Sales!$T:$T+Sales!$U:$U+Sales!$V:$V,"0")-K37} -> 0 | Y37: =_xlfn.XLOOKUP($A37,Sales!$A:$A,Sales!$AJ:$AJ,"0") -> 0 | Z37: =_xlfn.XLOOKUP($A37,Sales!$A:$A,Sales!$AL:$AL,"0") -> 0 | AA37: =_xlfn.XLOOKUP($A37,Sales!$A:$A,Sales!$AO:$AO,"0") -> 0 | AB37: =O37+P37+Q37+S37 -> 0 | AC37: =O37+P37+Q37+R37+S37+V37+W37+Y37+Z37+AA37+U37 -> 0 | AD37: =N37-AC37 -> 0 | AE37: =_xlfn.XLOOKUP($A37,Sales!$A:$A,Sales!$Q:$Q,"0") -> 0 | AG37: 36930 | AM37: =AL37-(AH37+AI37+AJ37)+AK37 -> 0
A38: 37014 | C38: =_xlfn.XLOOKUP($A38,Sales!$A:$A,Sales!$D:$D,"0") -> 335.96 | D38: =SUM(H38+F38+E38-Z38,"0") -> 4144.28 | E38: =_xlfn.XLOOKUP($A38,Sales!$A:$A,Sales!$G:$G,"0") -> 71.64 | F38: =_xlfn.XLOOKUP($A38,Sales!$A:$A,Sales!$F:$F,"0") -> 0 | G38: =_xlfn.XLOOKUP($A38,Sales!$A:$A,Sales!$AP:$AP,"0") -> 5.82 | H38: =_xlfn.XLOOKUP($A38,Sales!$A:$A,Sales!$C:$C,"0") -> 4072.64 | I38: =C38 -> 335.96 | J38: =_xlfn.XLOOKUP($A38,Sales!$A:$A,Sales!$J:$J,"0") -> 0 | K38: =_xlfn.XLOOKUP($A38,Sales!$A:$A,Sales!$H:$H,"0") -> 0 | L38: 0 | M38: =_xlfn.XLOOKUP($A38,Sales!$A:$A,Sales!$AP:$AP,"0") -> 5.82 | N38: =H38+I38+J38+M38+L38-K38 -> 4414.42 | O38: =_xlfn.XLOOKUP($A38,Sales!$A:$A,Sales!$L:$L,"0") -> 422.04 | P38: =_xlfn.XLOOKUP($A38,Sales!$A:$A,Sales!$M:$M,"0") -> 2679.96 | Q38: =_xlfn.XLOOKUP($A38,Sales!$A:$A,Sales!$N:$N,"0") -> 81.73 | R38: =_xlfn.XLOOKUP($A38,Sales!$A:$A,Sales!$O:$O,"0") -> 45.3 | S38: =_xlfn.XLOOKUP($A38,Sales!$A:$A,Sales!$P:$P,"0") -> 0 | V38: =_xlfn.XLOOKUP($A38,Sales!$A:$A,Sales!$I:$I,"0")*-1 -> 15.89 | W38: =_xlfn.XLOOKUP($A38,Sales!$A:$A,Sales!$Z:$Z,"0")-K38-U38 -> 1169.5 | X38: {=_xlfn.XLOOKUP($A38,Sales!$A:$A,Sales!$T:$T+Sales!$U:$U+Sales!$V:$V,"0")-K38} -> 1168 | Y38: =_xlfn.XLOOKUP($A38,Sales!$A:$A,Sales!$AJ:$AJ,"0") -> 0 | Z38: =_xlfn.XLOOKUP($A38,Sales!$A:$A,Sales!$AL:$AL,"0") -> 0 | AA38: =_xlfn.XLOOKUP($A38,Sales!$A:$A,Sales!$AO:$AO,"0") -> 0 | AB38: =O38+P38+Q38+S38 -> 3183.73 | AC38: =O38+P38+Q38+R38+S38+V38+W38+Y38+Z38+AA38+U38 -> 4414.42 | AD38: =N38-AC38 -> 0 | AE38: =_xlfn.XLOOKUP($A38,Sales!$A:$A,Sales!$Q:$Q,"0") -> -1.5 | AG38: 37014 | AH38: =VLOOKUP(AG38,Sales!A:V,20,FALSE) -> 1168 | AI38: =VLOOKUP(AG38,Sales!A:U,21,FALSE) -> 0 | AJ38: =VLOOKUP(AG38,Sales!A:V,22,FALSE) -> 0 | AK38: =VLOOKUP(AG38,Sales!A:Q,17,FALSE) -> -1.5 | AL38: =SUMIF(A:A,AG38,W:W) -> 1169.5 | AM38: =AL38-(AH38+AI38+AJ38)+AK38 -> 0
A39: 37171 | C39: =_xlfn.XLOOKUP($A39,Sales!$A:$A,Sales!$D:$D,"0") -> 290.26 | D39: =SUM(H39+F39+E39-Z39,"0") -> 3328.66 | E39: =_xlfn.XLOOKUP($A39,Sales!$A:$A,Sales!$G:$G,"0") -> 95.02 | F39: =_xlfn.XLOOKUP($A39,Sales!$A:$A,Sales!$F:$F,"0") -> 0 | G39: =_xlfn.XLOOKUP($A39,Sales!$A:$A,Sales!$AP:$AP,"0") -> 13.74 | H39: =_xlfn.XLOOKUP($A39,Sales!$A:$A,Sales!$C:$C,"0") -> 3325.13 | I39: =C39 -> 290.26 | J39: =_xlfn.XLOOKUP($A39,Sales!$A:$A,Sales!$J:$J,"0") -> 0 | K39: =_xlfn.XLOOKUP($A39,Sales!$A:$A,Sales!$H:$H,"0") -> 0 | L39: 0 | M39: =_xlfn.XLOOKUP($A39,Sales!$A:$A,Sales!$AP:$AP,"0") -> 13.74 | N39: =H39+I39+J39+M39+L39-K39 -> 3629.13 | O39: =_xlfn.XLOOKUP($A39,Sales!$A:$A,Sales!$L:$L,"0") -> 409.77 | P39: =_xlfn.XLOOKUP($A39,Sales!$A:$A,Sales!$M:$M,"0") -> 1857.32 | Q39: =_xlfn.XLOOKUP($A39,Sales!$A:$A,Sales!$N:$N,"0") -> 27.95 | R39: =_xlfn.XLOOKUP($A39,Sales!$A:$A,Sales!$O:$O,"0") -> 5.97 | S39: =_xlfn.XLOOKUP($A39,Sales!$A:$A,Sales!$P:$P,"0") -> 0 | V39: =_xlfn.XLOOKUP($A39,Sales!$A:$A,Sales!$I:$I,"0")*-1 -> 15 | W39: =_xlfn.XLOOKUP($A39,Sales!$A:$A,Sales!$Z:$Z,"0")-K39-U39 -> 1055.79 | X39: {=_xlfn.XLOOKUP($A39,Sales!$A:$A,Sales!$T:$T+Sales!$U:$U+Sales!$V:$V,"0")-K39} -> 1055 | Y39: =_xlfn.XLOOKUP($A39,Sales!$A:$A,Sales!$AJ:$AJ,"0") -> 0 | Z39: =_xlfn.XLOOKUP($A39,Sales!$A:$A,Sales!$AL:$AL,"0") -> 91.49 | AA39: =_xlfn.XLOOKUP($A39,Sales!$A:$A,Sales!$AO:$AO,"0") -> 165.84 | AB39: =O39+P39+Q39+S39 -> 2295.04 | AC39: =O39+P39+Q39+R39+S39+V39+W39+Y39+Z39+AA39+U39 -> 3629.13 | AD39: =N39-AC39 -> 0 | AE39: =_xlfn.XLOOKUP($A39,Sales!$A:$A,Sales!$Q:$Q,"0") -> -0.79 | AG39: 37171 | AH39: =VLOOKUP(AG39,Sales!A:V,20,FALSE) -> 1055 | AI39: =VLOOKUP(AG39,Sales!A:U,21,FALSE) -> 0 | AJ39: =VLOOKUP(AG39,Sales!A:V,22,FALSE) -> 0 | AK39: =VLOOKUP(AG39,Sales!A:Q,17,FALSE) -> -0.79 | AL39: =SUMIF(A:A,AG39,W:W) -> 1055.79 | AM39: =AL39-(AH39+AI39+AJ39)+AK39 -> -3.6415315e-14
A40: 37718 | C40: =_xlfn.XLOOKUP($A40,Sales!$A:$A,Sales!$D:$D,"0") -> 0 | D40: =SUM(H40+F40+E40-Z40,"0") -> 3885.7 | E40: =_xlfn.XLOOKUP($A40,Sales!$A:$A,Sales!$G:$G,"0") -> 99.02 | F40: =_xlfn.XLOOKUP($A40,Sales!$A:$A,Sales!$F:$F,"0") -> 0 | G40: =_xlfn.XLOOKUP($A40,Sales!$A:$A,Sales!$AP:$AP,"0") -> 1.31 | H40: =_xlfn.XLOOKUP($A40,Sales!$A:$A,Sales!$C:$C,"0") -> 3799.11 | I40: =C40 -> 0 | J40: =_xlfn.XLOOKUP($A40,Sales!$A:$A,Sales!$J:$J,"0") -> 0 | K40: =_xlfn.XLOOKUP($A40,Sales!$A:$A,Sales!$H:$H,"0") -> 0 | L40: 0 | M40: =_xlfn.XLOOKUP($A40,Sales!$A:$A,Sales!$AP:$AP,"0") -> 1.31 | N40: =H40+I40+J40+M40+L40-K40 -> 3800.42 | O40: =_xlfn.XLOOKUP($A40,Sales!$A:$A,Sales!$L:$L,"0") -> 717.12 | P40: =_xlfn.XLOOKUP($A40,Sales!$A:$A,Sales!$M:$M,"0") -> 2220.89 | Q40: =_xlfn.XLOOKUP($A40,Sales!$A:$A,Sales!$N:$N,"0") -> 0 | R40: =_xlfn.XLOOKUP($A40,Sales!$A:$A,Sales!$O:$O,"0") -> 58.3 | S40: =_xlfn.XLOOKUP($A40,Sales!$A:$A,Sales!$P:$P,"0") -> 0 | V40: =_xlfn.XLOOKUP($A40,Sales!$A:$A,Sales!$I:$I,"0")*-1 -> 5.38 | W40: =_xlfn.XLOOKUP($A40,Sales!$A:$A,Sales!$Z:$Z,"0")-K40-U40 -> 597.03 | X40: {=_xlfn.XLOOKUP($A40,Sales!$A:$A,Sales!$T:$T+Sales!$U:$U+Sales!$V:$V,"0")-K40} -> 602 | Y40: =_xlfn.XLOOKUP($A40,Sales!$A:$A,Sales!$AJ:$AJ,"0") -> 0 | Z40: =_xlfn.XLOOKUP($A40,Sales!$A:$A,Sales!$AL:$AL,"0") -> 12.43 | AA40: =_xlfn.XLOOKUP($A40,Sales!$A:$A,Sales!$AO:$AO,"0") -> 189.27 | AB40: =O40+P40+Q40+S40 -> 2938.01 | AC40: =O40+P40+Q40+R40+S40+V40+W40+Y40+Z40+AA40+U40 -> 3800.42 | AD40: =N40-AC40 -> 0 | AE40: =_xlfn.XLOOKUP($A40,Sales!$A:$A,Sales!$Q:$Q,"0") -> 4.97 | AG40: 37718 | AH40: =VLOOKUP(AG40,Sales!A:V,20,FALSE) -> 602 | AI40: =VLOOKUP(AG40,Sales!A:U,21,FALSE) -> 0 | AJ40: =VLOOKUP(AG40,Sales!A:V,22,FALSE) -> 0 | AK40: =VLOOKUP(AG40,Sales!A:Q,17,FALSE) -> 4.97 | AL40: =SUMIF(A:A,AG40,W:W) -> 597.03 | AM40: =AL40-(AH40+AI40+AJ40)+AK40 -> -2.7533531e-14
A41: 37732 | C41: =_xlfn.XLOOKUP($A41,Sales!$A:$A,Sales!$D:$D,"0") -> 433.88 | D41: =SUM(H41+F41+E41-Z41,"0") -> 5359.01 | E41: =_xlfn.XLOOKUP($A41,Sales!$A:$A,Sales!$G:$G,"0") -> 176.73 | F41: =_xlfn.XLOOKUP($A41,Sales!$A:$A,Sales!$F:$F,"0") -> 0 | G41: =_xlfn.XLOOKUP($A41,Sales!$A:$A,Sales!$AP:$AP,"0") -> 11.97 | H41: =_xlfn.XLOOKUP($A41,Sales!$A:$A,Sales!$C:$C,"0") -> 5233.61 | I41: =C41 -> 433.88 | J41: =_xlfn.XLOOKUP($A41,Sales!$A:$A,Sales!$J:$J,"0") -> 0 | K41: =_xlfn.XLOOKUP($A41,Sales!$A:$A,Sales!$H:$H,"0") -> 0 | L41: 0 | M41: =_xlfn.XLOOKUP($A41,Sales!$A:$A,Sales!$AP:$AP,"0") -> 11.97 | N41: =H41+I41+J41+M41+L41-K41 -> 5679.46 | O41: =_xlfn.XLOOKUP($A41,Sales!$A:$A,Sales!$L:$L,"0") -> 668.14 | P41: =_xlfn.XLOOKUP($A41,Sales!$A:$A,Sales!$M:$M,"0") -> 3059.33 | Q41: =_xlfn.XLOOKUP($A41,Sales!$A:$A,Sales!$N:$N,"0") -> 166.27 | R41: =_xlfn.XLOOKUP($A41,Sales!$A:$A,Sales!$O:$O,"0") -> 217.7 | S41: =_xlfn.XLOOKUP($A41,Sales!$A:$A,Sales!$P:$P,"0") -> 0 | V41: =_xlfn.XLOOKUP($A41,Sales!$A:$A,Sales!$I:$I,"0")*-1 -> 20.29 | W41: =_xlfn.XLOOKUP($A41,Sales!$A:$A,Sales!$Z:$Z,"0")-K41-U41 -> 715.01 | X41: {=_xlfn.XLOOKUP($A41,Sales!$A:$A,Sales!$T:$T+Sales!$U:$U+Sales!$V:$V,"0")-K41} -> 715 | Y41: =_xlfn.XLOOKUP($A41,Sales!$A:$A,Sales!$AJ:$AJ,"0") -> 19.14 | Z41: =_xlfn.XLOOKUP($A41,Sales!$A:$A,Sales!$AL:$AL,"0") -> 51.33 | AA41: =_xlfn.XLOOKUP($A41,Sales!$A:$A,Sales!$AO:$AO,"0") -> 762.25 | AB41: =O41+P41+Q41+S41 -> 3893.74 | AC41: =O41+P41+Q41+R41+S41+V41+W41+Y41+Z41+AA41+U41 -> 5679.46 | AD41: =N41-AC41 -> 0 | AE41: =_xlfn.XLOOKUP($A41,Sales!$A:$A,Sales!$Q:$Q,"0") -> -0.01 | AG41: 37732 | AH41: =VLOOKUP(AG41,Sales!A:V,20,FALSE) -> 715 | AI41: =VLOOKUP(AG41,Sales!A:U,21,FALSE) -> 0 | AJ41: =VLOOKUP(AG41,Sales!A:V,22,FALSE) -> 0 | AK41: =VLOOKUP(AG41,Sales!A:Q,17,FALSE) -> -0.01 | AL41: =SUMIF(A:A,AG41,W:W) -> 715.01 | AM41: =AL41-(AH41+AI41+AJ41)+AK41 -> -9.0951552e-15
A42: 40404 | C42: =_xlfn.XLOOKUP($A42,Sales!$A:$A,Sales!$D:$D,"0") -> 0 | D42: =SUM(H42+F42+E42-Z42,"0") -> 6092.45 | E42: =_xlfn.XLOOKUP($A42,Sales!$A:$A,Sales!$G:$G,"0") -> 272.95 | F42: =_xlfn.XLOOKUP($A42,Sales!$A:$A,Sales!$F:$F,"0") -> 5.58 | G42: =_xlfn.XLOOKUP($A42,Sales!$A:$A,Sales!$AP:$AP,"0") -> 12.44 | H42: =_xlfn.XLOOKUP($A42,Sales!$A:$A,Sales!$C:$C,"0") -> 6086.02 | I42: =C42 -> 0 | J42: =_xlfn.XLOOKUP($A42,Sales!$A:$A,Sales!$J:$J,"0") -> 0 | K42: =_xlfn.XLOOKUP($A42,Sales!$A:$A,Sales!$H:$H,"0") -> 0 | L42: 0 | M42: =_xlfn.XLOOKUP($A42,Sales!$A:$A,Sales!$AP:$AP,"0") -> 12.44 | N42: =H42+I42+J42+M42+L42-K42 -> 6098.46 | O42: =_xlfn.XLOOKUP($A42,Sales!$A:$A,Sales!$L:$L,"0") -> 653.31 | P42: =_xlfn.XLOOKUP($A42,Sales!$A:$A,Sales!$M:$M,"0") -> 3578.68 | Q42: =_xlfn.XLOOKUP($A42,Sales!$A:$A,Sales!$N:$N,"0") -> 73.08 | R42: =_xlfn.XLOOKUP($A42,Sales!$A:$A,Sales!$O:$O,"0") -> 78.98 | S42: =_xlfn.XLOOKUP($A42,Sales!$A:$A,Sales!$P:$P,"0") -> 0 | V42: =_xlfn.XLOOKUP($A42,Sales!$A:$A,Sales!$I:$I,"0")*-1 -> 18.56 | W42: =_xlfn.XLOOKUP($A42,Sales!$A:$A,Sales!$Z:$Z,"0")-K42-U42 -> 973.36 | X42: {=_xlfn.XLOOKUP($A42,Sales!$A:$A,Sales!$T:$T+Sales!$U:$U+Sales!$V:$V,"0")-K42} -> 966 | Y42: =_xlfn.XLOOKUP($A42,Sales!$A:$A,Sales!$AJ:$AJ,"0") -> 37.25 | Z42: =_xlfn.XLOOKUP($A42,Sales!$A:$A,Sales!$AL:$AL,"0") -> 272.1 | AA42: =_xlfn.XLOOKUP($A42,Sales!$A:$A,Sales!$AO:$AO,"0") -> 413.14 | AB42: =O42+P42+Q42+S42 -> 4305.07 | AC42: =O42+P42+Q42+R42+S42+V42+W42+Y42+Z42+AA42+U42 -> 6098.46 | AD42: 0 | AE42: =_xlfn.XLOOKUP($A42,Sales!$A:$A,Sales!$Q:$Q,"0") -> -7.36 | AG42: 40404 | AH42: =VLOOKUP(AG42,Sales!A:V,20,FALSE) -> 966 | AI42: =VLOOKUP(AG42,Sales!A:U,21,FALSE) -> 0 | AJ42: =VLOOKUP(AG42,Sales!A:V,22,FALSE) -> 0 | AK42: =VLOOKUP(AG42,Sales!A:Q,17,FALSE) -> -7.36 | AL42: =SUMIF(A:A,AG42,W:W) -> 973.36 | AM42: =AL42-(AH42+AI42+AJ42)+AK42 -> 1.3322676e-14
A43: 33444 | C43: =_xlfn.XLOOKUP($A43,Sales!$A:$A,Sales!$D:$D,"0") -> 187.74 | D43: =SUM(H43+F43+E43-Z43,"0") -> 2655.54 | E43: =_xlfn.XLOOKUP($A43,Sales!$A:$A,Sales!$G:$G,"0") -> 65.95 | F43: =_xlfn.XLOOKUP($A43,Sales!$A:$A,Sales!$F:$F,"0") -> 0 | G43: =_xlfn.XLOOKUP($A43,Sales!$A:$A,Sales!$AP:$AP,"0") -> 7.45 | H43: =_xlfn.XLOOKUP($A43,Sales!$A:$A,Sales!$C:$C,"0") -> 2589.59 | I43: =C43 -> 187.74 | J43: =_xlfn.XLOOKUP($A43,Sales!$A:$A,Sales!$J:$J,"0") -> 0 | K43: =_xlfn.XLOOKUP($A43,Sales!$A:$A,Sales!$H:$H,"0") -> 0 | L43: 0 | M43: =_xlfn.XLOOKUP($A43,Sales!$A:$A,Sales!$AP:$AP,"0") -> 7.45 | N43: =H43+I43+J43+M43+L43-K43 -> 2784.78 | O43: =_xlfn.XLOOKUP($A43,Sales!$A:$A,Sales!$L:$L,"0") -> 313.73 | P43: =_xlfn.XLOOKUP($A43,Sales!$A:$A,Sales!$M:$M,"0") -> 1845.18 | Q43: =_xlfn.XLOOKUP($A43,Sales!$A:$A,Sales!$N:$N,"0") -> 43.36 | R43: =_xlfn.XLOOKUP($A43,Sales!$A:$A,Sales!$O:$O,"0") -> 0 | S43: =_xlfn.XLOOKUP($A43,Sales!$A:$A,Sales!$P:$P,"0") -> 0 | V43: =_xlfn.XLOOKUP($A43,Sales!$A:$A,Sales!$I:$I,"0")*-1 -> 0 | W43: =_xlfn.XLOOKUP($A43,Sales!$A:$A,Sales!$Z:$Z,"0")-K43-U43 -> 582.51 | X43: {=_xlfn.XLOOKUP($A43,Sales!$A:$A,Sales!$T:$T+Sales!$U:$U+Sales!$V:$V,"0")-K43} -> 582 | Y43: =_xlfn.XLOOKUP($A43,Sales!$A:$A,Sales!$AJ:$AJ,"0") -> 0 | Z43: =_xlfn.XLOOKUP($A43,Sales!$A:$A,Sales!$AL:$AL,"0") -> 0 | AA43: =_xlfn.XLOOKUP($A43,Sales!$A:$A,Sales!$AO:$AO,"0") -> 0 | AB43: =O43+P43+Q43+S43 -> 2202.27 | AC43: =O43+P43+Q43+R43+S43+V43+W43+Y43+Z43+AA43+U43 -> 2784.78 | AD43: 0 | AE43: =_xlfn.XLOOKUP($A43,Sales!$A:$A,Sales!$Q:$Q,"0") -> -0.51 | AG43: 33444 | AH43: =VLOOKUP(AG43,Sales!A:V,20,FALSE) -> 582 | AI43: =VLOOKUP(AG43,Sales!A:U,21,FALSE) -> 0 | AJ43: =VLOOKUP(AG43,Sales!A:V,22,FALSE) -> 0 | AK43: =VLOOKUP(AG43,Sales!A:Q,17,FALSE) -> -0.51 | AL43: =SUMIF(A:A,AG43,W:W) -> 582.51 | AM43: =AL43-(AH43+AI43+AJ43)+AK43 -> -9.1038288e-15
C45: =SUM(C2:C44) -> 7759.55 | D45: =SUM(D2:D44) -> 273718.16 | E45: =SUM(E2:E44) -> 9697.43 | F45: =SUM(F2:F44) -> 459.3 | G45: =SUM(G2:G44) -> 632.53 | H45: =SUM(H2:H44) -> 277859.94 | I45: =SUM(I2:I44) -> 7759.55 | J45: =SUM(J2:J44) -> 95 | ... S45: =SUM(S2:S44) -> 0 | U45: =SUM(U2:U44) -> 285.78 | V45: =SUM(V2:V44) -> 996.24 | W45: =SUM(W2:W44) -> 44023.13 | X45: =SUM(X2:X44) -> 41647.19 | Y45: =SUM(Y2:Y44) -> 3398.11 | Z45: =SUM(Z2:Z44) -> 14298.51 | AA45: =SUM(AA2:AA44) -> 28895.07 | AB45: =SUM(AB2:AB44) -> 190155.11 | ... AD45: =SUM(AD2:AD44) -> 0 | AM45: =SUM(AM2:AM41) -> -9

Sheet Tax Review
A1: Store no. | B1: May | C1: Net Sales | D1: Discounts | F1: TAXABLE SALES | G1: TAX CALCULATION | I1: Sales Tax Payable | J1: DIFFERRENCE | L1: RATE CALCULATION | M1: DIFFERRENCE
A2: 28841 | B2: 0.08125 | C2: =VLOOKUP(A2,Conciliation!A:H,8,) -> 4931.78 | D2: =VLOOKUP(A2,Conciliation!A:E,5,) -> 151.86 | F2: =C2 -> 4931.78 | G2: =F2*B2 -> 400.70713 | I2: =VLOOKUP(A2,Conciliation!A:C,3,) -> 392.96 | J2: =G2-I2 -> 7.747125 | L2: =I2/F2 -> 0.079679142 | M2: =B2-L2 -> 0.0015708578
A3: 28842 | B3: 0.08375 | C3: =VLOOKUP(A3,Conciliation!A:H,8,) -> 6909.03 | D3: =VLOOKUP(A3,Conciliation!A:E,5,) -> 202.13 | F3: =C3 -> 6909.03 | G3: =F3*B3 -> 578.63126 | I3: =VLOOKUP(A3,Conciliation!A:C,3,) -> 567.13 | J3: =G3-I3 -> 11.501263 | L3: =I3/F3 -> 0.082085329 | M3: =B3-L3 -> 0.0016646711
A4: 28843 | B4: 0.09125 | C4: =VLOOKUP(A4,Conciliation!A:H,8,) -> 5394.89 | D4: =VLOOKUP(A4,Conciliation!A:E,5,) -> 164.27 | F4: =C4 -> 5394.89 | G4: =F4*B4 -> 492.28371 | I4: =VLOOKUP(A4,Conciliation!A:C,3,) -> 482.66 | J4: =G4-I4 -> 9.6237125 | L4: =I4/F4 -> 0.089466143 | M4: =B4-L4 -> 0.001783857
A5: 28844 | B5: 0.08 | C5: =VLOOKUP(A5,Conciliation!A:H,8,) -> 10050.16 | D5: =VLOOKUP(A5,Conciliation!A:E,5,) -> 315.18 | F5: =C5 -> 10050.16 | G5: =F5*B5 -> 804.0128 | I5: =VLOOKUP(A5,Conciliation!A:C,3,) -> 794.81 | J5: =G5-I5 -> 9.2028 | L5: =I5/F5 -> 0.079084313 | M5: =B5-L5 -> 0.00091568691
A6: 28845 | B6: 0.08125 | C6: =VLOOKUP(A6,Conciliation!A:H,8,) -> 9685.93 | D6: =VLOOKUP(A6,Conciliation!A:E,5,) -> 298.4 | F6: =C6 -> 9685.93 | G6: =F6*B6 -> 786.98181 | I6: =VLOOKUP(A6,Conciliation!A:C,3,) -> 776.16 | J6: =G6-I6 -> 10.821813 | L6: =I6/F6 -> 0.080132729 | M6: =B6-L6 -> 0.0011172714
A7: 28846 | B7: 0.08375 | C7: =VLOOKUP(A7,Conciliation!A:H,8,) -> 7920.15 | D7: =VLOOKUP(A7,Conciliation!A:E,5,) -> 238 | F7: =C7 -> 7920.15 | G7: =F7*B7 -> 663.31256 | I7: =VLOOKUP(A7,Conciliation!A:C,3,) -> 628.61 | J7: =G7-I7 -> 34.702562 | L7: =I7/F7 -> 0.079368446 | M7: =B7-L7 -> 0.0043815537
A8: 30256 | B8: 0.08125 | C8: =VLOOKUP(A8,Conciliation!A:H,8,) -> 5789.49 | D8: =VLOOKUP(A8,Conciliation!A:E,5,) -> 124.31 | F8: =C8 -> 5789.49 | G8: =F8*B8 -> 470.39606 | I8: =VLOOKUP(A8,Conciliation!A:C,3,) -> 463.5 | J8: =G8-I8 -> 6.8960625 | L8: =I8/F8 -> 0.080058865 | M8: =B8-L8 -> 0.0011911347
A9: 36224 | B9: 0.08125 | C9: =VLOOKUP(A9,Conciliation!A:H,8,) -> 5130.87 | D9: =VLOOKUP(A9,Conciliation!A:E,5,) -> 142.86 | F9: =C9 -> 5130.87 | G9: =F9*B9 -> 416.88319 | I9: =VLOOKUP(A9,Conciliation!A:C,3,) -> 410.72 | J9: =G9-I9 -> 6.1631875 | L9: =I9/F9 -> 0.080048803 | M9: =B9-L9 -> 0.0012011974
A10: 37014 | B10: 0.0825 | C10: =VLOOKUP(A10,Conciliation!A:H,8,) -> 4072.64 | D10: =VLOOKUP(A10,Conciliation!A:E,5,) -> 71.64 | F10: =C10 -> 4072.64 | G10: =F10*B10 -> 335.9928 | I10: =VLOOKUP(A10,Conciliation!A:C,3,) -> 335.96 | J10: =G10-I10 -> 0.0328 | L10: =I10/F10 -> 0.082491946 | M10: =B10-L10 -> 8.053744e-06
A11: 37732 | B11: 0.08375 | C11: =VLOOKUP(A11,Conciliation!A:H,8,) -> 5233.61 | D11: =VLOOKUP(A11,Conciliation!A:E,5,) -> 176.73 | F11: =C11 -> 5233.61 | G11: =F11*B11 -> 438.31484 | I11: =VLOOKUP(A11,Conciliation!A:C,3,) -> 433.88 | J11: =G11-I11 -> 4.4348375 | L11: =I11/F11 -> 0.082902624 | M11: =B11-L11 -> 0.00084737638
A12: 30491 | B12: 0.0875 | C12: =VLOOKUP(A12,Conciliation!A:H,8,) -> 4455.23 | D12: =VLOOKUP(A12,Conciliation!A:E,5,) -> 201.65 | F12: =C12 -> 4455.23 | G12: =F12*B12 -> 389.83262 | I12: =VLOOKUP(A12,Conciliation!A:C,3,) -> 389.13 | J12: =G12-I12 -> 0.702625 | L12: =I12/F12 -> 0.087342292 | M12: =B12-L12 -> 0.00015770791
A13: 29423 | B13: 0.0825 | C13: =VLOOKUP(A13,Conciliation!A:H,8,) -> 4437.27 | D13: =VLOOKUP(A13,Conciliation!A:E,5,) -> 70.6 | F13: =C13 -> 4437.27 | G13: =F13*B13 -> 366.07478 | I13: =VLOOKUP(A13,Conciliation!A:C,3,) -> 364.8 | J13: =G13-I13 -> 1.274775 | L13: =I13/F13 -> 0.082212712 | M13: =B13-L13 -> 0.00028728813
... A19: 32952 | B19: 0.079 | C19: =VLOOKUP(A19,Conciliation!A:H,8,) -> 5845.93 | D19: =VLOOKUP(A19,Conciliation!A:E,5,) -> 127.55 | F19: =C19 -> 5845.93 | G19: =F19*B19 -> 461.82847 | I19: =VLOOKUP(A19,Conciliation!A:C,3,) -> 440.07 | J19: =G19-I19 -> 21.75847 | L19: =I19/F19 -> 0.075278014 | M19: =B19-L19 -> 0.0037219861

Sheet Daily Sales Taco Bell  RED
A1: JOURNAL | B1: DATE | C1: LINE_NO
A2: SJ | B2: 46091 | C2: 1 | D2: POS Data Upload Sabretooth | E2: Gross Food Sales | G2: 400200 | H2: 28841 | J2: =_xlfn.XLOOKUP($H2,Conciliation!$A:$A,Conciliation!$D:$D,"0") -> 5040.05 | L2: =SUM(I:I) -> 296503.75 | M2: =L2-L3 -> 0
C3: 2 | D3: POS Data Upload Sabretooth | E3: Gross Food Sales | G3: 400200 | H3: 28842 | J3: =_xlfn.XLOOKUP($H3,Conciliation!$A:$A,Conciliation!$D:$D,"0") -> 6973.73 | L3: =SUM(J:J) -> 296503.75
C4: 3 | D4: POS Data Upload Sabretooth | E4: Gross Food Sales | G4: 400200 | H4: 28843 | J4: =_xlfn.XLOOKUP($H4,Conciliation!$A:$A,Conciliation!$D:$D,"0") -> 5473.4
C5: 4 | D5: POS Data Upload Sabretooth | E5: Gross Food Sales | G5: 400200 | H5: 28844 | J5: =_xlfn.XLOOKUP($H5,Conciliation!$A:$A,Conciliation!$D:$D,"0") -> 10252.94
C6: 5 | D6: POS Data Upload Sabretooth | E6: Gross Food Sales | G6: 400200 | H6: 28845 | J6: =_xlfn.XLOOKUP($H6,Conciliation!$A:$A,Conciliation!$D:$D,"0") -> 9879.26
C7: 6 | D7: POS Data Upload Sabretooth | E7: Gross Food Sales | G7: 400200 | H7: 28846 | J7: =_xlfn.XLOOKUP($H7,Conciliation!$A:$A,Conciliation!$D:$D,"0") -> 7855.45
C8: 7 | D8: POS Data Upload Sabretooth | E8: Gross Food Sales | G8: 400200 | H8: 29423 | J8: =_xlfn.XLOOKUP($H8,Conciliation!$A:$A,Conciliation!$D:$D,"0") -> 4491.12
C9: 8 | D9: POS Data Upload Sabretooth | E9: Gross Food Sales | G9: 400200 | H9: 30256 | J9: =_xlfn.XLOOKUP($H9,Conciliation!$A:$A,Conciliation!$D:$D,"0") -> 5861.52
C10: 9 | D10: POS Data Upload Sabretooth | E10: Gross Food Sales | G10: 400200 | H10: 30491 | J10: =_xlfn.XLOOKUP($H10,Conciliation!$A:$A,Conciliation!$D:$D,"0") -> 4656.88
C11: 10 | D11: POS Data Upload Sabretooth | E11: Gross Food Sales | G11: 400200 | H11: 32680 | J11: =_xlfn.XLOOKUP($H11,Conciliation!$A:$A,Conciliation!$D:$D,"0") -> 5279.46
C12: 11 | D12: POS Data Upload Sabretooth | E12: Gross Food Sales | G12: 400200 | H12: 32932 | J12: =_xlfn.XLOOKUP($H12,Conciliation!$A:$A,Conciliation!$D:$D,"0") -> 6625.5
C13: 12 | D13: POS Data Upload Sabretooth | E13: Gross Food Sales | G13: 400200 | H13: 32933 | J13: =_xlfn.XLOOKUP($H13,Conciliation!$A:$A,Conciliation!$D:$D,"0") -> 11276.94
C14: 13 | D14: POS Data Upload Sabretooth | E14: Gross Food Sales | G14: 400200 | H14: 32934 | J14: =_xlfn.XLOOKUP($H14,Conciliation!$A:$A,Conciliation!$D:$D,"0") -> 8336.89
C15: 14 | D15: POS Data Upload Sabretooth | E15: Gross Food Sales | G15: 400200 | H15: 32935 | J15: =_xlfn.XLOOKUP($H15,Conciliation!$A:$A,Conciliation!$D:$D,"0") -> 7555.98
... C40: 39 | D40: POS Data Upload Sabretooth | E40: Gross Food Sales | G40: 400200 | H40: 33444 | J40: =_xlfn.XLOOKUP($H40,Conciliation!$A:$A,Conciliation!$D:$D,"0") -> 2655.54
C41: 40 | D41: POS Data Upload Sabretooth | E41: Discounts -Employee meals | G41: 410000 | H41: 28841 | I41: =_xlfn.XLOOKUP($H41,Conciliation!$A:$A,Conciliation!$E:$E,"0") -> 151.86
C42: 41 | D42: POS Data Upload Sabretooth | E42: Discounts -Employee meals | G42: 410000 | H42: 28842 | I42: =_xlfn.XLOOKUP($H42,Conciliation!$A:$A,Conciliation!$E:$E,"0") -> 202.13
C43: 42 | D43: POS Data Upload Sabretooth | E43: Discounts -Employee meals | G43: 410000 | H43: 28843 | I43: =_xlfn.XLOOKUP($H43,Conciliation!$A:$A,Conciliation!$E:$E,"0") -> 164.27
C44: 43 | D44: POS Data Upload Sabretooth | E44: Discounts -Employee meals | G44: 410000 | H44: 28844 | I44: =_xlfn.XLOOKUP($H44,Conciliation!$A:$A,Conciliation!$E:$E,"0") -> 315.18
C45: 44 | D45: POS Data Upload Sabretooth | E45: Discounts -Employee meals | G45: 410000 | H45: 28845 | I45: =_xlfn.XLOOKUP($H45,Conciliation!$A:$A,Conciliation!$E:$E,"0") -> 298.4
C46: 45 | D46: POS Data Upload Sabretooth | E46: Discounts -Employee meals | G46: 410000 | H46: 28846 | I46: =_xlfn.XLOOKUP($H46,Conciliation!$A:$A,Conciliation!$E:$E,"0") -> 238
C47: 46 | D47: POS Data Upload Sabretooth | E47: Discounts -Employee meals | G47: 410000 | H47: 29423 | I47: =_xlfn.XLOOKUP($H47,Conciliation!$A:$A,Conciliation!$E:$E,"0") -> 70.6
C48: 47 | D48: POS Data Upload Sabretooth | E48: Discounts -Employee meals | G48: 410000 | H48: 30256 | I48: =_xlfn.XLOOKUP($H48,Conciliation!$A:$A,Conciliation!$E:$E,"0") -> 124.31
C49: 48 | D49: POS Data Upload Sabretooth | E49: Discounts -Employee meals | G49: 410000 | H49: 30491 | I49: =_xlfn.XLOOKUP($H49,Conciliation!$A:$A,Conciliation!$E:$E,"0") -> 201.65
C50: 49 | D50: POS Data Upload Sabretooth | E50: Discounts -Employee meals | G50: 410000 | H50: 32680 | I50: =_xlfn.XLOOKUP($H50,Conciliation!$A:$A,Conciliation!$E:$E,"0") -> 199.74
C51: 50 | D51: POS Data Upload Sabretooth | E51: Discounts -Employee meals | G51: 410000 | H51: 32932 | I51: =_xlfn.XLOOKUP($H51,Conciliation!$A:$A,Conciliation!$E:$E,"0") -> 280.58
C52: 51 | D52: POS Data Upload Sabretooth | E52: Discounts -Employee meals | G52: 410000 | H52: 32933 | I52: =_xlfn.XLOOKUP($H52,Conciliation!$A:$A,Conciliation!$E:$E,"0") -> 451.4
... C79: 78 | D79: POS Data Upload Sabretooth | E79: Discounts -Employee meals | G79: 410000 | H79: 33444 | I79: =_xlfn.XLOOKUP($H79,Conciliation!$A:$A,Conciliation!$E:$E,"0") -> 65.95
C80: 79 | D80: POS Data Upload Sabretooth | E80: Coupons - Promotions | G80: 410000 | H80: 28841 | I80: =_xlfn.XLOOKUP($H80,Conciliation!$A:$A,Conciliation!$F:$F,"0") -> 3.19
C81: 80 | D81: POS Data Upload Sabretooth | E81: Coupons - Promotions | G81: 410000 | H81: 28842 | I81: =_xlfn.XLOOKUP($H81,Conciliation!$A:$A,Conciliation!$F:$F,"0") -> 0
C82: 81 | D82: POS Data Upload Sabretooth | E82: Coupons - Promotions | G82: 410000 | H82: 28843 | I82: =_xlfn.XLOOKUP($H82,Conciliation!$A:$A,Conciliation!$F:$F,"0") -> 0
C83: 82 | D83: POS Data Upload Sabretooth | E83: Coupons - Promotions | G83: 410000 | H83: 28844 | I83: =_xlfn.XLOOKUP($H83,Conciliation!$A:$A,Conciliation!$F:$F,"0") -> 0
C84: 83 | D84: POS Data Upload Sabretooth | E84: Coupons - Promotions | G84: 410000 | H84: 28845 | I84: =_xlfn.XLOOKUP($H84,Conciliation!$A:$A,Conciliation!$F:$F,"0") -> 0
C85: 84 | D85: POS Data Upload Sabretooth | E85: Coupons - Promotions | G85: 410000 | H85: 28846 | I85: =_xlfn.XLOOKUP($H85,Conciliation!$A:$A,Conciliation!$F:$F,"0") -> 0
C86: 85 | D86: POS Data Upload Sabretooth | E86: Coupons - Promotions | G86: 410000 | H86: 29423 | I86: =_xlfn.XLOOKUP($H86,Conciliation!$A:$A,Conciliation!$F:$F,"0") -> 0
C87: 86 | D87: POS Data Upload Sabretooth | E87: Coupons - Promotions | G87: 410000 | H87: 30256 | I87: =_xlfn.XLOOKUP($H87,Conciliation!$A:$A,Conciliation!$F:$F,"0") -> 0
C88: 87 | D88: POS Data Upload Sabretooth | E88: Coupons - Promotions | G88: 410000 | H88: 30491 | I88: =_xlfn.XLOOKUP($H88,Conciliation!$A:$A,Conciliation!$F:$F,"0") -> 0
C89: 88 | D89: POS Data Upload Sabretooth | E89: Coupons - Promotions | G89: 410000 | H89: 32680 | I89: =_xlfn.XLOOKUP($H89,Conciliation!$A:$A,Conciliation!$F:$F,"0") -> 3.69
C90: 89 | D90: POS Data Upload Sabretooth | E90: Coupons - Promotions | G90: 410000 | H90: 32932 | I90: =_xlfn.XLOOKUP($H90,Conciliation!$A:$A,Conciliation!$F:$F,"0") -> 9.75
C91: 90 | D91: POS Data Upload Sabretooth | E91: Coupons - Promotions | G91: 410000 | H91: 32933 | I91: =_xlfn.XLOOKUP($H91,Conciliation!$A:$A,Conciliation!$F:$F,"0") -> 129.18
... C118: 117 | D118: POS Data Upload Sabretooth | E118: Coupons - Promotions | G118: 410000 | H118: 33444 | I118: =_xlfn.XLOOKUP($H118,Conciliation!$A:$A,Conciliation!$F:$F,"0") -> 0
C119: 118 | D119: POS Data Upload Sabretooth | E119: Sales Tax Payable | G119: 222000 | H119: 28841 | J119: =_xlfn.XLOOKUP($H119,Conciliation!$A:$A,Conciliation!$C:$C,"0") -> 392.96
C120: 119 | D120: POS Data Upload Sabretooth | E120: Sales Tax Payable | G120: 222000 | H120: 28842 | J120: =_xlfn.XLOOKUP($H120,Conciliation!$A:$A,Conciliation!$C:$C,"0") -> 567.13
C121: 120 | D121: POS Data Upload Sabretooth | E121: Sales Tax Payable | G121: 222000 | H121: 28843 | J121: =_xlfn.XLOOKUP($H121,Conciliation!$A:$A,Conciliation!$C:$C,"0") -> 482.66
C122: 121 | D122: POS Data Upload Sabretooth | E122: Sales Tax Payable | G122: 222000 | H122: 28844 | J122: =_xlfn.XLOOKUP($H122,Conciliation!$A:$A,Conciliation!$C:$C,"0") -> 794.81
C123: 122 | D123: POS Data Upload Sabretooth | E123: Sales Tax Payable | G123: 222000 | H123: 28845 | J123: =_xlfn.XLOOKUP($H123,Conciliation!$A:$A,Conciliation!$C:$C,"0") -> 776.16
C124: 123 | D124: POS Data Upload Sabretooth | E124: Sales Tax Payable | G124: 222000 | H124: 28846 | J124: =_xlfn.XLOOKUP($H124,Conciliation!$A:$A,Conciliation!$C:$C,"0") -> 628.61
C125: 124 | D125: POS Data Upload Sabretooth | E125: Sales Tax Payable | G125: 222000 | H125: 29423 | J125: =_xlfn.XLOOKUP($H125,Conciliation!$A:$A,Conciliation!$C:$C,"0") -> 364.8
C126: 125 | D126: POS Data Upload Sabretooth | E126: Sales Tax Payable | G126: 222000 | H126: 30256 | J126: =_xlfn.XLOOKUP($H126,Conciliation!$A:$A,Conciliation!$C:$C,"0") -> 463.5
C127: 126 | D127: POS Data Upload Sabretooth | E127: Sales Tax Payable | G127: 222000 | H127: 30491 | J127: =_xlfn.XLOOKUP($H127,Conciliation!$A:$A,Conciliation!$C:$C,"0") -> 389.13
C128: 127 | D128: POS Data Upload Sabretooth | E128: Sales Tax Payable | G128: 222000 | H128: 32680 | J128: =_xlfn.XLOOKUP($H128,Conciliation!$A:$A,Conciliation!$C:$C,"0") -> 418.82
C129: 128 | D129: POS Data Upload Sabretooth | E129: Sales Tax Payable | G129: 222000 | H129: 32932 | J129: =_xlfn.XLOOKUP($H129,Conciliation!$A:$A,Conciliation!$C:$C,"0") -> 0
C130: 129 | D130: POS Data Upload Sabretooth | E130: Sales Tax Payable | G130: 222000 | H130: 32933 | J130: =_xlfn.XLOOKUP($H130,Conciliation!$A:$A,Conciliation!$C:$C,"0") -> 0
... C157: 156 | D157: POS Data Upload Sabretooth | E157: Sales Tax Payable | G157: 222000 | H157: 33444 | J157: =_xlfn.XLOOKUP($H157,Conciliation!$A:$A,Conciliation!$C:$C,"0") -> 187.74
C158: 157 | D158: POS Data Upload Sabretooth | E158: Non Taxable Sales | G158: 400201 | H158: 28841 | J158: =_xlfn.XLOOKUP($H158,Conciliation!$A:$A,Conciliation!$Z:$Z,"0") -> 46.78
C159: 158 | D159: POS Data Upload Sabretooth | E159: Non Taxable Sales | G159: 400201 | H159: 28842 | J159: =_xlfn.XLOOKUP($H159,Conciliation!$A:$A,Conciliation!$Z:$Z,"0") -> 137.43
C160: 159 | D160: POS Data Upload Sabretooth | E160: Non Taxable Sales | G160: 400201 | H160: 28843 | J160: =_xlfn.XLOOKUP($H160,Conciliation!$A:$A,Conciliation!$Z:$Z,"0") -> 85.76
C161: 160 | D161: POS Data Upload Sabretooth | E161: Non Taxable Sales | G161: 400201 | H161: 28844 | J161: =_xlfn.XLOOKUP($H161,Conciliation!$A:$A,Conciliation!$Z:$Z,"0") -> 112.4
C162: 161 | D162: POS Data Upload Sabretooth | E162: Non Taxable Sales | G162: 400201 | H162: 28845 | J162: =_xlfn.XLOOKUP($H162,Conciliation!$A:$A,Conciliation!$Z:$Z,"0") -> 105.07
C163: 162 | D163: POS Data Upload Sabretooth | E163: Non Taxable Sales | G163: 400201 | H163: 28846 | J163: =_xlfn.XLOOKUP($H163,Conciliation!$A:$A,Conciliation!$Z:$Z,"0") -> 302.7
C164: 163 | D164: POS Data Upload Sabretooth | E164: Non Taxable Sales | G164: 400201 | H164: 29423 | J164: =_xlfn.XLOOKUP($H164,Conciliation!$A:$A,Conciliation!$Z:$Z,"0") -> 16.75
C165: 164 | D165: POS Data Upload Sabretooth | E165: Non Taxable Sales | G165: 400201 | H165: 30256 | J165: =_xlfn.XLOOKUP($H165,Conciliation!$A:$A,Conciliation!$Z:$Z,"0") -> 52.28
C166: 165 | D166: POS Data Upload Sabretooth | E166: Non Taxable Sales | G166: 400201 | H166: 30491 | J166: =_xlfn.XLOOKUP($H166,Conciliation!$A:$A,Conciliation!$Z:$Z,"0") -> 0
C167: 166 | D167: POS Data Upload Sabretooth | E167: Non Taxable Sales | G167: 400201 | H167: 32680 | J167: =_xlfn.XLOOKUP($H167,Conciliation!$A:$A,Conciliation!$Z:$Z,"0") -> 10.98
C168: 167 | D168: POS Data Upload Sabretooth | E168: Non Taxable Sales | G168: 400201 | H168: 32932 | J168: =_xlfn.XLOOKUP($H168,Conciliation!$A:$A,Conciliation!$Z:$Z,"0") -> 589.16
C169: 168 | D169: POS Data Upload Sabretooth | E169: Non Taxable Sales | G169: 400201 | H169: 32933 | J169: =_xlfn.XLOOKUP($H169,Conciliation!$A:$A,Conciliation!$Z:$Z,"0") -> 1326.83
... C196: 195 | D196: POS Data Upload Sabretooth | E196: Non Taxable Sales | G196: 400201 | H196: 33444 | J196: =_xlfn.XLOOKUP($H196,Conciliation!$A:$A,Conciliation!$Z:$Z,"0") -> 0
C197: 196 | D197: POS Data Upload Sabretooth | E197: Donations | G197: 212000 | H197: 28841 | J197: =_xlfn.XLOOKUP($H197,Conciliation!$A:$A,Conciliation!$M:$M,"0") -> 21.59
C198: 197 | D198: POS Data Upload Sabretooth | E198: Donations | G198: 212000 | H198: 28842 | J198: =_xlfn.XLOOKUP($H198,Conciliation!$A:$A,Conciliation!$M:$M,"0") -> 37.8
C199: 198 | D199: POS Data Upload Sabretooth | E199: Donations | G199: 212000 | H199: 28843 | J199: =_xlfn.XLOOKUP($H199,Conciliation!$A:$A,Conciliation!$M:$M,"0") -> 22.89
C200: 199 | D200: POS Data Upload Sabretooth | E200: Donations | G200: 212000 | H200: 28844 | J200: =_xlfn.XLOOKUP($H200,Conciliation!$A:$A,Conciliation!$M:$M,"0") -> 34.64
C201: 200 | D201: POS Data Upload Sabretooth | E201: Donations | G201: 212000 | H201: 28845 | J201: =_xlfn.XLOOKUP($H201,Conciliation!$A:$A,Conciliation!$M:$M,"0") -> 24.73
C202: 201 | D202: POS Data Upload Sabretooth | E202: Donations | G202: 212000 | H202: 28846 | J202: =_xlfn.XLOOKUP($H202,Conciliation!$A:$A,Conciliation!$M:$M,"0") -> 27.83
C203: 202 | D203: POS Data Upload Sabretooth | E203: Donations | G203: 212000 | H203: 29423 | J203: =_xlfn.XLOOKUP($H203,Conciliation!$A:$A,Conciliation!$M:$M,"0") -> 13.8
C204: 203 | D204: POS Data Upload Sabretooth | E204: Donations | G204: 212000 | H204: 30256 | J204: =_xlfn.XLOOKUP($H204,Conciliation!$A:$A,Conciliation!$M:$M,"0") -> 16.43
C205: 204 | D205: POS Data Upload Sabretooth | E205: Donations | G205: 212000 | H205: 30491 | J205: =_xlfn.XLOOKUP($H205,Conciliation!$A:$A,Conciliation!$M:$M,"0") -> 28.2
C206: 205 | D206: POS Data Upload Sabretooth | E206: Donations | G206: 212000 | H206: 32680 | J206: =_xlfn.XLOOKUP($H206,Conciliation!$A:$A,Conciliation!$M:$M,"0") -> 25.52
C207: 206 | D207: POS Data Upload Sabretooth | E207: Donations | G207: 212000 | H207: 32932 | J207: =_xlfn.XLOOKUP($H207,Conciliation!$A:$A,Conciliation!$M:$M,"0") -> 16.58
C208: 207 | D208: POS Data Upload Sabretooth | E208: Donations | G208: 212000 | H208: 32933 | J208: =_xlfn.XLOOKUP($H208,Conciliation!$A:$A,Conciliation!$M:$M,"0") -> 29.87
... C235: 234 | D235: POS Data Upload Sabretooth | E235: Donations | G235: 212000 | H235: 33444 | J235: =_xlfn.XLOOKUP($H235,Conciliation!$A:$A,Conciliation!$M:$M,"0") -> 7.45
C236: 235 | D236: POS Data Upload Sabretooth | E236: Gift Cards SOLD | G236: 115000 | H236: 28841 | J236: =_xlfn.XLOOKUP($H236,Conciliation!$A:$A,Conciliation!$J:$J,"0") -> 15
C237: 236 | D237: POS Data Upload Sabretooth | E237: Gift Cards SOLD | G237: 115000 | H237: 28842 | J237: =_xlfn.XLOOKUP($H237,Conciliation!$A:$A,Conciliation!$J:$J,"0") -> 0
C238: 237 | D238: POS Data Upload Sabretooth | E238: Gift Cards SOLD | G238: 115000 | H238: 28843 | J238: =_xlfn.XLOOKUP($H238,Conciliation!$A:$A,Conciliation!$J:$J,"0") -> 0
C239: 238 | D239: POS Data Upload Sabretooth | E239: Gift Cards SOLD | G239: 115000 | H239: 28844 | J239: =_xlfn.XLOOKUP($H239,Conciliation!$A:$A,Conciliation!$J:$J,"0") -> 0
C240: 239 | D240: POS Data Upload Sabretooth | E240: Gift Cards SOLD | G240: 115000 | H240: 28845 | J240: =_xlfn.XLOOKUP($H240,Conciliation!$A:$A,Conciliation!$J:$J,"0") -> 10
C241: 240 | D241: POS Data Upload Sabretooth | E241: Gift Cards SOLD | G241: 115000 | H241: 28846 | J241: =_xlfn.XLOOKUP($H241,Conciliation!$A:$A,Conciliation!$J:$J,"0") -> 0
C242: 241 | D242: POS Data Upload Sabretooth | E242: Gift Cards SOLD | G242: 115000 | H242: 29423 | J242: =_xlfn.XLOOKUP($H242,Conciliation!$A:$A,Conciliation!$J:$J,"0") -> 0
C243: 242 | D243: POS Data Upload Sabretooth | E243: Gift Cards SOLD | G243: 115000 | H243: 30256 | J243: =_xlfn.XLOOKUP($H243,Conciliation!$A:$A,Conciliation!$J:$J,"0") -> 0
C244: 243 | D244: POS Data Upload Sabretooth | E244: Gift Cards SOLD | G244: 115000 | H244: 30491 | J244: =_xlfn.XLOOKUP($H244,Conciliation!$A:$A,Conciliation!$J:$J,"0") -> 0
C245: 244 | D245: POS Data Upload Sabretooth | E245: Gift Cards SOLD | G245: 115000 | H245: 32680 | J245: =_xlfn.XLOOKUP($H245,Conciliation!$A:$A,Conciliation!$J:$J,"0") -> 0
C246: 245 | D246: POS Data Upload Sabretooth | E246: Gift Cards SOLD | G246: 115000 | H246: 32932 | J246: =_xlfn.XLOOKUP($H246,Conciliation!$A:$A,Conciliation!$J:$J,"0") -> 0
C247: 246 | D247: POS Data Upload Sabretooth | E247: Gift Cards SOLD | G247: 115000 | H247: 32933 | J247: =_xlfn.XLOOKUP($H247,Conciliation!$A:$A,Conciliation!$J:$J,"0") -> 20
... C274: 273 | D274: POS Data Upload Sabretooth | E274: Gift Cards SOLD | G274: 115000 | H274: 33444 | J274: =_xlfn.XLOOKUP($H274,Conciliation!$A:$A,Conciliation!$J:$J,"0") -> 0
C275: 274 | D275: POS Data Upload Sabretooth | E275: Paid Outs | G275: 116200 | H275: 28841 | I275: =_xlfn.XLOOKUP($H275,Conciliation!$A:$A,Conciliation!$K:$K,"0") -> 28.9
C276: 275 | D276: POS Data Upload Sabretooth | E276: Paid Outs | G276: 116200 | H276: 28842 | I276: =_xlfn.XLOOKUP($H276,Conciliation!$A:$A,Conciliation!$K:$K,"0") -> 0
C277: 276 | D277: POS Data Upload Sabretooth | E277: Paid Outs | G277: 116200 | H277: 28843 | I277: =_xlfn.XLOOKUP($H277,Conciliation!$A:$A,Conciliation!$K:$K,"0") -> 0
C278: 277 | D278: POS Data Upload Sabretooth | E278: Paid Outs | G278: 116200 | H278: 28844 | I278: =_xlfn.XLOOKUP($H278,Conciliation!$A:$A,Conciliation!$K:$K,"0") -> 0
C279: 278 | D279: POS Data Upload Sabretooth | E279: Paid Outs | G279: 116200 | H279: 28845 | I279: =_xlfn.XLOOKUP($H279,Conciliation!$A:$A,Conciliation!$K:$K,"0") -> 0
C280: 279 | D280: POS Data Upload Sabretooth | E280: Paid Outs | G280: 116200 | H280: 28846 | I280: =_xlfn.XLOOKUP($H280,Conciliation!$A:$A,Conciliation!$K:$K,"0") -> 0
...

Sheet Statistical Delivery
A1: JOURNAL | B1: DATE | C1: LINE_NO
A2: SJ | B2: 46091 | C2: 1 | D2: Statistical Delivery Sales | E2: Statistical Delivery Sales | G2: 990300 | H2: 28841 | I2: =_xlfn.XLOOKUP($H2,Conciliation!$A:$A,Conciliation!$AA:$AA,"0") -> 706.33
C3: 2 | D3: Statistical Delivery Sales | E3: Statistical Delivery Sales | G3: 990300 | H3: 28842 | I3: =_xlfn.XLOOKUP($H3,Conciliation!$A:$A,Conciliation!$AA:$AA,"0") -> 820.69
C4: 3 | D4: Statistical Delivery Sales | E4: Statistical Delivery Sales | G4: 990300 | H4: 28843 | I4: =_xlfn.XLOOKUP($H4,Conciliation!$A:$A,Conciliation!$AA:$AA,"0") -> 672.5
C5: 4 | D5: Statistical Delivery Sales | E5: Statistical Delivery Sales | G5: 990300 | H5: 28844 | I5: =_xlfn.XLOOKUP($H5,Conciliation!$A:$A,Conciliation!$AA:$AA,"0") -> 1057.01
C6: 5 | D6: Statistical Delivery Sales | E6: Statistical Delivery Sales | G6: 990300 | H6: 28845 | I6: =_xlfn.XLOOKUP($H6,Conciliation!$A:$A,Conciliation!$AA:$AA,"0") -> 1703.9
C7: 6 | D7: Statistical Delivery Sales | E7: Statistical Delivery Sales | G7: 990300 | H7: 28846 | I7: =_xlfn.XLOOKUP($H7,Conciliation!$A:$A,Conciliation!$AA:$AA,"0") -> 1625.87
C8: 7 | D8: Statistical Delivery Sales | E8: Statistical Delivery Sales | G8: 990300 | H8: 30256 | I8: =_xlfn.XLOOKUP($H8,Conciliation!$A:$A,Conciliation!$AA:$AA,"0") -> 542.43
C9: 8 | D9: Statistical Delivery Sales | E9: Statistical Delivery Sales | G9: 990300 | H9: 36224 | I9: =_xlfn.XLOOKUP($H9,Conciliation!$A:$A,Conciliation!$AA:$AA,"0") -> 565.67
C10: 9 | D10: Statistical Delivery Sales | E10: Statistical Delivery Sales | G10: 990300 | H10: 37014 | I10: =_xlfn.XLOOKUP($H10,Conciliation!$A:$A,Conciliation!$AA:$AA,"0") -> 0
C11: 10 | D11: Statistical Delivery Sales | E11: Statistical Delivery Sales | G11: 990300 | H11: 30491 | I11: =_xlfn.XLOOKUP($H11,Conciliation!$A:$A,Conciliation!$AA:$AA,"0") -> 87.27
C12: 11 | D12: Statistical Delivery Sales | E12: Statistical Delivery Sales | G12: 990300 | H12: 29423 | I12: =_xlfn.XLOOKUP($H12,Conciliation!$A:$A,Conciliation!$AA:$AA,"0") -> 122.62
C13: 12 | D13: Statistical Delivery Sales | E13: Statistical Delivery Sales | G13: 990300 | H13: 32680 | I13: =_xlfn.XLOOKUP($H13,Conciliation!$A:$A,Conciliation!$AA:$AA,"0") -> 418.21
C14: 13 | D14: Statistical Delivery Sales | E14: Statistical Delivery Sales | G14: 990300 | H14: 34793 | I14: =_xlfn.XLOOKUP($H14,Conciliation!$A:$A,Conciliation!$AA:$AA,"0") -> 48.95
... C39: 38 | D39: Statistical Delivery Sales | E39: Statistical Delivery Sales | G39: 990300 | H39: 40404 | I39: =_xlfn.XLOOKUP($H39,Conciliation!$A:$A,Conciliation!$AA:$AA,"0") -> 413.14
D40: Statistical Delivery Sales | E40: Statistical Delivery Sales | G40: 990300 | H40: 33444 | I40: =_xlfn.XLOOKUP($H40,Conciliation!$A:$A,Conciliation!$AA:$AA,"0") -> 0
C41: 39 | D41: Statistical Delivery Sales | E41: Statistical Delivery Sales | G41: 990301 | H41: 28841 | J41: =_xlfn.XLOOKUP($H41,Conciliation!$A:$A,Conciliation!$AA:$AA,"0") -> 706.33
C42: 40 | D42: Statistical Delivery Sales | E42: Statistical Delivery Sales | G42: 990301 | H42: 28842 | J42: =_xlfn.XLOOKUP($H42,Conciliation!$A:$A,Conciliation!$AA:$AA,"0") -> 820.69
C43: 41 | D43: Statistical Delivery Sales | E43: Statistical Delivery Sales | G43: 990301 | H43: 28843 | J43: =_xlfn.XLOOKUP($H43,Conciliation!$A:$A,Conciliation!$AA:$AA,"0") -> 672.5
C44: 42 | D44: Statistical Delivery Sales | E44: Statistical Delivery Sales | G44: 990301 | H44: 28844 | J44: =_xlfn.XLOOKUP($H44,Conciliation!$A:$A,Conciliation!$AA:$AA,"0") -> 1057.01
C45: 43 | D45: Statistical Delivery Sales | E45: Statistical Delivery Sales | G45: 990301 | H45: 28845 | J45: =_xlfn.XLOOKUP($H45,Conciliation!$A:$A,Conciliation!$AA:$AA,"0") -> 1703.9
C46: 44 | D46: Statistical Delivery Sales | E46: Statistical Delivery Sales | G46: 990301 | H46: 28846 | J46: =_xlfn.XLOOKUP($H46,Conciliation!$A:$A,Conciliation!$AA:$AA,"0") -> 1625.87
C47: 45 | D47: Statistical Delivery Sales | E47: Statistical Delivery Sales | G47: 990301 | H47: 30256 | J47: =_xlfn.XLOOKUP($H47,Conciliation!$A:$A,Conciliation!$AA:$AA,"0") -> 542.43
C48: 46 | D48: Statistical Delivery Sales | E48: Statistical Delivery Sales | G48: 990301 | H48: 36224 | J48: =_xlfn.XLOOKUP($H48,Conciliation!$A:$A,Conciliation!$AA:$AA,"0") -> 565.67
C49: 47 | D49: Statistical Delivery Sales | E49: Statistical Delivery Sales | G49: 990301 | H49: 37014 | J49: =_xlfn.XLOOKUP($H49,Conciliation!$A:$A,Conciliation!$AA:$AA,"0") -> 0
C50: 48 | D50: Statistical Delivery Sales | E50: Statistical Delivery Sales | G50: 990301 | H50: 30491 | J50: =_xlfn.XLOOKUP($H50,Conciliation!$A:$A,Conciliation!$AA:$AA,"0") -> 87.27
C51: 49 | D51: Statistical Delivery Sales | E51: Statistical Delivery Sales | G51: 990301 | H51: 29423 | J51: =_xlfn.XLOOKUP($H51,Conciliation!$A:$A,Conciliation!$AA:$AA,"0") -> 122.62
C52: 50 | D52: Statistical Delivery Sales | E52: Statistical Delivery Sales | G52: 990301 | H52: 32680 | J52: =_xlfn.XLOOKUP($H52,Conciliation!$A:$A,Conciliation!$AA:$AA,"0") -> 418.21
... C78: 76 | D78: Statistical Delivery Sales | E78: Statistical Delivery Sales | G78: 990301 | H78: 40404 | J78: =_xlfn.XLOOKUP($H78,Conciliation!$A:$A,Conciliation!$AA:$AA,"0") -> 413.14
D79: Statistical Delivery Sales | E79: Statistical Delivery Sales | G79: 990301 | H79: 33444 | J79: =_xlfn.XLOOKUP($H79,Conciliation!$A:$A,Conciliation!$AA:$AA,"0") -> 0
C80: 77 | D80: Statistical Delivery Sales | E80: Statistical Delivery Sales | G80: 990200 | H80: 28841 | I80: =_xlfn.XLOOKUP($H80,Conciliation!$A:$A,Conciliation!$Z:$Z,"0") -> 46.78
C81: 78 | D81: Statistical Delivery Sales | E81: Statistical Delivery Sales | G81: 990200 | H81: 28842 | I81: =_xlfn.XLOOKUP($H81,Conciliation!$A:$A,Conciliation!$Z:$Z,"0") -> 137.43
C82: 79 | D82: Statistical Delivery Sales | E82: Statistical Delivery Sales | G82: 990200 | H82: 28843 | I82: =_xlfn.XLOOKUP($H82,Conciliation!$A:$A,Conciliation!$Z:$Z,"0") -> 85.76
C83: 80 | D83: Statistical Delivery Sales | E83: Statistical Delivery Sales | G83: 990200 | H83: 28844 | I83: =_xlfn.XLOOKUP($H83,Conciliation!$A:$A,Conciliation!$Z:$Z,"0") -> 112.4
C84: 81 | D84: Statistical Delivery Sales | E84: Statistical Delivery Sales | G84: 990200 | H84: 28845 | I84: =_xlfn.XLOOKUP($H84,Conciliation!$A:$A,Conciliation!$Z:$Z,"0") -> 105.07
C85: 82 | D85: Statistical Delivery Sales | E85: Statistical Delivery Sales | G85: 990200 | H85: 28846 | I85: =_xlfn.XLOOKUP($H85,Conciliation!$A:$A,Conciliation!$Z:$Z,"0") -> 302.7
C86: 83 | D86: Statistical Delivery Sales | E86: Statistical Delivery Sales | G86: 990200 | H86: 30256 | I86: =_xlfn.XLOOKUP($H86,Conciliation!$A:$A,Conciliation!$Z:$Z,"0") -> 52.28
C87: 84 | D87: Statistical Delivery Sales | E87: Statistical Delivery Sales | G87: 990200 | H87: 36224 | I87: =_xlfn.XLOOKUP($H87,Conciliation!$A:$A,Conciliation!$Z:$Z,"0") -> 56.33
C88: 85 | D88: Statistical Delivery Sales | E88: Statistical Delivery Sales | G88: 990200 | H88: 37014 | I88: =_xlfn.XLOOKUP($H88,Conciliation!$A:$A,Conciliation!$Z:$Z,"0") -> 0
C89: 86 | D89: Statistical Delivery Sales | E89: Statistical Delivery Sales | G89: 990200 | H89: 30491 | I89: =_xlfn.XLOOKUP($H89,Conciliation!$A:$A,Conciliation!$Z:$Z,"0") -> 0
C90: 87 | D90: Statistical Delivery Sales | E90: Statistical Delivery Sales | G90: 990200 | H90: 29423 | I90: =_xlfn.XLOOKUP($H90,Conciliation!$A:$A,Conciliation!$Z:$Z,"0") -> 16.75
C91: 88 | D91: Statistical Delivery Sales | E91: Statistical Delivery Sales | G91: 990200 | H91: 32680 | I91: =_xlfn.XLOOKUP($H91,Conciliation!$A:$A,Conciliation!$Z:$Z,"0") -> 10.98
... C117: 114 | D117: Statistical Delivery Sales | E117: Statistical Delivery Sales | G117: 990200 | H117: 40404 | I117: =_xlfn.XLOOKUP($H117,Conciliation!$A:$A,Conciliation!$Z:$Z,"0") -> 272.1
D118: Statistical Delivery Sales | E118: Statistical Delivery Sales | G118: 990200 | H118: 33444 | I118: =_xlfn.XLOOKUP($H118,Conciliation!$A:$A,Conciliation!$Z:$Z,"0") -> 0
C119: 115 | D119: Statistical Delivery Sales | E119: Statistical Delivery Sales | G119: 990201 | H119: 28841 | J119: =_xlfn.XLOOKUP($H119,Conciliation!$A:$A,Conciliation!$Z:$Z,"0") -> 46.78
C120: 116 | D120: Statistical Delivery Sales | E120: Statistical Delivery Sales | G120: 990201 | H120: 28842 | J120: =_xlfn.XLOOKUP($H120,Conciliation!$A:$A,Conciliation!$Z:$Z,"0") -> 137.43
C121: 117 | D121: Statistical Delivery Sales | E121: Statistical Delivery Sales | G121: 990201 | H121: 28843 | J121: =_xlfn.XLOOKUP($H121,Conciliation!$A:$A,Conciliation!$Z:$Z,"0") -> 85.76
C122: 118 | D122: Statistical Delivery Sales | E122: Statistical Delivery Sales | G122: 990201 | H122: 28844 | J122: =_xlfn.XLOOKUP($H122,Conciliation!$A:$A,Conciliation!$Z:$Z,"0") -> 112.4
C123: 119 | D123: Statistical Delivery Sales | E123: Statistical Delivery Sales | G123: 990201 | H123: 28845 | J123: =_xlfn.XLOOKUP($H123,Conciliation!$A:$A,Conciliation!$Z:$Z,"0") -> 105.07
C124: 120 | D124: Statistical Delivery Sales | E124: Statistical Delivery Sales | G124: 990201 | H124: 28846 | J124: =_xlfn.XLOOKUP($H124,Conciliation!$A:$A,Conciliation!$Z:$Z,"0") -> 302.7
C125: 121 | D125: Statistical Delivery Sales | E125: Statistical Delivery Sales | G125: 990201 | H125: 30256 | J125: =_xlfn.XLOOKUP($H125,Conciliation!$A:$A,Conciliation!$Z:$Z,"0") -> 52.28
C126: 122 | D126: Statistical Delivery Sales | E126: Statistical Delivery Sales | G126: 990201 | H126: 36224 | J126: =_xlfn.XLOOKUP($H126,Conciliation!$A:$A,Conciliation!$Z:$Z,"0") -> 56.33
C127: 123 | D127: Statistical Delivery Sales | E127: Statistical Delivery Sales | G127: 990201 | H127: 37014 | J127: =_xlfn.XLOOKUP($H127,Conciliation!$A:$A,Conciliation!$Z:$Z,"0") -> 0
C128: 124 | D128: Statistical Delivery Sales | E128: Statistical Delivery Sales | G128: 990201 | H128: 30491 | J128: =_xlfn.XLOOKUP($H128,Conciliation!$A:$A,Conciliation!$Z:$Z,"0") -> 0
C129: 125 | D129: Statistical Delivery Sales | E129: Statistical Delivery Sales | G129: 990201 | H129: 29423 | J129: =_xlfn.XLOOKUP($H129,Conciliation!$A:$A,Conciliation!$Z:$Z,"0") -> 16.75
C130: 126 | D130: Statistical Delivery Sales | E130: Statistical Delivery Sales | G130: 990201 | H130: 32680 | J130: =_xlfn.XLOOKUP($H130,Conciliation!$A:$A,Conciliation!$Z:$Z,"0") -> 10.98
... C156: 152 | D156: Statistical Delivery Sales | E156: Statistical Delivery Sales | G156: 990201 | H156: 40404 | J156: =_xlfn.XLOOKUP($H156,Conciliation!$A:$A,Conciliation!$Z:$Z,"0") -> 272.1
D157: Statistical Delivery Sales | E157: Statistical Delivery Sales | G157: 990201 | H157: 33444 | J157: =_xlfn.XLOOKUP($H157,Conciliation!$A:$A,Conciliation!$Z:$Z,"0") -> 0
C158: 153 | D158: Statistical Delivery Sales | E158: Statistical Delivery Sales | G158: 990100 | H158: 28841 | I158: =_xlfn.XLOOKUP($H158,Conciliation!$A:$A,Conciliation!$Y:$Y,"0") -> 0
C159: 154 | D159: Statistical Delivery Sales | E159: Statistical Delivery Sales | G159: 990100 | H159: 28842 | I159: =_xlfn.XLOOKUP($H159,Conciliation!$A:$A,Conciliation!$Y:$Y,"0") -> 0
C160: 155 | D160: Statistical Delivery Sales | E160: Statistical Delivery Sales | G160: 990100 | H160: 28843 | I160: =_xlfn.XLOOKUP($H160,Conciliation!$A:$A,Conciliation!$Y:$Y,"0") -> 27.42
C161: 156 | D161: Statistical Delivery Sales | E161: Statistical Delivery Sales | G161: 990100 | H161: 28844 | I161: =_xlfn.XLOOKUP($H161,Conciliation!$A:$A,Conciliation!$Y:$Y,"0") -> 0
C162: 157 | D162: Statistical Delivery Sales | E162: Statistical Delivery Sales | G162: 990100 | H162: 28845 | I162: =_xlfn.XLOOKUP($H162,Conciliation!$A:$A,Conciliation!$Y:$Y,"0") -> 90.74
C163: 158 | D163: Statistical Delivery Sales | E163: Statistical Delivery Sales | G163: 990100 | H163: 28846 | I163: =_xlfn.XLOOKUP($H163,Conciliation!$A:$A,Conciliation!$Y:$Y,"0") -> 37.79
C164: 159 | D164: Statistical Delivery Sales | E164: Statistical Delivery Sales | G164: 990100 | H164: 30256 | I164: =_xlfn.XLOOKUP($H164,Conciliation!$A:$A,Conciliation!$Y:$Y,"0") -> 0
C165: 160 | D165: Statistical Delivery Sales | E165: Statistical Delivery Sales | G165: 990100 | H165: 36224 | I165: =_xlfn.XLOOKUP($H165,Conciliation!$A:$A,Conciliation!$Y:$Y,"0") -> 50.37
C166: 161 | D166: Statistical Delivery Sales | E166: Statistical Delivery Sales | G166: 990100 | H166: 37014 | I166: =_xlfn.XLOOKUP($H166,Conciliation!$A:$A,Conciliation!$Y:$Y,"0") -> 0
C167: 162 | D167: Statistical Delivery Sales | E167: Statistical Delivery Sales | G167: 990100 | H167: 30491 | I167: =_xlfn.XLOOKUP($H167,Conciliation!$A:$A,Conciliation!$Y:$Y,"0") -> 0
C168: 163 | D168: Statistical Delivery Sales | E168: Statistical Delivery Sales | G168: 990100 | H168: 29423 | I168: =_xlfn.XLOOKUP($H168,Conciliation!$A:$A,Conciliation!$Y:$Y,"0") -> 0
C169: 164 | D169: Statistical Delivery Sales | E169: Statistical Delivery Sales | G169: 990100 | H169: 32680 | I169: =_xlfn.XLOOKUP($H169,Conciliation!$A:$A,Conciliation!$Y:$Y,"0") -> 0
... C196: 190 | D196: Statistical Delivery Sales | E196: Statistical Delivery Sales | G196: 990100 | H196: 33444 | I196: =_xlfn.XLOOKUP($H196,Conciliation!$A:$A,Conciliation!$Y:$Y,"0") -> 0
C197: 191 | D197: Statistical Delivery Sales | E197: Statistical Delivery Sales | G197: 990101 | H197: 28841 | J197: =_xlfn.XLOOKUP($H197,Conciliation!$A:$A,Conciliation!$Y:$Y,"0") -> 0
C198: 192 | D198: Statistical Delivery Sales | E198: Statistical Delivery Sales | G198: 990101 | H198: 28842 | J198: =_xlfn.XLOOKUP($H198,Conciliation!$A:$A,Conciliation!$Y:$Y,"0") -> 0
C199: 193 | D199: Statistical Delivery Sales | E199: Statistical Delivery Sales | G199: 990101 | H199: 28843 | J199: =_xlfn.XLOOKUP($H199,Conciliation!$A:$A,Conciliation!$Y:$Y,"0") -> 27.42
C200: 194 | D200: Statistical Delivery Sales | E200: Statistical Delivery Sales | G200: 990101 | H200: 28844 | J200: =_xlfn.XLOOKUP($H200,Conciliation!$A:$A,Conciliation!$Y:$Y,"0") -> 0
C201: 195 | D201: Statistical Delivery Sales | E201: Statistical Delivery Sales | G201: 990101 | H201: 28845 | J201: =_xlfn.XLOOKUP($H201,Conciliation!$A:$A,Conciliation!$Y:$Y,"0") -> 90.74
C202: 196 | D202: Statistical Delivery Sales | E202: Statistical Delivery Sales | G202: 990101 | H202: 28846 | J202: =_xlfn.XLOOKUP($H202,Conciliation!$A:$A,Conciliation!$Y:$Y,"0") -> 37.79
C203: 197 | D203: Statistical Delivery Sales | E203: Statistical Delivery Sales | G203: 990101 | H203: 30256 | J203: =_xlfn.XLOOKUP($H203,Conciliation!$A:$A,Conciliation!$Y:$Y,"0") -> 0
C204: 198 | D204: Statistical Delivery Sales | E204: Statistical Delivery Sales | G204: 990101 | H204: 36224 | J204: =_xlfn.XLOOKUP($H204,Conciliation!$A:$A,Conciliation!$Y:$Y,"0") -> 50.37
C205: 199 | D205: Statistical Delivery Sales | E205: Statistical Delivery Sales | G205: 990101 | H205: 37014 | J205: =_xlfn.XLOOKUP($H205,Conciliation!$A:$A,Conciliation!$Y:$Y,"0") -> 0
C206: 200 | D206: Statistical Delivery Sales | E206: Statistical Delivery Sales | G206: 990101 | H206: 30491 | J206: =_xlfn.XLOOKUP($H206,Conciliation!$A:$A,Conciliation!$Y:$Y,"0") -> 0
C207: 201 | D207: Statistical Delivery Sales | E207: Statistical Delivery Sales | G207: 990101 | H207: 29423 | J207: =_xlfn.XLOOKUP($H207,Conciliation!$A:$A,Conciliation!$Y:$Y,"0") -> 0
C208: 202 | D208: Statistical Delivery Sales | E208: Statistical Delivery Sales | G208: 990101 | H208: 32680 | J208: =_xlfn.XLOOKUP($H208,Conciliation!$A:$A,Conciliation!$Y:$Y,"0") -> 0
... C234: 228 | D234: Statistical Delivery Sales | E234: Statistical Delivery Sales | G234: 990101 | H234: 40404 | J234: =_xlfn.XLOOKUP($H234,Conciliation!$A:$A,Conciliation!$Y:$Y,"0") -> 37.25
D235: Statistical Delivery Sales | E235: Statistical Delivery Sales | G235: 990101 | H235: 33444 | J235: =_xlfn.XLOOKUP($H235,Conciliation!$A:$A,Conciliation!$Y:$Y,"0") -> 0

Sheet Daily Sales Taco Bell 03-14 202
A1: JOURNAL | B1: DATE | C1: LINE_NO | D1: DESCRIPTION | E1: MEMO | F1: DEPT_ID | G1: ACCT_NO | H1: LOCATION_ID | I1: DEBIT | J1: CREDIT
A2: SJ | B2: =Sales!B2 -> 05/26/2026 | C2: {=_xlfn.SEQUENCE(ROWS(_xlfn.ANCHORARRAY(D2)))} -> 1 | D2: {=_xlfn.LET( _xlpm.data,_xlfn._xlws.FILTER('Daily Sales Taco Bell RED'!D:K,(('Daily Sales Taco Bell RED'!I:I<>0)+('Daily Sales Taco Bell RED'!J:J<>0))), _xlpm.memoCol,INDEX(_xlpm.data,,2), _xlpm.locCol,INDEX(_xlpm.data,,5), _xlpm.specialLoc,ISNUMBER(MATCH(_xlpm.locCol,{28841,28843,28844,28845,28846,30256,30491,36224},0)), _xlpm.sortGroup, IF((_xlpm.memoCol="Cash Expected Deposit")*_xlpm.specialLoc,1, IF((_xlpm.memoCol="EBT Expected Deposit")*_xlpm.specialLoc,2,0)), _xlpm.sorted,_xlfn.SORTBY(_xlpm.data,_xlpm.sortGroup,1,_xlpm.locCol,1), _xlfn.HSTACK( INDEX(_xlpm.sorted,,1), INDEX(_xlpm.sorted,,2), IF(INDEX(_xlpm.sorted,,3)=0,"",INDEX(_xlpm.sorted,,3)), INDEX(_xlpm.sorted,,4), INDEX(_xlpm.sorted,,5), IF(INDEX(_xlpm.sorted,,6)=0,"",INDEX(_xlpm.sorted,,6)), IF(INDEX(_xlpm.sorted,,7)=0,"",INDEX(_xlpm.sorted,,7)), IF(INDEX(_xlpm.sorted,,8)=0,"",INDEX(_xlpm.sorted,,8)) ) )} -> POS Data Upload Sabretooth | E2: Gross Food Sales | G2: 400200 | H2: 28841 | J2: 5040.05
C3: 2 | D3: POS Data Upload Sabretooth | E3: Discounts -Employee meals | G3: 410000 | H3: 28841 | I3: 151.86
C4: 3 | D4: POS Data Upload Sabretooth | E4: Coupons - Promotions | G4: 410000 | H4: 28841 | I4: 3.19
C5: 4 | D5: POS Data Upload Sabretooth | E5: Sales Tax Payable | G5: 222000 | H5: 28841 | J5: 392.96
C6: 5 | D6: POS Data Upload Sabretooth | E6: Non Taxable Sales | G6: 400201 | H6: 28841 | J6: 46.78
C7: 6 | D7: POS Data Upload Sabretooth | E7: Donations | G7: 212000 | H7: 28841 | J7: 21.59
C8: 7 | D8: POS Data Upload Sabretooth | E8: Gift Cards SOLD | G8: 115000 | H8: 28841 | J8: 15
C9: 8 | D9: POS Data Upload Sabretooth | E9: Paid Outs | G9: 116200 | H9: 28841 | I9: 28.9
C10: 9 | D10: POS Data Upload Sabretooth | E10: Credit Cards Expected Deposit | G10: 111200 | H10: 28841 | I10: 3431.9
C11: 10 | D11: POS Data Upload Sabretooth | E11: AMEX Expected Deposit | G11: 111200 | H11: 28841 | I11: 120.76
C12: 11 | D12: POS Data Upload Sabretooth | E12: Gift Cards REEDEM | G12: 144800 | H12: 28841 | I12: 5.1
C13: 12 | D13: POS Data Upload Sabretooth | E13: Uber | F13: UBD | G13: 122000 | H13: 28841 | I13: 46.78
C14: 13 | D14: POS Data Upload Sabretooth | E14: DoorDash | F14: DDD | G14: 123000 | H14: 28841 | I14: 706.33
C15: 14 | D15: POS Data Upload Sabretooth | E15: Gross Food Sales | G15: 400200 | H15: 28842 | J15: 6973.73
C16: 15 | D16: POS Data Upload Sabretooth | E16: Discounts -Employee meals | G16: 410000 | H16: 28842 | I16: 202.13
C17: 16 | D17: POS Data Upload Sabretooth | E17: Sales Tax Payable | G17: 222000 | H17: 28842 | J17: 567.13
C18: 17 | D18: POS Data Upload Sabretooth | E18: Non Taxable Sales | G18: 400201 | H18: 28842 | J18: 137.43
C19: 18 | D19: POS Data Upload Sabretooth | E19: Donations | G19: 212000 | H19: 28842 | J19: 37.8
C20: 19 | D20: POS Data Upload Sabretooth | E20: Cash Expected Deposit | G20: 101900 | H20: 28842 | I20: 1108.08
C21: 20 | D21: POS Data Upload Sabretooth | E21: Credit Cards Expected Deposit | G21: 111200 | H21: 28842 | I21: 5324.52
C22: 21 | D22: POS Data Upload Sabretooth | E22: AMEX Expected Deposit | G22: 111200 | H22: 28842 | I22: 113.84
C23: 22 | D23: POS Data Upload Sabretooth | E23: Gift Cards REEDEM | G23: 144800 | H23: 28842 | I23: 9.4
C24: 23 | D24: POS Data Upload Sabretooth | E24: Uber | F24: UBD | G24: 122000 | H24: 28842 | I24: 137.43
C25: 24 | D25: POS Data Upload Sabretooth | E25: DoorDash | F25: DDD | G25: 123000 | H25: 28842 | I25: 820.69
C26: 25 | D26: POS Data Upload Sabretooth | E26: Gross Food Sales | G26: 400200 | H26: 28843 | J26: 5473.4
C27: 26 | D27: POS Data Upload Sabretooth | E27: Discounts -Employee meals | G27: 410000 | H27: 28843 | I27: 164.27
C28: 27 | D28: POS Data Upload Sabretooth | E28: Sales Tax Payable | G28: 222000 | H28: 28843 | J28: 482.66
C29: 28 | D29: POS Data Upload Sabretooth | E29: Non Taxable Sales | G29: 400201 | H29: 28843 | J29: 85.76
C30: 29 | D30: POS Data Upload Sabretooth | E30: Donations | G30: 212000 | H30: 28843 | J30: 22.89
C31: 30 | D31: POS Data Upload Sabretooth | E31: Credit Cards Expected Deposit | G31: 111200 | H31: 28843 | I31: 3809.79
C32: 31 | D32: POS Data Upload Sabretooth | E32: AMEX Expected Deposit | G32: 111200 | H32: 28843 | I32: 131.52
C33: 32 | D33: POS Data Upload Sabretooth | E33: GrubHub | F33: GHD | G33: 124000 | H33: 28843 | I33: 27.42
C34: 33 | D34: POS Data Upload Sabretooth | E34: Uber | F34: UBD | G34: 122000 | H34: 28843 | I34: 85.76
C35: 34 | D35: POS Data Upload Sabretooth | E35: DoorDash | F35: DDD | G35: 123000 | H35: 28843 | I35: 672.5
C36: 35 | D36: POS Data Upload Sabretooth | E36: Gross Food Sales | G36: 400200 | H36: 28844 | J36: 10252.94
C37: 36 | D37: POS Data Upload Sabretooth | E37: Discounts -Employee meals | G37: 410000 | H37: 28844 | I37: 315.18
C38: 37 | D38: POS Data Upload Sabretooth | E38: Sales Tax Payable | G38: 222000 | H38: 28844 | J38: 794.81
C39: 38 | D39: POS Data Upload Sabretooth | E39: Non Taxable Sales | G39: 400201 | H39: 28844 | J39: 112.4
C40: 39 | D40: POS Data Upload Sabretooth | E40: Donations | G40: 212000 | H40: 28844 | J40: 34.64
C41: 40 | D41: POS Data Upload Sabretooth | E41: Credit Cards Expected Deposit | G41: 111200 | H41: 28844 | I41: 6989.31
C42: 41 | D42: POS Data Upload Sabretooth | E42: AMEX Expected Deposit | G42: 111200 | H42: 28844 | I42: 38.59
C43: 42 | D43: POS Data Upload Sabretooth | E43: Gift Cards REEDEM | G43: 144800 | H43: 28844 | I43: 39.25
C44: 43 | D44: POS Data Upload Sabretooth | E44: Uber | F44: UBD | G44: 122000 | H44: 28844 | I44: 112.4
C45: 44 | D45: POS Data Upload Sabretooth | E45: DoorDash | F45: DDD | G45: 123000 | H45: 28844 | I45: 1057.01
C46: 45 | D46: POS Data Upload Sabretooth | E46: Gross Food Sales | G46: 400200 | H46: 28845 | J46: 9879.26
C47: 46 | D47: POS Data Upload Sabretooth | E47: Discounts -Employee meals | G47: 410000 | H47: 28845 | I47: 298.4
C48: 47 | D48: POS Data Upload Sabretooth | E48: Sales Tax Payable | G48: 222000 | H48: 28845 | J48: 776.16
C49: 48 | D49: POS Data Upload Sabretooth | E49: Non Taxable Sales | G49: 400201 | H49: 28845 | J49: 105.07
C50: 49 | D50: POS Data Upload Sabretooth | E50: Donations | G50: 212000 | H50: 28845 | J50: 24.73
C51: 50 | D51: POS Data Upload Sabretooth | E51: Gift Cards SOLD | G51: 115000 | H51: 28845 | J51: 10
C52: 51 | D52: POS Data Upload Sabretooth | E52: Credit Cards Expected Deposit | G52: 111200 | H52: 28845 | I52: 7032.02
C53: 52 | D53: POS Data Upload Sabretooth | E53: AMEX Expected Deposit | G53: 111200 | H53: 28845 | I53: 349.48
C54: 53 | D54: POS Data Upload Sabretooth | E54: Gift Cards REEDEM | G54: 144800 | H54: 28845 | I54: 26.25
C55: 54 | D55: POS Data Upload Sabretooth | E55: GrubHub | F55: GHD | G55: 124000 | H55: 28845 | I55: 90.74
C56: 55 | D56: POS Data Upload Sabretooth | E56: Uber | F56: UBD | G56: 122000 | H56: 28845 | I56: 105.07
C57: 56 | D57: POS Data Upload Sabretooth | E57: DoorDash | F57: DDD | G57: 123000 | H57: 28845 | I57: 1703.9
C58: 57 | D58: POS Data Upload Sabretooth | E58: Gross Food Sales | G58: 400200 | H58: 28846 | J58: 7855.45
C59: 58 | D59: POS Data Upload Sabretooth | E59: Discounts -Employee meals | G59: 410000 | H59: 28846 | I59: 238
C60: 59 | D60: POS Data Upload Sabretooth | E60: Sales Tax Payable | G60: 222000 | H60: 28846 | J60: 628.61
C61: 60 | D61: POS Data Upload Sabretooth | E61: Non Taxable Sales | G61: 400201 | H61: 28846 | J61: 302.7
C62: 61 | D62: POS Data Upload Sabretooth | E62: Donations | G62: 212000 | H62: 28846 | J62: 27.83
C63: 62 | D63: POS Data Upload Sabretooth | E63: Credit Cards Expected Deposit | G63: 111200 | H63: 28846 | I63: 4925.43
C64: 63 | D64: POS Data Upload Sabretooth | E64: AMEX Expected Deposit | G64: 111200 | H64: 28846 | I64: 75.28
C65: 64 | D65: POS Data Upload Sabretooth | E65: Gift Cards REEDEM | G65: 144800 | H65: 28846 | I65: 9.72
C66: 65 | D66: POS Data Upload Sabretooth | E66: GrubHub | F66: GHD | G66: 124000 | H66: 28846 | I66: 37.79
C67: 66 | D67: POS Data Upload Sabretooth | E67: Uber | F67: UBD | G67: 122000 | H67: 28846 | I67: 302.7
C68: 67 | D68: POS Data Upload Sabretooth | E68: DoorDash | F68: DDD | G68: 123000 | H68: 28846 | I68: 1625.87
C69: 68 | D69: POS Data Upload Sabretooth | E69: Gross Food Sales | G69: 400200 | H69: 29423 | J69: 4491.12
C70: 69 | D70: POS Data Upload Sabretooth | E70: Discounts -Employee meals | G70: 410000 | H70: 29423 | I70: 70.6
C71: 70 | D71: POS Data Upload Sabretooth | E71: Sales Tax Payable | G71: 222000 | H71: 29423 | J71: 364.8
C72: 71 | D72: POS Data Upload Sabretooth | E72: Non Taxable Sales | G72: 400201 | H72: 29423 | J72: 16.75
C73: 72 | D73: POS Data Upload Sabretooth | E73: Donations | G73: 212000 | H73: 29423 | J73: 13.8
C74: 73 | D74: POS Data Upload Sabretooth | E74: Cash Expected Deposit | G74: 101900 | H74: 29423 | I74: 1172.5
C75: 74 | D75: POS Data Upload Sabretooth | E75: Credit Cards Expected Deposit | G75: 111200 | H75: 29423 | I75: 3441.48
C76: 75 | D76: POS Data Upload Sabretooth | E76: AMEX Expected Deposit | G76: 111200 | H76: 29423 | I76: 62.52
C77: 76 | D77: POS Data Upload Sabretooth | E77: Uber | F77: UBD | G77: 122000 | H77: 29423 | I77: 16.75
C78: 77 | D78: POS Data Upload Sabretooth | E78: DoorDash | F78: DDD | G78: 123000 | H78: 29423 | I78: 122.62
C79: 78 | D79: POS Data Upload Sabretooth | E79: Gross Food Sales | G79: 400200 | H79: 30256 | J79: 5861.52
C80: 79 | D80: POS Data Upload Sabretooth | E80: Discounts -Employee meals | G80: 410000 | H80: 30256 | I80: 124.31
C81: 80 | D81: POS Data Upload Sabretooth | E81: Sales Tax Payable | G81: 222000 | H81: 30256 | J81: 463.5
C82: 81 | D82: POS Data Upload Sabretooth | E82: Non Taxable Sales | G82: 400201 | H82: 30256 | J82: 52.28
C83: 82 | D83: POS Data Upload Sabretooth | E83: Donations | G83: 212000 | H83: 30256 | J83: 16.43
C84: 83 | D84: POS Data Upload Sabretooth | E84: Credit Cards Expected Deposit | G84: 111200 | H84: 30256 | I84: 4397.33
C85: 84 | D85: POS Data Upload Sabretooth | E85: AMEX Expected Deposit | G85: 111200 | H85: 30256 | I85: 199.38
C86: 85 | D86: POS Data Upload Sabretooth | E86: Uber | F86: UBD | G86: 122000 | H86: 30256 | I86: 52.28
C87: 86 | D87: POS Data Upload Sabretooth | E87: DoorDash | F87: DDD | G87: 123000 | H87: 30256 | I87: 542.43
C88: 87 | D88: POS Data Upload Sabretooth | E88: Gross Food Sales | G88: 400200 | H88: 30491 | J88: 4656.88
C89: 88 | D89: POS Data Upload Sabretooth | E89: Discounts -Employee meals | G89: 410000 | H89: 30491 | I89: 201.65
C90: 89 | D90: POS Data Upload Sabretooth | E90: Sales Tax Payable | G90: 222000 | H90: 30491 | J90: 389.13
C91: 90 | D91: POS Data Upload Sabretooth | E91: Donations | G91: 212000 | H91: 30491 | J91: 28.2
C92: 91 | D92: POS Data Upload Sabretooth | E92: Credit Cards Expected Deposit | G92: 111200 | H92: 30491 | I92: 3668.51
C93: 92 | D93: POS Data Upload Sabretooth | E93: AMEX Expected Deposit | G93: 111200 | H93: 30491 | I93: 186.03
C94: 93 | D94: POS Data Upload Sabretooth | E94: Gift Cards REEDEM | G94: 144800 | H94: 30491 | I94: 36.6
C95: 94 | D95: POS Data Upload Sabretooth | E95: DoorDash | F95: DDD | G95: 123000 | H95: 30491 | I95: 87.27
C96: 95 | D96: POS Data Upload Sabretooth | E96: Gross Food Sales | G96: 400200 | H96: 32680 | J96: 5279.46
C97: 96 | D97: POS Data Upload Sabretooth | E97: Discounts -Employee meals | G97: 410000 | H97: 32680 | I97: 199.74
C98: 97 | D98: POS Data Upload Sabretooth | E98: Coupons - Promotions | G98: 410000 | H98: 32680 | I98: 3.69
C99: 98 | D99: POS Data Upload Sabretooth | E99: Sales Tax Payable | G99: 222000 | H99: 32680 | J99: 418.82
C100: 99 | D100: POS Data Upload Sabretooth | E100: Non Taxable Sales | G100: 400201 | H100: 32680 | J100: 10.98
...

Sheet Daily Sales Taco Bell 03-10 202
A1: JOURNAL | B1: DATE | C1: LINE_NO | D1: DESCRIPTION | E1: MEMO | F1: DEPT_ID | G1: ACCT_NO | H1: LOCATION_ID | I1: DEBIT | J1: CREDIT
A2: SJ | B2: ='Daily Sales Taco Bell 03-14 202'!B2 -> 05/26/2026 | C2: {=_xlfn.SEQUENCE(ROWS(_xlfn.ANCHORARRAY(D2)))} -> 1 | D2: {=IF(ISBLANK(_xlfn._xlws.SORT(_xlfn._xlws.FILTER('Statistical Delivery'!D:K,(('Statistical Delivery'!I:I<>0)+('Statistical Delivery'!J:J<>0))),5,-1,FALSE)),"",_xlfn._xlws.SORT(_xlfn._xlws.FILTER('Statistical Delivery'!D:K,(('Statistical Delivery'!I:I<>0)+('Statistical Delivery'!J:J<>0))),5,-1,FALSE))} -> Statistical Delivery Sales | E2: Statistical Delivery Sales | G2: 990300 | H2: 40404 | I2: 413.14
C3: 2 | D3: Statistical Delivery Sales | E3: Statistical Delivery Sales | G3: 990301 | H3: 40404 | J3: 413.14
C4: 3 | D4: Statistical Delivery Sales | E4: Statistical Delivery Sales | G4: 990200 | H4: 40404 | I4: 272.1
C5: 4 | D5: Statistical Delivery Sales | E5: Statistical Delivery Sales | G5: 990201 | H5: 40404 | J5: 272.1
C6: 5 | D6: Statistical Delivery Sales | E6: Statistical Delivery Sales | G6: 990100 | H6: 40404 | I6: 37.25
C7: 6 | D7: Statistical Delivery Sales | E7: Statistical Delivery Sales | G7: 990101 | H7: 40404 | J7: 37.25
C8: 7 | D8: Statistical Delivery Sales | E8: Statistical Delivery Sales | G8: 990300 | H8: 37732 | I8: 762.25
C9: 8 | D9: Statistical Delivery Sales | E9: Statistical Delivery Sales | G9: 990301 | H9: 37732 | J9: 762.25
C10: 9 | D10: Statistical Delivery Sales | E10: Statistical Delivery Sales | G10: 990200 | H10: 37732 | I10: 51.33
C11: 10 | D11: Statistical Delivery Sales | E11: Statistical Delivery Sales | G11: 990201 | H11: 37732 | J11: 51.33
C12: 11 | D12: Statistical Delivery Sales | E12: Statistical Delivery Sales | G12: 990100 | H12: 37732 | I12: 19.14
C13: 12 | D13: Statistical Delivery Sales | E13: Statistical Delivery Sales | G13: 990101 | H13: 37732 | J13: 19.14
C14: 13 | D14: Statistical Delivery Sales | E14: Statistical Delivery Sales | G14: 990300 | H14: 37718 | I14: 189.27
C15: 14 | D15: Statistical Delivery Sales | E15: Statistical Delivery Sales | G15: 990301 | H15: 37718 | J15: 189.27
C16: 15 | D16: Statistical Delivery Sales | E16: Statistical Delivery Sales | G16: 990200 | H16: 37718 | I16: 12.43
C17: 16 | D17: Statistical Delivery Sales | E17: Statistical Delivery Sales | G17: 990201 | H17: 37718 | J17: 12.43
C18: 17 | D18: Statistical Delivery Sales | E18: Statistical Delivery Sales | G18: 990300 | H18: 37171 | I18: 165.84
C19: 18 | D19: Statistical Delivery Sales | E19: Statistical Delivery Sales | G19: 990301 | H19: 37171 | J19: 165.84
C20: 19 | D20: Statistical Delivery Sales | E20: Statistical Delivery Sales | G20: 990200 | H20: 37171 | I20: 91.49
C21: 20 | D21: Statistical Delivery Sales | E21: Statistical Delivery Sales | G21: 990201 | H21: 37171 | J21: 91.49
C22: 21 | D22: Statistical Delivery Sales | E22: Statistical Delivery Sales | G22: 990300 | H22: 36224 | I22: 565.67
C23: 22 | D23: Statistical Delivery Sales | E23: Statistical Delivery Sales | G23: 990301 | H23: 36224 | J23: 565.67
C24: 23 | D24: Statistical Delivery Sales | E24: Statistical Delivery Sales | G24: 990200 | H24: 36224 | I24: 56.33
C25: 24 | D25: Statistical Delivery Sales | E25: Statistical Delivery Sales | G25: 990201 | H25: 36224 | J25: 56.33
C26: 25 | D26: Statistical Delivery Sales | E26: Statistical Delivery Sales | G26: 990100 | H26: 36224 | I26: 50.37
C27: 26 | D27: Statistical Delivery Sales | E27: Statistical Delivery Sales | G27: 990101 | H27: 36224 | J27: 50.37
C28: 27 | D28: Statistical Delivery Sales | E28: Statistical Delivery Sales | G28: 990300 | H28: 34793 | I28: 48.95
C29: 28 | D29: Statistical Delivery Sales | E29: Statistical Delivery Sales | G29: 990301 | H29: 34793 | J29: 48.95
C30: 29 | D30: Statistical Delivery Sales | E30: Statistical Delivery Sales | G30: 990200 | H30: 34793 | I30: 69.75
C31: 30 | D31: Statistical Delivery Sales | E31: Statistical Delivery Sales | G31: 990201 | H31: 34793 | J31: 69.75
C32: 31 | D32: Statistical Delivery Sales | E32: Statistical Delivery Sales | G32: 990300 | H32: 32952 | I32: 215.73
C33: 32 | D33: Statistical Delivery Sales | E33: Statistical Delivery Sales | G33: 990301 | H33: 32952 | J33: 215.73
C34: 33 | D34: Statistical Delivery Sales | E34: Statistical Delivery Sales | G34: 990200 | H34: 32952 | I34: 58.86
C35: 34 | D35: Statistical Delivery Sales | E35: Statistical Delivery Sales | G35: 990201 | H35: 32952 | J35: 58.86
C36: 35 | D36: Statistical Delivery Sales | E36: Statistical Delivery Sales | G36: 990300 | H36: 32951 | I36: 922.13
C37: 36 | D37: Statistical Delivery Sales | E37: Statistical Delivery Sales | G37: 990301 | H37: 32951 | J37: 922.13
C38: 37 | D38: Statistical Delivery Sales | E38: Statistical Delivery Sales | G38: 990200 | H38: 32951 | I38: 720.5
C39: 38 | D39: Statistical Delivery Sales | E39: Statistical Delivery Sales | G39: 990201 | H39: 32951 | J39: 720.5
C40: 39 | D40: Statistical Delivery Sales | E40: Statistical Delivery Sales | G40: 990100 | H40: 32951 | I40: 75.6
C41: 40 | D41: Statistical Delivery Sales | E41: Statistical Delivery Sales | G41: 990101 | H41: 32951 | J41: 75.6
C42: 41 | D42: Statistical Delivery Sales | E42: Statistical Delivery Sales | G42: 990300 | H42: 32950 | I42: 687.29
C43: 42 | D43: Statistical Delivery Sales | E43: Statistical Delivery Sales | G43: 990301 | H43: 32950 | J43: 687.29
C44: 43 | D44: Statistical Delivery Sales | E44: Statistical Delivery Sales | G44: 990200 | H44: 32950 | I44: 362.68
C45: 44 | D45: Statistical Delivery Sales | E45: Statistical Delivery Sales | G45: 990201 | H45: 32950 | J45: 362.68
C46: 45 | D46: Statistical Delivery Sales | E46: Statistical Delivery Sales | G46: 990100 | H46: 32950 | I46: 265.5
C47: 46 | D47: Statistical Delivery Sales | E47: Statistical Delivery Sales | G47: 990101 | H47: 32950 | J47: 265.5
C48: 47 | D48: Statistical Delivery Sales | E48: Statistical Delivery Sales | G48: 990300 | H48: 32949 | I48: 585.21
C49: 48 | D49: Statistical Delivery Sales | E49: Statistical Delivery Sales | G49: 990301 | H49: 32949 | J49: 585.21
C50: 49 | D50: Statistical Delivery Sales | E50: Statistical Delivery Sales | G50: 990200 | H50: 32949 | I50: 283.31
C51: 50 | D51: Statistical Delivery Sales | E51: Statistical Delivery Sales | G51: 990201 | H51: 32949 | J51: 283.31
C52: 51 | D52: Statistical Delivery Sales | E52: Statistical Delivery Sales | G52: 990100 | H52: 32949 | I52: 136.62
C53: 52 | D53: Statistical Delivery Sales | E53: Statistical Delivery Sales | G53: 990101 | H53: 32949 | J53: 136.62
C54: 53 | D54: Statistical Delivery Sales | E54: Statistical Delivery Sales | G54: 990300 | H54: 32948 | I54: 684.08
C55: 54 | D55: Statistical Delivery Sales | E55: Statistical Delivery Sales | G55: 990301 | H55: 32948 | J55: 684.08
C56: 55 | D56: Statistical Delivery Sales | E56: Statistical Delivery Sales | G56: 990200 | H56: 32948 | I56: 193.85
C57: 56 | D57: Statistical Delivery Sales | E57: Statistical Delivery Sales | G57: 990201 | H57: 32948 | J57: 193.85
C58: 57 | D58: Statistical Delivery Sales | E58: Statistical Delivery Sales | G58: 990100 | H58: 32948 | I58: 28.44
C59: 58 | D59: Statistical Delivery Sales | E59: Statistical Delivery Sales | G59: 990101 | H59: 32948 | J59: 28.44
C60: 59 | D60: Statistical Delivery Sales | E60: Statistical Delivery Sales | G60: 990300 | H60: 32947 | I60: 555.62
C61: 60 | D61: Statistical Delivery Sales | E61: Statistical Delivery Sales | G61: 990301 | H61: 32947 | J61: 555.62
C62: 61 | D62: Statistical Delivery Sales | E62: Statistical Delivery Sales | G62: 990200 | H62: 32947 | I62: 450.31
C63: 62 | D63: Statistical Delivery Sales | E63: Statistical Delivery Sales | G63: 990201 | H63: 32947 | J63: 450.31
C64: 63 | D64: Statistical Delivery Sales | E64: Statistical Delivery Sales | G64: 990100 | H64: 32947 | I64: 48.09
C65: 64 | D65: Statistical Delivery Sales | E65: Statistical Delivery Sales | G65: 990101 | H65: 32947 | J65: 48.09
C66: 65 | D66: Statistical Delivery Sales | E66: Statistical Delivery Sales | G66: 990300 | H66: 32946 | I66: 720.4
C67: 66 | D67: Statistical Delivery Sales | E67: Statistical Delivery Sales | G67: 990301 | H67: 32946 | J67: 720.4
C68: 67 | D68: Statistical Delivery Sales | E68: Statistical Delivery Sales | G68: 990200 | H68: 32946 | I68: 630.53
C69: 68 | D69: Statistical Delivery Sales | E69: Statistical Delivery Sales | G69: 990201 | H69: 32946 | J69: 630.53
C70: 69 | D70: Statistical Delivery Sales | E70: Statistical Delivery Sales | G70: 990100 | H70: 32946 | I70: 108.78
C71: 70 | D71: Statistical Delivery Sales | E71: Statistical Delivery Sales | G71: 990101 | H71: 32946 | J71: 108.78
C72: 71 | D72: Statistical Delivery Sales | E72: Statistical Delivery Sales | G72: 990300 | H72: 32945 | I72: 895.13
C73: 72 | D73: Statistical Delivery Sales | E73: Statistical Delivery Sales | G73: 990301 | H73: 32945 | J73: 895.13
C74: 73 | D74: Statistical Delivery Sales | E74: Statistical Delivery Sales | G74: 990200 | H74: 32945 | I74: 516.68
C75: 74 | D75: Statistical Delivery Sales | E75: Statistical Delivery Sales | G75: 990201 | H75: 32945 | J75: 516.68
C76: 75 | D76: Statistical Delivery Sales | E76: Statistical Delivery Sales | G76: 990100 | H76: 32945 | I76: 108.49
C77: 76 | D77: Statistical Delivery Sales | E77: Statistical Delivery Sales | G77: 990101 | H77: 32945 | J77: 108.49
C78: 77 | D78: Statistical Delivery Sales | E78: Statistical Delivery Sales | G78: 990300 | H78: 32944 | I78: 1334.44
C79: 78 | D79: Statistical Delivery Sales | E79: Statistical Delivery Sales | G79: 990301 | H79: 32944 | J79: 1334.44
C80: 79 | D80: Statistical Delivery Sales | E80: Statistical Delivery Sales | G80: 990200 | H80: 32944 | I80: 1383.04
C81: 80 | D81: Statistical Delivery Sales | E81: Statistical Delivery Sales | G81: 990201 | H81: 32944 | J81: 1383.04
C82: 81 | D82: Statistical Delivery Sales | E82: Statistical Delivery Sales | G82: 990100 | H82: 32944 | I82: 435.86
C83: 82 | D83: Statistical Delivery Sales | E83: Statistical Delivery Sales | G83: 990101 | H83: 32944 | J83: 435.86
C84: 83 | D84: Statistical Delivery Sales | E84: Statistical Delivery Sales | G84: 990300 | H84: 32943 | I84: 1662.94
C85: 84 | D85: Statistical Delivery Sales | E85: Statistical Delivery Sales | G85: 990301 | H85: 32943 | J85: 1662.94
C86: 85 | D86: Statistical Delivery Sales | E86: Statistical Delivery Sales | G86: 990200 | H86: 32943 | I86: 867.32
C87: 86 | D87: Statistical Delivery Sales | E87: Statistical Delivery Sales | G87: 990201 | H87: 32943 | J87: 867.32
C88: 87 | D88: Statistical Delivery Sales | E88: Statistical Delivery Sales | G88: 990100 | H88: 32943 | I88: 125.88
C89: 88 | D89: Statistical Delivery Sales | E89: Statistical Delivery Sales | G89: 990101 | H89: 32943 | J89: 125.88
C90: 89 | D90: Statistical Delivery Sales | E90: Statistical Delivery Sales | G90: 990300 | H90: 32942 | I90: 577.52
C91: 90 | D91: Statistical Delivery Sales | E91: Statistical Delivery Sales | G91: 990301 | H91: 32942 | J91: 577.52
C92: 91 | D92: Statistical Delivery Sales | E92: Statistical Delivery Sales | G92: 990200 | H92: 32942 | I92: 183.84
C93: 92 | D93: Statistical Delivery Sales | E93: Statistical Delivery Sales | G93: 990201 | H93: 32942 | J93: 183.84
C94: 93 | D94: Statistical Delivery Sales | E94: Statistical Delivery Sales | G94: 990100 | H94: 32942 | I94: 114.83
C95: 94 | D95: Statistical Delivery Sales | E95: Statistical Delivery Sales | G95: 990101 | H95: 32942 | J95: 114.83
C96: 95 | D96: Statistical Delivery Sales | E96: Statistical Delivery Sales | G96: 990300 | H96: 32941 | I96: 904.4
C97: 96 | D97: Statistical Delivery Sales | E97: Statistical Delivery Sales | G97: 990301 | H97: 32941 | J97: 904.4
C98: 97 | D98: Statistical Delivery Sales | E98: Statistical Delivery Sales | G98: 990200 | H98: 32941 | I98: 778.21
C99: 98 | D99: Statistical Delivery Sales | E99: Statistical Delivery Sales | G99: 990201 | H99: 32941 | J99: 778.21
C100: 99 | D100: Statistical Delivery Sales | E100: Statistical Delivery Sales | G100: 990100 | H100: 32941 | I100: 176.61
...
